Workbook

Sheet Country Overview
C1: Regulated | D1: Regulated/ if fitted
C2: Mandatory | D2: Mandatory fitment
C3: in drafting | D3: Pending document (Regulation under drafting stage)
C4: - | D4: Not Regulated/ to be considered
E5: GLOBAL | F5: ​Europe | AY5: North America | BB5: South America | CI5: Asia & Pacific | CN5: ASEAN | DX5: ​CIS (Commonwealth of Independent States) & EAEU (Eurasion Economic Union) | EJ5: Africa | GC5: Arab States
A6: Vehicle Category | B6: Category | C6: Acronym/ Scope | D6: Regulated Functions | E6: UN 1958 Agreement (UN Regulation 0 Whole Vehicle Type Approval) | F6: Main countries European Union (Germany, France,..) Swiss UK Turkey (Israel) | G6: Switzerland | H6: United Kingdom | I6: Turkey | J6: Israel | K6: Germany | L6: Andorra | M6: Austria | N6: Albania | O6: Belgium | P6: Bosnia and Herzegovina | Q6: Bulgaria | R6: Croatia | S6: Cyprus | T6: Czech Republic | U6: Denmark | V6: Estonia | W6: Finland | X6: France | Y6: Georgia | Z6: Greece | AA6: Hungary | AB6: Iceland | AC6: Ireland | AD6: Italy | AE6: Latvia | AF6: Liechtenstein | AG6: Lithuania | AH6: Luxembourg | AI6: Malta | AJ6: Monaco | AK6: Montenegro | AL6: Netherlands | AM6: Norway | AN6: Poland | AO6: Portugal | AP6: Romania | AQ6: San Marino | AR6: Serbia | AS6: Slovakia | AT6: Slovenia | AU6: Spain | AV6: Sweden | AW6: The Former Yugoslav Rep. of Macedonia | AX6: Vatican | AY6: Main countries USA (displayed) Canada partly applies UN] | AZ6: United States | BA6: Canada | BB6: Main countries Brazil Mexico (UN and FMVSS) | BC6: Brazil | BD6: Colombia UN 1958 agreement member (in application process) | BE6: Mexico | BF6: Antigua and Barbuda | BG6: Bahamas | BH6: Barbados | BI6: Belize | BJ6: Bolivia (Plurinational State of) | BK6: Chile | BL6: Costa Rica | BM6: Cuba | BN6: Dominica | BO6: Dominican Rep. | BP6: Ecuador | BQ6: El Salvador | BR6: Grenada | BS6: Guatemala | BT6: Guyana | BU6: Haiti | BV6: Honduras | BW6: Jamaica | BX6: Nicaragua | BY6: Panama | BZ6: Paraguay | CA6: Peru | CB6: Saint Kitts and Nevis | CC6: Saint Lucia | CD6: Saint Vincent and the Grenadines | CE6: Suriname | CF6: Trinidad and Tobago | CG6: Uruguay | CH6: Venezuela | CI6: China | CJ6: Hong Kong (China) | CK6: India | CL6: Japan (UN 1958) | CM6: Korea (Rep. of) (UN 1958) | CN6: Main countries Indonesia Thailand (UN 1958) Philippines Malaysia (UN 1958) | CO6: Taiwan (China) | CP6: Thailand | CQ6: Indonesia | CR6: Malaysia | CS6: Philippines | CT6: Singapore | CU6: Afghanistan | CV6: Bangladesh | CW6: Bhutan | CX6: Brunei Darussalam | CY6: Cambodia | CZ6: Fiji | DA6: Iran (Islamic Republic of) | DB6: Kiribati | DC6: Lao P.D.R. | DD6: Macau (China) | DE6: Maldives | DF6: Marshall Islands | DG6: Micronesia | DH6: Mongolia | DI6: Myanmar | DJ6: Nauru | DK6: Nepal (Republic of) | DL6: New Zealand | DM6: Pakistan | DN6: Papua New Guinea | DO6: Samoa | DP6: Solomon Islands | DQ6: Sri Lanka | DR6: Timor-Leste | DS6: Tonga | DT6: Tuvalu | DU6: Vanuatu | DV6: Viet Nam | DW6: Australia (UN 1958) AU_ADR_Harmonisation_EN_2022-04-04 (1).pdf | DX6: Main countires EAEU Russia (UN 1958) Ukraine | DY6: Armenia | DZ6: Azerbaijan | EA6: Belarus | EB6: Kazakhstan | EC6: Kyrgyzstan | ED6: Moldova | EE6: Russian Federation | EF6: Tajikistan | EG6: Turkmenistan | EH6: Ukraine | EI6: Uzbekistan | EJ6: Main countries South Africa (UN 1958) Namibia Nigeria | EK6: South Africa | EL6: Namibia | EM6: Nigeria | EN6: Angola | EO6: Benin | EP6: Botswana | EQ6: Burkina Faso | ER6: Burundi | ES6: Cameroon | ET6: Cabo Verde | EU6: Central African Rep. | EV6: Chad | EW6: Congo (Rep. of the) | EX6: Côte d'Ivoire | EY6: Dem. Rep. of the Congo) | EZ6: Equatorial Guinea | FA6: Eritrea | FB6: Eswatini | FC6: Ethiopia | FD6: Gabon | FE6: Gambia | FF6: Ghana | FG6: Guinea | FH6: Guinea-Bissau | FI6: Kenya | FJ6: Lesotho | FK6: Liberia | FL6: Madagascar | FM6: Malawi | FN6: Mali | FO6: Mauritius | FP6: Mozambique | FQ6: Niger | FR6: Rwanda | FS6: Sao Tome and Principe | FT6: Senegal | FU6: Seychelles | FV6: Sierra Leone | FW6: South Sudan | FX6: Tanzania | FY6: Togo | FZ6: Uganda | GA6: Zambia | GB6: Zimbabwe | GC6: Main countries Egypt (UN 1958) Saudi Arabia Oman Morocco Lebanon | GD6: Egypt | GE6: Saudi Arabia | GF6: Oman | GG6: Morocco | GH6: Lebanon | GI6: Jordan | GJ6: Algeria | GK6: Bahrain | GL6: Comoros | GM6: Djibouti | GN6: Iraq | GO6: Kuwait | GP6: Libya | GQ6: Mauritania | GR6: Qatar | GS6: Somalia | GT6: Sudan | GU6: Syrian Arab Republic | GV6: Tunisia | GW6: United Arab Emirates | GX6: Yemen | GY6: United Arab Emirates | GZ6: Yemen
B7: Framework Regulation (defining mandatory systems) | E7: UN Regulation No. 0 | F7: (EU) 2019/2144 | AY7: FMVSS CMVSS | BC7: BR_Decree_9557-2018_Rota_2030_EN_2019-03-04 (1).pdf | BD7: CO_Res_20223040044585-2022_EN_2025-10-09.pdf | BE7: MX_NOM-194-SE-2021_EN_2023-04-14.pdf | CK7: CMVR
BC8: BR_Port_SENATRAN_1554-2022_EN_2023-01-17.pdf
B9: CATEGORY M1 & N1
A10: M1 & N1 | B10: Warning/ emergency / Assisting features level 0-1
B11: Generic Regulations | D11: Framework regulations/ Type Approvals/ General Safety Regulations | CM11: KR_KMVSS_complete_corr_EN_2022-02-15.pdf
B12: Long. Control | C12: AEB | D12: Advanced Emergency Braking (includes FCW) | E12: UN R152 | F12: UN R152 | G12: Mandatory | H12: Mandatory | I12: Mandatory | J12: Mandatory | AY12: FMVSS 127 Mandatory by 2029 | AZ12: FMVSS 127 | BA12: - | BB12: UN R152 | BC12: UN R152 | BD12: UN R152 mandatory by 08/2027 all models by 08/2029 | BE12: UN R152 | CI12: !! GB/T 39901 (in process of being made mandatory with updated requirements 2028 (only for M1) | CK12: Regulated (2026) AIS-185 (M1 & N1) | CL12: UN R152 | CM12: KMVSS Article 90-3 M1/N1 = UN R152 | CN12: UN R152 | DW12: UN R152/ ADR98 | DX12: =E12 -> UN R152 | EJ12: =E12 -> UN R152 | GC12: =E12 -> UN R152
C13: AEB VRU | D13: Advanced Emergency Braking for VRU (pedestrian & Cyclists) | E13: UN R152 | F13: UN R152 | G13: Mandatory | H13: Mandatory | I13: Mandatory | J13: Mandatory | AY13: FMVSS 127 Mandatory by 2029 | AZ13: FMVSS 127 | BA13: - | BB13: UN R152 (pedestrians) | BC13: UN R152 (pedestrians) | BD13: UN R152 mandatory by 08/2027 all models by 08/2029 | BE13: UN R152 | CI13: in drafting | CK13: Regulated (2026) AIS-185 (M1 & N1) | CL13: UN R152 | CM13: KMVSS Article 90-3 M1/N1 = UN R152 | CN13: UN R152 | DW13: UN R152/ ADR98 | DX13: =E13 -> UN R152 | EJ13: =E13 -> UN R152 | GC13: =E13 -> UN R152
C14: R-AEB | D14: Rear Advanced Emergency Braking | E14: - | F14: UN R13H (M1) | AY14: - | AZ14: NCAP | BA14: - | BB14: - | BC14: - | BD14: - | BE14: - | CI14: GB 21670-2008 | CK14: IS 15986-2015 AIS-151 | CL14: - | CM14: - | CN14: - | DW14: =E14 -> - | DX14: =E14 -> - | EJ14: =E14 -> - | GC14: =E14 -> -
C15: TSR (ISA) | D15: Traffic Sign Recognition (Intelligent Speed Assistance) | E15: - | F15: (EU) 2021/1958 | G15: (EU) 2021/1958 | H15: - | I15: (EU) 2021/1958 | J15: EU 2021/1958 + Israel Catalogue Israeli Catalog of Road Signs 2022.pdf | K15: Mandatory | L15: Mandatory | M15: Mandatory | N15: Mandatory | O15: Mandatory | Q15: Mandatory | R15: Mandatory | S15: Mandatory | T15: Mandatory | U15: Mandatory | V15: Mandatory | W15: Mandatory | X15: Mandatory | Y15: Mandatory | Z15: Mandatory | AA15: Mandatory | AB15: Mandatory | AC15: Mandatory | AD15: Mandatory | AE15: Mandatory | AF15: Mandatory | AG15: Mandatory | AH15: Mandatory | AI15: Mandatory | AJ15: Mandatory | AK15: Mandatory | AL15: Mandatory | AM15: Mandatory | AN15: Mandatory | AO15: Mandatory | AP15: Mandatory | AQ15: Mandatory | AR15: - | AS15: Mandatory | AT15: Mandatory | AU15: Mandatory | AV15: Mandatory | AW15: Mandatory | AX15: Mandatory | AY15: - | AZ15: - | BA15: - | BB15: - | BD15: - | BE15: - | CI15: GB/T 44433-2024 | CK15: - | CL15: - | CM15: - | CN15: - | DW15: =E15 -> - | DX15: =E15 -> - | EJ15: =E15 -> - | EK15: =R15 -> Mandatory | EL15: =S15 -> Mandatory | EM15: =T15 -> Mandatory | EN15: =U15 -> Mandatory | EO15: =V15 -> Mandatory | EP15: =W15 -> Mandatory | EQ15: =X15 -> Mandatory | ER15: =Y15 -> Mandatory | ... FU15: =BB15 -> - | FV15: =BC25 -> Res. CONTRAN 970/2022 | FW15: =BD15 -> - | FX15: =BE15 -> - | FY15: =BF15 -> 0 | FZ15: =BG15 -> 0 | GA15: =BH15 -> 0 | GB15: =BI15 -> 0 | GC15: =E15 -> -
C16: ACC | D16: Adaptive Cruise Control | E16: UN R13H ANNEX 8 (General Safety Assessment) | F16: UN R13H ANNEX 8 (General Safety Assessment) | AY16: - | AZ16: - | BA16: - | BB16: - | BF16: NCAP | BG16: NCAP | BH16: NCAP | BI16: NCAP | BJ16: NCAP | BK16: NCAP | BL16: NCAP | BM16: NCAP | BN16: NCAP | BO16: NCAP | BP16: NCAP | BQ16: NCAP | BR16: NCAP | BS16: NCAP | BT16: NCAP | BU16: NCAP | BV16: NCAP | BW16: NCAP | BX16: NCAP | BY16: NCAP | BZ16: NCAP | CA16: NCAP | CB16: NCAP | CC16: NCAP | CD16: NCAP | CE16: NCAP | CF16: NCAP | CG16: NCAP | CH16: NCAP | CI16: GB/T 20608-2006 GB 21670-2008 Annex D | CJ16: NCAP | CK16: - | CL16: UN R13H ANNEX 8 | CM16: UN R13H ANNEX 8 | CN16: UN R13H ANNEX 8 | CO16: NCAP | CP16: NCAP | CQ16: NCAP | CR16: NCAP | CS16: NCAP | CT16: NCAP | CU16: NCAP | CV16: NCAP | CW16: NCAP | CX16: NCAP | CY16: NCAP | CZ16: NCAP | DA16: NCAP | DB16: NCAP | DC16: NCAP | DD16: NCAP | DE16: NCAP | DF16: NCAP | DG16: NCAP | DH16: NCAP | DI16: NCAP | DJ16: NCAP | DK16: NCAP | DL16: NCAP | DM16: NCAP | DN16: NCAP | DO16: NCAP | DP16: NCAP | DQ16: NCAP | DR16: NCAP | DS16: NCAP | DT16: NCAP | DU16: NCAP | DV16: NCAP | DW16: =E16 -> UN R13H ANNEX 8 (General Safety Assessment) | DX16: =E16 -> UN R13H ANNEX 8 (General Safety Assessment) | EJ16: =E16 -> UN R13H ANNEX 8 (General Safety Assessment) | EK16: NCAP | EL16: NCAP | EM16: NCAP | EN16: NCAP | EO16: NCAP | EP16: NCAP | EQ16: NCAP | ER16: NCAP | ES16: NCAP | ET16: NCAP | EU16: NCAP | EV16: NCAP | EW16: NCAP | EX16: NCAP | EY16: NCAP | EZ16: NCAP | FA16: NCAP | FB16: NCAP | FC16: NCAP | FD16: NCAP | FE16: NCAP | FF16: NCAP | FG16: NCAP | FH16: NCAP | FI16: NCAP | FJ16: NCAP | FK16: NCAP | FL16: NCAP | FM16: NCAP | FN16: NCAP | FO16: NCAP | FP16: NCAP | FQ16: NCAP | FR16: NCAP | FS16: NCAP | FT16: NCAP | FU16: NCAP | FV16: NCAP | FW16: NCAP | FX16: NCAP | FY16: NCAP | FZ16: NCAP | GA16: NCAP | GB16: NCAP | GC16: =E16 -> UN R13H ANNEX 8 (General Safety Assessment)
C17: ACPE | D17: Acceleration Control for Pedal Error | E17: UN R175 | F17: UN R175 | G17: in drafting | H17: in drafting | I17: in drafting | J17: in drafting | AY17: - | AZ17: - | BA17: - | BB17: - | BC17: - | BD17: - | BE17: - | CI17: - | CK17: - | CL17: UN R175 | CM17: UN R175 | CN17: UN R175 | DW17: UN R175 | DX17: UN R175 | DY17: UN R175 | DZ17: UN R175 | EA17: UN R175 | EB17: UN R175 | EC17: UN R175 | ED17: UN R175 | EE17: UN R175 | EF17: UN R175 | EG17: UN R175 | EH17: UN R175 | EI17: UN R175 | EJ17: UN R175 | EK17: UN R175 | EL17: UN R175 | EM17: UN R175 | EN17: UN R175 | EO17: UN R175 | EP17: UN R175 | EQ17: UN R175 | ER17: UN R175 | ES17: UN R175 | ET17: UN R175 | EU17: UN R175 | EV17: UN R175 | EW17: UN R175 | EX17: UN R175 | EY17: UN R175 | EZ17: UN R175 | FA17: UN R175 | FB17: UN R175 | FC17: UN R175 | FD17: UN R175 | FE17: UN R175 | FF17: UN R175 | FG17: UN R175 | FH17: UN R175 | FI17: UN R175 | FJ17: UN R175 | FK17: UN R175 | FL17: UN R175 | FM17: UN R175 | FN17: UN R175 | FO17: UN R175 | FP17: UN R175 | FQ17: UN R175 | FR17: UN R175 | FS17: UN R175 | FT17: UN R175 | FU17: UN R175 | FV17: UN R175 | FW17: UN R175 | FX17: UN R175 | FY17: UN R175 | FZ17: UN R175 | GA17: UN R175 | GB17: UN R175 | GC17: UN R175
B18: Lateral Control/ ACSF | C18: LDWS | D18: Lane Departure Warning System | E18: UN R130 | F18: UN R130 | G18: Regulated | H18: Regulated | I18: Regulated | J18: Regulated | AY18: - | AZ18: - | BA18: - | BB18: UN R130 | BC18: UN R130 ISO 17361:2017 | BE18: UN R130 | CI18: GB/T 26773-2011 | CK18: in drafting AIS-188 | CL18: UN R130 | CM18: UN R130 | CN18: =E18 -> UN R130 | DW18: UN R130/ ADR 99 | DX18: =E18 -> UN R130 | EJ18: =E18 -> UN R130 | GC18: =E18 -> UN R130
C19: LKA | D19: Lane Keeping Assist | E19: UN R79 ACSF B1 | F19: UN R79 ACSF B1 | G19: Regulated | H19: Regulated | I19: Regulated | J19: Regulated | AY19: - | AZ19: - | BA19: - | BB19: UN R79 ACSF B1 | BC19: UN R79 ACSF B1 | BE19: UN R79 ACSF B1 | CI19: GB/T 39323-2020 | CK19: AIS 193 | CL19: UN R79 ACSF B1 | CM19: UN R79 ACSF B1 | CN19: =E19 -> UN R79 ACSF B1 | CO19: VSTD 47-2 (472) == UNR 79 | DX19: =E19 -> UN R79 ACSF B1 | EJ19: =E19 -> UN R79 ACSF B1 | GC19: =E19 -> UN R79 ACSF B1
C20: ELKS | D20: Emergency Lane Keeping System (based on lane detection) | E20: UN R in drafting (based on EU regulation) | F20: (EU) 2021/646 ELKS | G20: Mandatory | H20: Mandatory | I20: Mandatory | J20: Mandatory | AY20: - | AZ20: - | BA20: - | BB20: - | BC20: Regulated | CI20: - | CK20: in drafting AIS 191 Part1 (M1) | CL20: - | CM20: - | CN20: - | DW20: ADR 107/00 = (EU) 2021/646 ELKS | DX20: - | DY20: - | DZ20: - | EA20: - | EB20: - | EC20: - | ED20: - | EE20: - | EF20: - | EG20: - | EH20: - | EI20: - | EJ20: - | EK20: - | EL20: - | EM20: - | EN20: - | EO20: - | EP20: - | EQ20: - | ER20: - | ES20: - | ET20: - | EU20: - | EV20: - | EW20: - | EX20: - | EY20: - | EZ20: - | FA20: - | FB20: - | FC20: - | FD20: - | FE20: - | FF20: - | FG20: - | FH20: - | FI20: - | FJ20: - | FK20: - | FL20: - | FM20: - | FN20: - | FO20: - | FP20: - | FQ20: - | FR20: - | FS20: - | FT20: - | FU20: - | FV20: - | FW20: - | FX20: - | FY20: - | FZ20: - | GA20: - | GB20: - | GC20: -
C21: ESF | D21: Emergency Steering Function (object evasion) | E21: UN R79 ESF | F21: UN R79 ESF | AY21: - | AZ21: - | BA21: - | BB21: - | CI21: - | CL21: UN R79 ESF | CM21: UN R79 ESF | CN21: =E21 -> UN R79 ESF | CO21: VSTD 47-2 (472) == UNR 79 | DW21: UN R79 ESF | DX21: =E21 -> UN R79 ESF | EJ21: =E21 -> UN R79 ESF | GC21: =E21 -> UN R79 ESF
C22: Parking | D22: Assisted Parking (only Steering) | E22: UN R79 ACSF Cat A | F22: UN R79 ACSF Cat A | G22: Regulated | H22: Regulated | I22: Regulated | J22: Regulated | AY22: - | AZ22: - | BA22: - | BB22: - | BC22: Regulated | CI22: - | CK22: - | CL22: UN R79 ACSF Cat A | CM22: UN R79 ACSF Cat A | CN22: =E22 -> UN R79 ACSF Cat A | CO22: VSTD 47-2 (472) == UNR 79 | DW22: =E22 -> UN R79 ACSF Cat A | DX22: =E22 -> UN R79 ACSF Cat A | EJ22: =E22 -> UN R79 ACSF Cat A | GC22: =E22 -> UN R79 ACSF Cat A
C23: Lateral Control/ ACSF | D23: Lane Change Assist | E23: UN R79 ACSF Cat C | F23: UN R79 ACSF Cat C | G23: Regulated | H23: Regulated | I23: Regulated | J23: Regulated | AY23: - | AZ23: - | BA23: - | BB23: - | CI23: - | CK23: - | CL23: UN R79 ACSF Cat C | CM23: UN R79 ACSF Cat C | CN23: =E23 -> UN R79 ACSF Cat C | CO23: VSTD 47-2 (472) == UNR 79 | DW23: =E23 -> UN R79 ACSF Cat C | DX23: =E23 -> UN R79 ACSF Cat C | EJ23: =E23 -> UN R79 ACSF Cat C | GC23: =E23 -> UN R79 ACSF Cat C
D24: Risk Mitigation Function | E24: UN R79 RMF | F24: UN R79 RMF | AY24: - | AZ24: - | BA24: - | BB24: - | CI24: - | CK24: - | CL24: UN R79 RMF | CM24: UN R79 RMF | CN24: =E24 -> UN R79 RMF | DW24: =E24 -> UN R79 RMF | DX24: =E24 -> UN R79 RMF | EJ24: =E24 -> UN R79 RMF | GC24: =E24 -> UN R79 RMF
B25: Visibility | D25: Adaptive Lighting | E25: UN R48 | F25: UN R48 | G25: Regulated | H25: Regulated | I25: Regulated | J25: Regulated | AY25: FMVSS 108 | AZ25: FMVSS 108 | BA25: - | BB25: Res. CONTRAN 970/2022 | BC25: Res. CONTRAN 970/2022 | CI25: - | CK25: in drafting AIS-008 Rev2 | CL25: UN R48 | CM25: UN R48 | CN25: =E25 -> UN R48 | CO25: VSTD 3-5 (035) == UNR 48 | DW25: UN R48/ ADR 45/01 | DX25: =E25 -> UN R48 | EJ25: =E25 -> UN R48 | GC25: =E25 -> UN R48
B26: VRU Close Proximity Detection/Visibility | D26: VRU Rear (View / Detection) | E26: UN R158 | F26: UN R158 | G26: Mandatory | H26: Mandatory | I26: Mandatory | J26: Mandatory | L26: 158 | AY26: FMVSS 111 (Visibility Only) | AZ26: Mandatory | BA26: - | BB26: Resolution CONTRAN 759/2018 | BC26: Resolution CONTRAN 759/2018 | CI26: in drafting ~2027? | CK26: AIS-145 | CL26: UN R158 MLIT 619 Att 129 MLIT 619 Att 130 | CM26: UN R158 | CN26: =E26 -> UN R158 | DW26: UN R158 (ADR 108) | DX26: =E26 -> UN R158 | EJ26: =E26 -> UN R158 | GC26: =E26 -> UN R158
D27: VRU Front & Nearside (View / Detection) | E27: UN R166 | F27: UN R166 | G27: Regulated | H27: Regulated | I27: Regulated | J27: Regulated | L27: 166 | AY27: - | AZ27: - | BA27: - | BB27: - | BC27: - | CI27: - | CK27: - | CL27: UN R166 | CM27: UN R166 | CN27: =E27 -> UN R166 | DW27: =E27 -> UN R166 | DX27: =E27 -> UN R166 | EJ27: =E27 -> UN R166 | GC27: =E27 -> UN R166
D28: Blind Spot Information System | E28: - | F28: - | G28: Mandatory* | H28: Mandatory* | I28: Mandatory* | J28: Mandatory* | AY28: - | AZ28: - | BA28: - | BB28: - | BC28: - | CI28: GB/T 39265-2020 | CK28: - | CL28: - | CM28: - | CN28: - | DW28: - | DX28: - | EJ28: - | GC28: -
D29: Moving Off Information System | E29: - | F29: - | G29: Mandatory* | H29: Mandatory* | I29: Mandatory* | J29: Mandatory* | AY29: - | AZ29: - | BA29: - | BB29: - | BC29: - | CI29: - | CK29: - | CL29: - | CM29: - | CN29: - | DW29: - | DX29: - | EJ29: - | GC29: -
C30: IVD/ CMS | D30: Indirect Vision Devices/ Camera Monitoring System | E30: UN R46 | F30: UN R46 | G30: Regulated | H30: Regulated | I30: Regulated | J30: Regulated | AY30: - | AZ30: in drafting ? | BA30: - | BB30: - | BC30: - | CI30: GB 15084-2022 | CK30: AIS-001 Part 1 AIS-002 Part 1 | CL30: UN R46 | CM30: UN R46 | CN30: =E30 -> UN R46 | CO30: VSTD 23-2 (232) VSTD 27-1 (271) == UNR 46 | DW30: =E30 -> UN R46 | DX30: =E30 -> UN R46 | EJ30: =E30 -> UN R46 | GC30: =E30 -> UN R46
B31: Driver/ Occupant Monitoring | C31: DDAW | D31: Driver Drowsiness and Attention Warning | E31: UN R in drafting (based on EU regulation) | F31: (EU) 2021/1341 | G31: Mandatory | H31: Mandatory | I31: Mandatory | J31: Mandatory | AY31: drafting | AZ31: - | BA31: - | BC31: - | CI31: - | CK31: Regulated (2025) AIS-184 (M, N2 & N3) | CL31: - | CM31: - | CN31: =E31 -> UN R in drafting (based on EU regulation) | DW31: =E31 -> UN R in drafting (based on EU regulation) | DX31: =E31 -> UN R in drafting (based on EU regulation) | EJ31: =E31 -> UN R in drafting (based on EU regulation) | GC31: =E31 -> UN R in drafting (based on EU regulation)
C32: ADDW | D32: Advanced Driver Distraction Warning | E32: - | F32: (EU) 2023/2590 | G32: Mandatory | H32: Mandatory | I32: Mandatory | J32: Mandatory | AY32: - | AZ32: - | BA32: - | BB32: - | BC32: - | CI32: - | CK32: - | CL32: - | CM32: - | CN32: =E32 -> - | DW32: =E32 -> - | DX32: =E32 -> - | EJ32: =E32 -> - | GC32: =E32 -> -
C33: AIIF | D33: Alcohol Interlock Installation Facility | E33: - | F33: (EU) 2021/1243 | G33: Mandatory | H33: Mandatory | I33: Mandatory | J33: Mandatory | AY33: Mandatory? | AZ33: Mandatory? | BA33: - | BC33: - | CI33: - | CK33: - | CL33: - | CM33: - | CN33: - | CO33: - | CP33: - | CQ33: - | CR33: - | CS33: - | CT33: - | CU33: - | CV33: - | CW33: - | CX33: - | CY33: - | CZ33: - | DA33: - | DB33: - | DC33: - | DD33: - | DE33: - | DF33: - | DG33: - | DH33: - | DI33: - | DJ33: - | DK33: - | DL33: - | DM33: - | DN33: - | DO33: - | DP33: - | DQ33: - | DR33: - | DS33: - | DT33: - | DU33: - | DV33: - | DW33: - | DX33: - | DY33: - | DZ33: - | EA33: - | EB33: - | EC33: - | ED33: - | EE33: - | EF33: - | EG33: - | EH33: - | EI33: - | EJ33: - | EK33: - | EL33: - | EM33: - | EN33: - | EO33: - | EP33: - | EQ33: - | ER33: - | ES33: - | ET33: - | EU33: - | EV33: - | EW33: - | EX33: - | EY33: - | EZ33: - | FA33: - | FB33: - | FC33: - | FD33: - | FE33: - | FF33: - | FG33: - | FH33: - | FI33: - | FJ33: - | FK33: - | FL33: - | FM33: - | FN33: - | FO33: - | FP33: - | FQ33: - | FR33: - | FS33: - | FT33: - | FU33: - | FV33: - | FW33: - | FX33: - | FY33: - | FZ33: - | GA33: - | GB33: - | GC33: -
C34: DOW | D34: Door Operning Warning | E34: - | F34: - | G34: - | H34: - | I34: - | J34: - | K34: - | L34: - | M34: - | N34: - | O34: - | P34: - | Q34: - | R34: - | S34: - | T34: - | U34: - | V34: - | W34: - | X34: - | Y34: - | Z34: - | AA34: - | AB34: - | AC34: - | AD34: - | AE34: - | AF34: - | AG34: - | AH34: - | AI34: - | AJ34: - | AK34: - | AL34: - | AM34: - | AN34: - | AO34: - | AP34: - | AQ34: - | AR34: - | AS34: - | AT34: - | AU34: - | AV34: - | AW34: - | AX34: - | AY34: - | AZ34: - | BA34: - | BB34: - | BC34: - | CI34: CN_GB_T_44173-2024_EN_2024-09-18.pdf | CK34: - | CL34: - | CM34: - | CN34: - | CO34: - | CP34: - | CQ34: - | CR34: - | CS34: - | CT34: - | CU34: - | CV34: - | CW34: - | CX34: - | CY34: - | CZ34: - | DA34: - | DB34: - | DC34: - | DD34: - | DE34: - | DF34: - | DG34: - | DH34: - | DI34: - | DJ34: - | DK34: - | DL34: - | DM34: - | DN34: - | DO34: - | DP34: - | DQ34: - | DR34: - | DS34: - | DT34: - | DU34: - | DV34: - | DW34: - | DX34: - | DY34: - | DZ34: - | EA34: - | EB34: - | EC34: - | ED34: - | EE34: - | EF34: - | EG34: - | EH34: - | EI34: - | EJ34: - | EK34: - | EL34: - | EM34: - | EN34: - | EO34: - | EP34: - | EQ34: - | ER34: - | ES34: - | ET34: - | EU34: - | EV34: - | EW34: - | EX34: - | EY34: - | EZ34: - | FA34: - | FB34: - | FC34: - | FD34: - | FE34: - | FF34: - | FG34: - | FH34: - | FI34: - | FJ34: - | FK34: - | FL34: - | FM34: - | FN34: - | FO34: - | FP34: - | FQ34: - | FR34: - | FS34: - | FT34: - | FU34: - | FV34: - | FW34: - | FX34: - | FY34: - | FZ34: - | GA34: - | GB34: - | GC34: -
B35: Driver/ Occupant Monitoring | C35: DDAW | D35: Driver Drowsiness and Attention Warning | E35: - | F35: (EU) 2021/1341 | G35: Mandatory | H35: Mandatory | I35: Mandatory | J35: Mandatory | AY35: drafting | AZ35: - | BC35: - | CI35: - | CK35: Regulated (2025) AIS-184 (M, N2 & N3) | CL35: - | CM35: - | CN35: =E35 -> - | DW35: =E35 -> - | DX35: =E35 -> - | EJ35: =E35 -> - | GC35: =E35 -> -
C36: ADDW | D36: Advanced Driver Distraction Warning | E36: - | F36: (EU) 2023/2590 | G36: Mandatory | H36: Mandatory | I36: Mandatory | J36: Mandatory | AY36: - | AZ36: - | BB36: - | BC36: - | CI36: - | CK36: - | CL36: - | CM36: - | CN36: =E36 -> - | DW36: =E36 -> - | DX36: =E36 -> - | EJ36: =E36 -> - | GC36: =E36 -> -
C37: AIIF | D37: Alcohol Interlock Installation Facility | E37: - | F37: (EU) 2021/1243 | G37: Mandatory | H37: Mandatory | I37: Mandatory | J37: Mandatory | AY37: Mandatory? | AZ37: Mandatory? | BC37: - | CI37: - | CK37: - | CL37: - | CM37: - | CN37: =E37 -> - | DW37: =E37 -> - | DX37: =E37 -> - | EJ37: =E37 -> - | GC37: =E37 -> -
B38: Vehicle Data | C38: EDR | D38: Event Data Recorder | E38: UN R160 | F38: UN R160 | G38: Mandatory | H38: Mandatory | I38: Mandatory | J38: Mandatory | AY38: - | AZ38: - | BB38: - | BC38: - | CI38: GB 39732-2020 (M1) | CK38: in drafting AIS-192 (M1) | CL38: UN R160 | CM38: UN R160 | CN38: =E38 -> UN R160 | CO38: VSTD 98 (980) == UNR | DW38: =E38 -> UN R160 | DX38: =E38 -> UN R160 | EJ38: =E38 -> UN R160 | GC38: =E38 -> UN R160
C39: DSSAD | D39: Data Storage Systems for Automated Driving | E39: part of UN R157/ VMAD | F39: part of UN R157/ VMAD | G39: Regulated | H39: Regulated | I39: Regulated | J39: Regulated | AY39: - | AZ39: - | BB39: - | BC39: - | CI39: - | CK39: - | CL39: part of UN R157/ VMAD | CM39: part of UN R157/ VMAD | CN39: =E39 -> part of UN R157/ VMAD | DW39: =E39 -> part of UN R157/ VMAD | DX39: =E39 -> part of UN R157/ VMAD | EJ39: =E39 -> part of UN R157/ VMAD | GC39: =E39 -> part of UN R157/ VMAD
B40: Transversal | C40: SW | D40: Software Updates | E40: UN R156 | F40: UN R156 | G40: Mandatory | H40: Mandatory | I40: Mandatory | J40: Mandatory | AY40: - | AZ40: - | BA40: ? | BC40: - | CK40: in drafting AIS-190 | CL40: UN R156 | CM40: UN R156 | CN40: =E40 -> UN R156 | CO40: VSTD 98 (970) == UNR | DW40: UN R156 | DX40: =E40 -> UN R156 | EJ40: =E40 -> UN R156 | GC40: =E40 -> UN R156
C41: Cyber | D41: Cyber Security | E41: UN R155 | F41: UN R155 | G41: Mandatory | H41: Mandatory | I41: Mandatory | J41: Mandatory | AY41: - | AZ41: - | BA41: ? | BC41: - | CK41: in drafting AIS-189 | CL41: UN R155 | CM41: UN R155 | CN41: =E41 -> UN R155 | CO41: VSTD 98 (960) == UNR | DW41: UN R155 | DX41: =E41 -> UN R155 | EJ41: =E41 -> UN R155 | GC41: =E41 -> UN R155
B42: Road Traffic | D42: Lane Markings | E42: UN Regualtion 130 | CI42: GB 5768.3. | CK42: IRC:35:2015
B44: Automated driving features starting at level 2-4
B45: ADAS L2 | C45: DCAS | D45: Driver Controlled Assistance System (generic ADAS level 2) | E45: UN R171 | F45: =E45 -> UN R171 | G45: in drafting | H45: in drafting | I45: in drafting | J45: in drafting | AY45: - | AZ45: - | BB45: - | BC45: - | CI45: CDAS | CK45: in drafting adapting UN R171 | CL45: =E45 -> UN R171 | CM45: =E45 -> UN R171 | CN45: =E45 -> UN R171 | DW45: =E45 -> UN R171 | DX45: =E45 -> UN R171 | EJ45: =E45 -> UN R171 | GC45: =E45 -> UN R171
B46: ADAS L2 | C46: LKA+ACC | D46: Assitsted lane keeping (long+lateral control) | BB46: - | CI46: DRAFT GB/T Single Lane Manouvre
B47: ADAS L2 | C47: LCA+ACC | D47: Assisted lane Change (long+lateral control) | BB47: - | CI47: DRAFT GB/T Multi-lane manoeuver
B48: ADAS L2 | C48: Parking | D48: Automated/ Assisted Parking | E48: UN R79 ACSF Cat A | F48: =E48 -> UN R79 ACSF Cat A | G48: Regulated | H48: Regulated | I48: Regulated | J48: Regulated | AY48: - | AZ48: - | BB48: - | BC48: UN R79 ACSF Cat A | CI48: GB/T 41630-2022 | CK48: - | CL48: =E48 -> UN R79 ACSF Cat A | CM48: =E48 -> UN R79 ACSF Cat A | CN48: =E48 -> UN R79 ACSF Cat A | CO48: VSTD 47-2 (472) == UNR 79 | DW48: =E48 -> UN R79 ACSF Cat A | DX48: =E48 -> UN R79 ACSF Cat A | EJ48: =E48 -> UN R79 ACSF Cat A | GC48: =E48 -> UN R79 ACSF Cat A
B49: ADS L3 | C49: ALKS | D49: Automated Lane Keeping Systems (ADS level 3) | E49: UN R157 | F49: =E49 -> UN R157 | G49: Regulated | H49: Regulated | I49: Regulated | J49: Regulated | AY49: - | AZ49: - | BA49: - | BB49: - | BC49: - | BD49: - | BE49: - | CI49: - | CK49: in drafting AIS-191 Part 2 (M1) | CL49: =E49 -> UN R157 | CM49: =E49 -> UN R157 | CN49: =E49 -> UN R157 | DW49: =E49 -> UN R157 | DX49: =E49 -> UN R157 | EJ49: =E49 -> UN R157 | GC49: =E49 -> UN R157
B50: ADS L4 | C50: ADS | D50: Automated Driving System | E50: drafting | F50: (EU) 2022/1426 | G50: Regulated | H50: Regulated | I50: Regulated | J50: Regulated | AY50: Regulated (per State) | AZ50: Regulated | BB50: - | BC50: - | CI50: Regulated ? | CK50: - | CL50: =E50 -> drafting | CM50: =E50 -> drafting | CN50: =E50 -> drafting | DW50: ?? | DX50: =E50 -> drafting | EJ50: =E50 -> drafting | GC50: =E50 -> drafting
B51: Occupant Monitoring System | C51: OD | D51: Occupant Detection/ Occupant Monitoring System | E51: - | F51: - | G51: NCAP | H51: NCAP | I51: NCAP | J51: NCAP | AY51: drafting | BB51: - | BC51: - | CI51: - | CK51: - | CL51: =E51 -> - | CM51: =E51 -> - | CN51: =E51 -> - | DW51: =E51 -> - | DX51: =E51 -> - | EJ51: =E51 -> - | GC51: =E51 -> -
C52: e-Call | D52: Emergency Call | E52: UN R144 | F52: (EU) 2015/ 758 | G52: Mandatory | H52: Mandatory | I52: Mandatory | J52: Mandatory | AY52: - | BB52: - | BC52: - | CI52: - | CK52: Regulated AIS-140 | CL52: =E52 -> UN R144 | CM52: =E52 -> UN R144 | CN52: =E52 -> UN R144 | DW52: =E52 -> UN R144 | DX52: =E52 -> UN R144 | EJ52: =E52 -> UN R144 | GC52: =E52 -> UN R144
B56: CATEGORY M2, M3/ N2/ N3 (Few Topics also specific to N1 as mentioned)
A57: M2, M3/ N2/ N3 (Few Topics also specific to N1 as mentioned) | B57: Warning/ emergency / Assisting features level 0-1
B58: Long. Control | C58: AEB | D58: Advanced Emergency Braking (includes FCW) | E58: UN R131 | F58: UN R131 | G58: Mandatory | H58: Mandatory | I58: Mandatory | J58: Mandatory | AY58: FMVSS 128 Mandatory by 2030 | AZ58: in drafting | BA58: - | BB58: =E58 -> UN R131 | BC58: UN R131 | BD58: UN R131 mandatory by 08/2027 | BE58: UN R131 | CI58: !! GB/T 38186 (in process of being made mandatory with updated requirements 2026/27? (N, M2 & M3) | CK58: Regulated (2026) AIS-162 (M2, M3, N2 & N3) | CL58: =E58 -> UN R131 | CM58: KMVSS Article 90-3 Not equal UN R131/152!! | CN58: UN R131 | CO58: VSTD 72 (720) == UNR 131 | DW58: UN R131/ ADR 97 | DX58: =E58 -> UN R131 | EJ58: =E58 -> UN R131 | GC58: =E58 -> UN R131
C59: AEB VRU | D59: Advanced Emergency Braking for VRU (pedestrian & Cyclists) | E59: UN R131 | F59: UN R131 | G59: Mandatory | H59: Mandatory | I59: Mandatory | J59: Mandatory | AY59: - | AZ59: in drafting | BA59: - | BB59: - | BC59: UN R131 | BD59: UN R131 | BE59: UN R131 | CI59: in drafting | CK59: Regulated (2026) AIS-162 (M2, M3, N2 & N3) | CL59: =E59 -> UN R131 | CM59: KMVSS Article 90-3 Not equal UN R131/152!! | CN59: UN R131 | CO59: VSTD 72 (720) == UNR 131 | DW59: UN R131/ ADR 97 | DX59: =E59 -> UN R131 | EJ59: =E59 -> UN R131 | GC59: =E59 -> UN R131
C60: R-AEB | D60: Rear Advanced Emergency Braking | E60: - | F60: UN R13 (N, M2 & M3) | AY60: - | AZ60: NCAP | BA60: - | BB60: - | BC60: - | BD60: - | BE60: - | CI60: - | CK60: IS 11852-2019 AIS-150 | CL60: - | CM60: - | CN60: - | DW60: =E60 -> - | DX60: =E60 -> - | EJ60: =E60 -> - | GC60: =E60 -> -
C61: TSR (ISA) | D61: Traffic Sign Recognition (Intelligent Speed Assistance) | E61: - | F61: (EU) 2021/1958 | G61: (EU) 2021/1958 | H61: - | I61: (EU) 2021/1958 | J61: EU 2021/1958 + Israel Catalogue Israeli Catalog of Road Signs 2022.pdf | K61: Mandatory | L61: Mandatory | M61: Mandatory | N61: Mandatory | O61: Mandatory | Q61: Mandatory | R61: Mandatory | S61: Mandatory | T61: Mandatory | U61: Mandatory | V61: Mandatory | W61: Mandatory | X61: Mandatory | Y61: Mandatory | Z61: Mandatory | AA61: Mandatory | AB61: Mandatory | AC61: Mandatory | AD61: Mandatory | AE61: Mandatory | AF61: Mandatory | AG61: Mandatory | AH61: Mandatory | AI61: Mandatory | AJ61: Mandatory | AK61: Mandatory | AL61: Mandatory | AM61: Mandatory | AN61: Mandatory | AO61: Mandatory | AP61: Mandatory | AQ61: Mandatory | AR61: - | AS61: Mandatory | AT61: Mandatory | AU61: Mandatory | AV61: Mandatory | AW61: Mandatory | AX61: Mandatory | AY61: - | AZ61: - | BA61: - | BB61: - | BC61: - | BD61: - | BE61: - | CI61: - | CK61: - | CL61: - | CM61: - | CN61: - | DW61: =E61 -> - | DX61: =E61 -> - | EJ61: =E61 -> - | EK61: =R61 -> Mandatory | EL61: =S61 -> Mandatory | EM61: =T61 -> Mandatory | EN61: =U61 -> Mandatory | EO61: =V61 -> Mandatory | EP61: =W61 -> Mandatory | EQ61: =X61 -> Mandatory | ER61: =Y61 -> Mandatory | ... GB61: =BI61 -> 0 | GC61: =E61 -> -
C62: ACC | D62: Adaptive Cruise Control | E62: UN R13 ANNEX 8 (N, M2 & M3) | F62: UN R13 ANNEX 8 (N, M2 & M3) | AY62: - | AZ62: - | BA62: - | BB62: - | BF62: NCAP | BG62: NCAP | BH62: NCAP | BI62: NCAP | BJ62: NCAP | BK62: NCAP | BL62: NCAP | BM62: NCAP | BN62: NCAP | BO62: NCAP | BP62: NCAP | BQ62: NCAP | BR62: NCAP | BS62: NCAP | BT62: NCAP | BU62: NCAP | BV62: NCAP | BW62: NCAP | BX62: NCAP | BY62: NCAP | BZ62: NCAP | CA62: NCAP | CB62: NCAP | CC62: NCAP | CD62: NCAP | CE62: NCAP | CF62: NCAP | CG62: NCAP | CH62: NCAP | CJ62: NCAP | CK62: - | CL62: UN R13 ANNEX 8 (N, M2 & M3) | CM62: UN R13 ANNEX 8 (N, M2 & M3) | CN62: UN R13 ANNEX 8 (N, M2 & M3) | CO62: NCAP | CP62: NCAP | CQ62: NCAP | CR62: NCAP | CS62: NCAP | CT62: NCAP | CU62: NCAP | CV62: NCAP | CW62: NCAP | CX62: NCAP | CY62: NCAP | CZ62: NCAP | DA62: NCAP | DB62: NCAP | DC62: NCAP | DD62: NCAP | DE62: NCAP | DF62: NCAP | DG62: NCAP | DH62: NCAP | DI62: NCAP | DJ62: NCAP | DK62: NCAP | DL62: NCAP | DM62: NCAP | DN62: NCAP | DO62: NCAP | DP62: NCAP | DQ62: NCAP | DR62: NCAP | DS62: NCAP | DT62: NCAP | DU62: NCAP | DV62: NCAP | DW62: =E62 -> UN R13 ANNEX 8 (N, M2 & M3) | DX62: =E62 -> UN R13 ANNEX 8 (N, M2 & M3) | EJ62: =E62 -> UN R13 ANNEX 8 (N, M2 & M3) | EK62: NCAP | EL62: NCAP | EM62: NCAP | EN62: NCAP | EO62: NCAP | EP62: NCAP | EQ62: NCAP | ER62: NCAP | ES62: NCAP | ET62: NCAP | EU62: NCAP | EV62: NCAP | EW62: NCAP | EX62: NCAP | EY62: NCAP | EZ62: NCAP | FA62: NCAP | FB62: NCAP | FC62: NCAP | FD62: NCAP | FE62: NCAP | FF62: NCAP | FG62: NCAP | FH62: NCAP | FI62: NCAP | FJ62: NCAP | FK62: NCAP | FL62: NCAP | FM62: NCAP | FN62: NCAP | FO62: NCAP | FP62: NCAP | FQ62: NCAP | FR62: NCAP | FS62: NCAP | FT62: NCAP | FU62: NCAP | FV62: NCAP | FW62: NCAP | FX62: NCAP | FY62: NCAP | FZ62: NCAP | GA62: NCAP | GB62: NCAP | GC62: =E62 -> UN R13 ANNEX 8 (N, M2 & M3)
C63: ACPE | D63: Acceleration Control for Pedal Error | E63: - | F63: - | G63: in drafting | H63: in drafting | I63: in drafting | J63: in drafting | AY63: - | AZ63: - | BA63: - | BB63: - | BC63: - | BD63: - | BE63: - | CI63: - | CK63: - | CL63: - | CM63: - | CN63: =E63 -> - | DW63: =E63 -> - | DX63: =E63 -> - | EJ63: =E63 -> - | EK63: in drafting | EL63: in drafting | EM63: in drafting | EN63: in drafting | EO63: in drafting | EP63: in drafting | EQ63: in drafting | ER63: in drafting | ES63: in drafting | ET63: in drafting | EU63: in drafting | EV63: in drafting | EW63: in drafting | EX63: in drafting | EY63: in drafting | EZ63: in drafting | FA63: in drafting | FB63: in drafting | FC63: in drafting | FD63: in drafting | FE63: in drafting | FF63: in drafting | FG63: in drafting | FH63: in drafting | FI63: in drafting | FJ63: in drafting | FK63: in drafting | FL63: in drafting | FM63: in drafting | FN63: in drafting | FO63: in drafting | FP63: in drafting | FQ63: in drafting | FR63: in drafting | FS63: in drafting | FT63: in drafting | FU63: in drafting | FV63: in drafting | FW63: in drafting | FX63: in drafting | FY63: in drafting | FZ63: in drafting | GA63: in drafting | GB63: in drafting | GC63: =E63 -> -
B64: Lateral Control/ ACSF | C64: LDWS | D64: Lane Departure Warning System | E64: UN R130 | F64: UN R130 | G64: Regulated | H64: Regulated | I64: Regulated | J64: Regulated | AY64: - | AZ64: - | BA64: - | BB64: UN R130 | BC64: UN R130 ISO 17361:2017 | BE64: UN R130 | CI64: GB/T 26773-2011 | CK64: in drafting AIS-188 (M2, M3, N2, & N3) | CL64: UN R130 | CM64: UN R130 | CN64: =E64 -> UN R130 | CO64: VSTD 70 (700) == UNR 130 | DW64: UN R130 (ADR 99) | DX64: =E64 -> UN R130 | EJ64: =E64 -> UN R130 | GC64: =E64 -> UN R130
C65: LKA | D65: Lane Keeping Assist | E65: UN R79 ACSF B1 | F65: UN R79 ACSF B1 | G65: Regulated | H65: Regulated | I65: Regulated | J65: Regulated | AY65: - | AZ65: - | BA65: - | BB65: UN R79 ACSF B1 | BC65: UN R79 ACSF B1 | BE65: UN R79 ACSF B1 | CI65: - | CK65: (in drafting) AIS 193 | CL65: UN R79 ACSF B1 | CM65: UN R79 ACSF B1 | CN65: =E65 -> UN R79 ACSF B1 | CO65: VSTD 47-2 (472) == UNR 79 | DW65: =E65 -> UN R79 ACSF B1 | DX65: =E65 -> UN R79 ACSF B1 | EJ65: =E65 -> UN R79 ACSF B1 | GC65: =E65 -> UN R79 ACSF B1
C66: ELKS | D66: Emergency Lane Keeping System (based on lane detection) | E66: UN R79 CSF | F66: UN R79 CSF | G66: Mandatory | H66: Mandatory | I66: Mandatory | J66: Mandatory | AY66: - | AZ66: - | BA66: - | BB66: - | BC66: UN R79 CSF | BE66: UN R79 CSF | CI66: - | CK66: in drafting AIS 191 Part1 (M1) | CL66: - | CM66: - | CN66: - | DW66: UN R79 CSF | DX66: - | DY66: - | DZ66: - | EA66: - | EB66: - | EC66: - | ED66: - | EE66: - | EF66: - | EG66: - | EH66: - | EI66: - | EJ66: - | EK66: - | EL66: - | EM66: - | EN66: - | EO66: - | EP66: - | EQ66: - | ER66: - | ES66: - | ET66: - | EU66: - | EV66: - | EW66: - | EX66: - | EY66: - | EZ66: - | FA66: - | FB66: - | FC66: - | FD66: - | FE66: - | FF66: - | FG66: - | FH66: - | FI66: - | FJ66: - | FK66: - | FL66: - | FM66: - | FN66: - | FO66: - | FP66: - | FQ66: - | FR66: - | FS66: - | FT66: - | FU66: - | FV66: - | FW66: - | FX66: - | FY66: - | FZ66: - | GA66: - | GB66: - | GC66: -
C67: ESF | D67: Emergency Steering Function (object evasion) | E67: UN R79 ESF | F67: UN R79 ESF | AY67: - | BB67: - | BC67: UN R79 ESF | BE67: UN R79 ESF | CI67: - | CL67: UN R79 ESF | CM67: UN R79 ESF | CN67: =E67 -> UN R79 ESF | CO67: VSTD 47-2 (472) == UNR 79 | DW67: UN R79 ESF | DX67: =E67 -> UN R79 ESF | EJ67: =E67 -> UN R79 ESF | GC67: =E67 -> UN R79 ESF
C68: Parking | D68: Assisted Parking (only Steering) | E68: UN R79 ACSF Cat A | F68: UN R79 ACSF Cat A | G68: Regulated | H68: Regulated | I68: Regulated | J68: Regulated | AY68: - | AZ68: - | BA68: ? | BB68: - | BC68: UN R79 ACSF Cat A | BE68: UN R79 ACSF Cat A | CI68: - | CK68: - | CL68: UN R79 ACSF Cat A | CM68: UN R79 ACSF Cat A | CN68: =E68 -> UN R79 ACSF Cat A | CO68: VSTD 47-2 (472) == UNR 79 | DW68: =E68 -> UN R79 ACSF Cat A | DX68: =E68 -> UN R79 ACSF Cat A | EJ68: =E68 -> UN R79 ACSF Cat A | GC68: =E68 -> UN R79 ACSF Cat A
C69: LCA | D69: Lane Change Assist | E69: UN R79 ACSF Cat C | F69: UN R79 ACSF Cat C | G69: Regulated | H69: Regulated | I69: Regulated | J69: Regulated | AY69: - | AZ69: - | BA69: ? | BB69: - | CI69: - | CK69: - | CL69: UN R79 ACSF Cat C | CM69: UN R79 ACSF Cat C | CN69: =E69 -> UN R79 ACSF Cat C | CO69: VSTD 47-2 (472) == UNR 79 | DW69: =E69 -> UN R79 ACSF Cat C | DX69: =E69 -> UN R79 ACSF Cat C | EJ69: =E69 -> UN R79 ACSF Cat C | GC69: =E69 -> UN R79 ACSF Cat C
C70: RMF | D70: Risk Mitigation Function | E70: UN R79 RMF | F70: UN R79 RMF | AY70: - | AZ70: - | BA70: ? | BB70: - | CI70: - | CK70: - | CL70: UN R79 RMF | CM70: UN R79 RMF | CN70: =E70 -> UN R79 RMF | DW70: =E70 -> UN R79 RMF | DX70: =E70 -> UN R79 RMF | EJ70: =E70 -> UN R79 RMF | GC70: =E70 -> UN R79 RMF
B71: Visibility | D71: Adaptive Lighting | E71: UN R48 | F71: UN R48 | G71: Regulated | H71: Regulated | I71: Regulated | J71: Regulated | AY71: FMVSS 108 | AZ71: FMVSS 108 | BB71: - | CI71: - | CK71: in drafting AIS-008 Rev2 | CL71: UN R48 | CM71: UN R48 | CN71: =E71 -> UN R48 | CO71: VSTD 3-5 (035) == UNR 48 | DW71: =E71 -> UN R48 | DX71: =E71 -> UN R48 | EJ71: =E71 -> UN R48 | GC71: =E71 -> UN R48
B72: VRU Close Proximity Detection/Visibility | C72: VRU - R | D72: VRU Rear (View / Detection) | E72: UN R158 | F72: UN R158 | G72: Mandatory | H72: Mandatory | I72: Mandatory | J72: Mandatory | L72: 158 | AY72: FMVSS 111 (Visibility Only) | AZ72: Mandatory | BB72: Mandatory | BC72: Resolution CONTRAN 759/2018 | CI72: ? | CK72: AIS-145 | CL72: UN R158 | CM72: UN R158 | CN72: =E72 -> UN R158 | CO72: VSTD 71 (710) | DW72: UN R158 | DX72: =E72 -> UN R158 | EJ72: =E72 -> UN R158 | GC72: =E72 -> UN R158
C73: VRU - F & S | D73: VRU Front & Nearside (View / Detection) | E73: - | F73: - | G73: Regulated | H73: Regulated | I73: Regulated | J73: Regulated | L73: 166 | AY73: - | AZ73: - | BB73: - | BC73: - | CI73: - | CK73: - | CL73: - | CM73: - | CN73: - | DW73: - | DX73: - | EJ73: - | GC73: -
C74: BSIS | D74: Blind Spot Information System | E74: UN R151 | F74: UN R151 | G74: Mandatory* | H74: Mandatory* | I74: Mandatory* | J74: Mandatory* | AY74: - | AZ74: - | BB74: - | BC74: - | CI74: GB/T 39265-2020 | CK74: in drafting AIS-186 (M2, M3, N2, & N3) | CL74: UN R151 | CM74: UN R151 | CN74: =E74 -> UN R151 | CO74: VSTD 94 (940) == UNR 151 | CP74: UN R151 2025-01-01 for new types 2027-01-01: all vehicle types | DW74: =E74 -> UN R151 | DX74: =E74 -> UN R151 | EJ74: =E74 -> UN R151 | GC74: =E74 -> UN R151
C75: MOIS | D75: Moving Off Information System | E75: UN R159 | F75: UN R159 | G75: Mandatory* | H75: Mandatory* | I75: Mandatory* | J75: Mandatory* | AY75: - | AZ75: - | BB75: - | BC75: - | CI75: - | CK75: in drafting AIS-187 (M2, M3, N2, & N3) | CL75: UN R159 | CM75: UN R159 | CN75: =E75 -> UN R159 | DW75: =E75 -> UN R159 | DX75: =E75 -> UN R159 | EJ75: =E75 -> UN R159 | GC75: =E75 -> UN R159
C76: IVD/ CMS | D76: Indirect Vision Devices/ Camera Monitoring System | E76: UN R46 | F76: UN R46 | G76: Regulated | H76: Regulated | I76: Regulated | J76: Regulated | AY76: - | AZ76: in drafting ? | BB76: - | BC76: - | CI76: GB 15084-2022 | CK76: AIS-001 Part 1 AIS-002 Part 1 | CL76: UN R46 | CM76: UN R46 | CN76: =E76 -> UN R46 | CO76: VSTD 23-2 (232) VSTD 27-1 (271) == UNR 46 | DW76: =E76 -> UN R46 | DX76: =E76 -> UN R46 | EJ76: =E76 -> UN R46 | GC76: =E76 -> UN R46
B77: Driver/ Occupant Monitoring | C77: DDAW | D77: Driver Drowsiness and Attention Warning | E77: - | F77: (EU) 2021/1341 | G77: Mandatory | H77: Mandatory | I77: Mandatory | J77: Mandatory | AY77: drafting | AZ77: - | BC77: - | CI77: - | CK77: Regulated (2025) AIS-184 (M, N2 & N3) | CL77: - | CM77: - | CN77: =E77 -> - | DW77: =E77 -> - | DX77: =E77 -> - | EJ77: =E77 -> - | GC77: =E77 -> -
C78: ADDW | D78: Advanced Driver Distraction Warning | E78: - | F78: (EU) 2023/2590 | G78: Mandatory | H78: Mandatory | I78: Mandatory | J78: Mandatory | AY78: - | AZ78: - | BB78: - | BC78: - | CI78: - | CK78: - | CL78: - | CM78: - | CN78: =E78 -> - | DW78: =E78 -> - | DX78: =E78 -> - | EJ78: =E78 -> - | GC78: =E78 -> -
C79: AIIF | D79: Alcohol Interlock Installation Facility | E79: - | F79: (EU) 2021/1243 | G79: Mandatory | H79: Mandatory | I79: Mandatory | J79: Mandatory | AY79: Mandatory? | AZ79: Mandatory? | BC79: - | CI79: - | CK79: - | CL79: - | CM79: - | CN79: =E79 -> - | DW79: =E79 -> - | DX79: =E79 -> - | EJ79: =E79 -> - | GC79: =E79 -> -
B81: Vehicle Data | C81: EDR | D81: Event Data Recorder | E81: - | F81: - | G81: Mandatory | H81: Mandatory | I81: Mandatory | J81: Mandatory | AY81: - | AZ81: - | BB81: - | BC81: - | CI81: - | CK81: - | CL81: - | CM81: - | CN81: - | CO81: VSTD 98 (980) == UNR | DW81: - | DX81: - | EJ81: - | GC81: -
C82: DSSAD | D82: Data Storage System for Automated Driving | E82: part of UN R157/ VMAD | F82: part of UN R157/ VMAD | G82: Regulated | H82: Regulated | I82: Regulated | J82: Regulated | AY82: - | AZ82: - | BB82: - | BC82: - | CI82: - | CK82: - | CL82: part of UN R157/ VMAD | CM82: part of UN R157/ VMAD | CN82: =E82 -> part of UN R157/ VMAD | DW82: =E82 -> part of UN R157/ VMAD | DX82: =E82 -> part of UN R157/ VMAD | EJ82: =E82 -> part of UN R157/ VMAD | GC82: =E82 -> part of UN R157/ VMAD
B83: Transversal | C83: SW | D83: Software Updates | E83: UN R156 | F83: UN R156 | G83: Mandatory | H83: Mandatory | I83: Mandatory | J83: Mandatory | AY83: - | AZ83: - | BA83: ? | BC83: - | CK83: in drafting AIS-190 | CL83: UN R156 | CM83: UN R156 | CN83: =E83 -> UN R156 | CO83: VSTD 98 (970) == UNR | DW83: UN R156 | DX83: =E83 -> UN R156 | EJ83: =E83 -> UN R156 | GC83: =E83 -> UN R156
C84: Cyber | D84: Cyber Security | E84: UN R155 | F84: UN R155 | G84: Mandatory | H84: Mandatory | I84: Mandatory | J84: Mandatory | AY84: - | AZ84: - | BA84: ? | BC84: - | CK84: in drafting AIS-189 | CL84: UN R155 | CM84: UN R155 | CN84: =E84 -> UN R155 | CO84: VSTD 98 (960) == UNR | DW84: UN R155 | DX84: =E84 -> UN R155 | EJ84: =E84 -> UN R155 | GC84: =E84 -> UN R155
B85: Road Traffic | D85: Lane Markings | E85: UN Regualtion 130 | CI85: GB 5768.3. | CK85: IRC:35:2015
B87: =B44 -> Automated driving features starting at level 2-4 | U87: =U44 -> 0 | V87: =V44 -> 0 | W87: =W44 -> 0 | X87: =X44 -> 0 | Y87: =Y44 -> 0 | Z87: =Z44 -> 0 | AA87: =AA44 -> 0 | AB87: =AB44 -> 0 | ... GC87: =GC44 -> 0
B88: =B45 -> ADAS L2 | C88: =C45 -> DCAS | D88: =D45 -> Driver Controlled Assistance System (generic ADAS level 2) | E88: =E45 -> UN R171 | F88: =F45 -> UN R171 | G88: in drafting | H88: in drafting | I88: in drafting | J88: in drafting | AY88: =AY45 -> - | AZ88: - | BB88: =BB45 -> - | BC88: - | CI88: =CI45 -> CDAS | CK88: =CK45 -> in drafting adapting UN R171 | CL88: =CL45 -> UN R171 | CM88: =CM45 -> UN R171 | CN88: =CN45 -> UN R171 | DW88: =DW45 -> UN R171 | DX88: =DX45 -> UN R171 | EJ88: =EJ45 -> UN R171 | GC88: =GC45 -> UN R171
B89: =B46 -> ADAS L2 | C89: =C46 -> LKA+ACC | D89: =D46 -> Assitsted lane keeping (long+lateral control) | E89: =E46 -> 0 | F89: =F46 -> 0 | AY89: =AY46 -> 0 | BB89: =BB46 -> - | CI89: =CI46 -> DRAFT GB/T Single Lane Manouvre | CK89: =CK46 -> 0 | CL89: =CL46 -> 0 | CM89: =CM46 -> 0 | CN89: =CN46 -> 0 | DW89: =DW46 -> 0 | DX89: =DX46 -> 0 | EJ89: =EJ46 -> 0 | GC89: =GC46 -> 0
B90: =B47 -> ADAS L2 | C90: =C47 -> LCA+ACC | D90: =D47 -> Assisted lane Change (long+lateral control) | E90: =E47 -> 0 | F90: =F47 -> 0 | AY90: =AY47 -> 0 | BB90: =BB47 -> - | CI90: =CI47 -> DRAFT GB/T Multi-lane manoeuver | CK90: =CK47 -> 0 | CL90: =CL47 -> 0 | CM90: =CM47 -> 0 | CN90: =CN47 -> 0 | DW90: =DW47 -> 0 | DX90: =DX47 -> 0 | EJ90: =EJ47 -> 0 | GC90: =GC47 -> 0
B91: =B48 -> ADAS L2 | C91: =C48 -> Parking | D91: =D48 -> Automated/ Assisted Parking | E91: =E48 -> UN R79 ACSF Cat A | F91: =F48 -> UN R79 ACSF Cat A | G91: Regulated | H91: Regulated | I91: Regulated | J91: Regulated | AY91: =AY48 -> - | AZ91: - | BB91: =BB48 -> - | BC91: UN R79 ACSF Cat A | CI91: - | CK91: =CK48 -> - | CL91: =CL48 -> UN R79 ACSF Cat A | CM91: =CM48 -> UN R79 ACSF Cat A | CN91: =CN48 -> UN R79 ACSF Cat A | CO91: VSTD 47-2 (472) == UNR 79 | DW91: =DW48 -> UN R79 ACSF Cat A | DX91: =DX48 -> UN R79 ACSF Cat A | EJ91: =EJ48 -> UN R79 ACSF Cat A | GC91: =GC48 -> UN R79 ACSF Cat A
B92: =B49 -> ADS L3 | C92: =C49 -> ALKS | D92: =D49 -> Automated Lane Keeping Systems (ADS level 3) | E92: =E49 -> UN R157 | F92: =F49 -> UN R157 | G92: Regulated | H92: Regulated | I92: Regulated | J92: Regulated | AY92: =AY49 -> - | AZ92: - | BA92: - | BB92: =BB49 -> - | BC92: - | BD92: - | BE92: - | CI92: =CI49 -> - | CK92: - | CL92: =CL49 -> UN R157 | CM92: =CM49 -> UN R157 | CN92: =CN49 -> UN R157 | DW92: =DW49 -> UN R157 | DX92: =DX49 -> UN R157 | EJ92: =EJ49 -> UN R157 | GC92: =GC49 -> UN R157
B93: =B50 -> ADS L4 | C93: =C50 -> ADS | D93: =D50 -> Automated Driving System | E93: =E50 -> drafting | F93: =F50 -> (EU) 2022/1426 | G93: Regulated | H93: Regulated | I93: Regulated | J93: Regulated | AY93: =AY50 -> Regulated (per State) | AZ93: Regulated | BB93: =BB50 -> - | BC93: - | CI93: =CI50 -> Regulated ? | CK93: =CK50 -> - | CL93: =CL50 -> drafting | CM93: =CM50 -> drafting | CN93: =CN50 -> drafting | DW93: =DW50 -> ?? | DX93: =DX50 -> drafting | EJ93: =EJ50 -> drafting | GC93: =GC50 -> drafting
B94: =B51 -> Occupant Monitoring System | C94: =C51 -> OD | D94: =D51 -> Occupant Detection/ Occupant Monitoring System | E94: =E51 -> - | F94: =F51 -> - | G94: NCAP | H94: NCAP | I94: NCAP | J94: NCAP | AY94: =AY51 -> drafting | BB94: =BB51 -> - | BC94: - | CI94: =CI51 -> - | CK94: =CK51 -> - | CL94: =CL51 -> - | CM94: =CM51 -> - | CN94: =CN51 -> - | DW94: =DW51 -> - | DX94: =DX51 -> - | EJ94: =EJ51 -> - | GC94: =GC51 -> -
B95: =B52 -> 0 | C95: =C52 -> e-Call | D95: =D52 -> Emergency Call | E95: - | F95: - | G95: Mandatory | H95: Mandatory | I95: Mandatory | J95: Mandatory | AY95: =AY52 -> - | BB95: =BB52 -> - | BC95: - | CI95: =CI52 -> - | CK95: =CK52 -> Regulated AIS-140 | CL95: - | CM95: - | CN95: - | CO95: - | CP95: - | CQ95: - | CR95: - | CS95: - | CT95: - | CU95: - | CV95: - | CW95: - | CX95: - | CY95: - | CZ95: - | DA95: - | DB95: - | DC95: - | DD95: - | DE95: - | DF95: - | DG95: - | DH95: - | DI95: - | DJ95: - | DK95: - | DL95: - | DM95: - | DN95: - | DO95: - | DP95: - | DQ95: - | DR95: - | DS95: - | DT95: - | DU95: - | DV95: - | DW95: - | DX95: - | DY95: - | DZ95: - | EA95: - | EB95: - | EC95: - | ED95: - | EE95: - | EF95: - | EG95: - | EH95: - | EI95: - | EJ95: - | EK95: - | EL95: - | EM95: - | EN95: - | EO95: - | EP95: - | EQ95: - | ER95: - | ES95: - | ET95: - | EU95: - | EV95: - | EW95: - | EX95: - | EY95: - | EZ95: - | FA95: - | FB95: - | FC95: - | FD95: - | FE95: - | FF95: - | FG95: - | FH95: - | FI95: - | FJ95: - | FK95: - | FL95: - | FM95: - | FN95: - | FO95: - | FP95: - | FQ95: - | FR95: - | FS95: - | FT95: - | FU95: - | FV95: - | FW95: - | FX95: - | FY95: - | FZ95: - | GA95: - | GB95: - | GC95: -
A97: https://unece.org/fileadmin/DAM/trans/main/wp29/wp29resolutions/ECE-TRANS-WP.29-78r6e.pdf
A98: "Category M1" | B98: Vehicles used for the carriage of passengers and comprising not more than eight seats in addition to the driver's seat.
A99: "Category M2" | B99: Vehicles used for the carriage of passengers, comprising more than eight seats in addition to the driver's seat, and having a maximum mass not exceeding 5 tonnes.
A100: "Category M3" | B100: Vehicles used for the carriage of passengers, comprising more than eight seats in addition to the driver's seat, and having a maximum mass exceeding 5 tonnes
A101: "Category N1" | B101: Vehicles used for the carriage of goods and having a maximum mass not exceeding 3.5 tonnes.
A102: "Category N2" | B102: Vehicles used for the carriage of goods and having a maximum mass exceeding 3.5 tonnes but not exceeding 12 tonnes.
A103: "Category N3" | B103: Vehicles used for the carriage of goods and having a maximum mass exceeding 12 tonnes.
B106: Trade Agreements (Trade Barriers?)
B107: Traffic Rules

Sheet MAPPING with Deliverables
A2: Absolute Number | B2: GSR marker | C2: Category | D2: Platform | E2: Market | F2: aClassification | G2: aApplicability | H2: Coverage Review | I2: Coverage Review Comment | J2: Scope or Acronym | K2: Object_Title&Text | L2: Subtitle | M2: Description | N2: Revision | O2: Date of application | P2: Vehicle Category | Q2: Module name | R2: Link | S2: Valeo Standard/ Process Reference | T2: Evidence (Engineering Gate Deliverable) | U2: Reference to Eng. Gate | V2: Compliance Guide | W2: Compliance Guide Comment | X2: Certification/ Type Approval required
A3: 7 | B3: Undefined | K3: 1 Purpose/ Scope
A4: 2 | B4: Undefined | K4: This module serves as a database containing norms and regulations which are to be applied or are to be considered for the development of CDV products.
A5: 15 | B5: Undefined | K5: 2 General Definitions
A6: 18 | B6: Undefined | K6: Norms and Regulations are hereby addressed as document.
A7: 28 | B7: Undefined | K7: 2.1 Attributes
A8: 3 | B8: Undefined | K8: Specific attributes are addressed to the documents to identify their applicabilty.
A9: 21 | B9: Undefined | K9: These attributes shall be used in combination with the filter function.
A10: 16 | B10: Undefined | K10: 2.1.1 Function
A11: 17 | B11: Undefined | K11: With the attribute Function documents are allocated to a specific function they describe and specify (e.g. EMC = Electromagnetic Compatibilty; AEB = Autonomous Emergency Braking, ... ).
A12: 25 | B12: Undefined | K12: The functions definitions and abbreviations are based on the ADASIS (Advanced Drivers Assistance Systems Interface Specifications) standard (see Appendix I).
A13: 19 | B13: Undefined | K13: In case the document does not address specific functions but specifies general requirements it will be marked as generic.
A14: 20 | B14: Undefined | K14: 2.1.2 Market Allocation
... A55: 367 | B55: Undefined | K55: Based on an international agreement (The Wassenaar Arrangement on Export Controls for Conventional Arms and Dual-Use Goods and Technologies) to contribute to regional and international security and stability by promoting transparency and greater responsibility in transfers of conventional arms and dual-use goods and technologies, thus preventing destabilizing accumulations. Participating states seek, through their national policies, to ensure that transfers of these items do not contribute to the development or enhancement of military capabilities which undermine these goals, and are not diverted to support such capabilities.
A56: 368 | B56: Undefined | C56: INTERNAL | D56: Transversal/ Generic | E56: Worldwide | F56: A | G56: Yes | H56: Covered by Valeo Process | J56: Export Control | K56: Product development and Export Control restriction | L56: GSI-RD-679 | M56: Mandatory Group Instruction This instruction presents the rules to be applied in order to master the Export Control restrictions of the products that we develop. | N56: A01 | Q56: no module available GSI-RD-679-A01_Product development and Export Control restriction | S56: GSI-RD-679 https://sites.google.com/a/valeo.com/group-procedures/group-procedures?filterM=GSI-RD-H01-0679 | T56: Export Control Assessment Questionnaire for Projects and Platforms | V56: Documentation (e.g. Datasheet; Drawing, FMEA,..) Covered by Platform/metiers Standards | W56: DU Classification and Approval
A57: 556 | B57: Undefined | C57: INTERNAL | D57: Transversal/ Generic | E57: Worldwide | F57: A | G57: Yes | H57: Covered by Valeo Process | J57: Export Control | K57: Export Controls of electronic parts | L57: GSI-RD-H01-0854 A03 | M57: Mandatory Group Instruction The purpose of this procedure is to describe the Valeo rules and processes applicable to detect and manage electronic parts that can be subject to Export Controls. It completes other procedures that are implemented at product levels. | N57: A03 | O57: 2023 | Q57: no module available | R57: https://docs.google.com/document/d/100OCp6Si8lebeB50uMYUcKSPxmOOM5ev3BsX4AHGNW8/edit#heading=h.3znysh7 | S57: GSI-RD-679 https://sites.google.com/a/valeo.com/group-procedures/group-procedures?filterM=GSI-RD-H01-0679 | T57: Export Control Assessment Questionnaire for Projects and Platforms | V57: Documentation (e.g. Datasheet; Drawing, FMEA,..) Covered by Platform/metiers Standards | W57: DU Classification and Approval
A58: 369 | B58: Undefined | C58: REGULATION | D58: Transversal/ Generic | E58: Europe | F58: A | G58: Yes | H58: Covered by Valeo Process | J58: Export Control | K58: (EU) 2021/821 | L58: Regulation (EU) 2021/821 of the European Parliament and of the Council of 20 May 2021 setting up a Union regime for the control of exports, brokering, technical assistance, transit and transfer of dual-use items | M58: This Regulation establishes a Union regime for the control of exports, brokering, technical assistance, transit and transfer of dual-use items. | N58: 45047 | S58: GSI-RD-679 https://sites.google.com/a/valeo.com/group-procedures/group-procedures?filterM=GSI-RD-H01-0679 | T58: Export Control Assessment Questionnaire for Projects and Platforms | V58: Documentation (e.g. Datasheet; Drawing, FMEA,..) Covered by Platform/metiers Standards | W58: DU Classification and Approval DU Classification and Approval
A59: 371 | B59: Undefined | C59: REGULATION | E59: USA | F59: A | G59: Yes | H59: Covered by Valeo Process | J59: Export Control | K59: De minimis Rules and Guidelines | L59: § 734.4 and Supplement No. 2 to part 734 of the EAR (as modified on 11 April 2018) | M59: Based on determined US content within the product the EAR are to be applied accordingly. | N59: 43191 | S59: GSI-RD-679 https://sites.google.com/a/valeo.com/group-procedures/group-procedures?filterM=GSI-RD-H01-0679 | T59: Export Control Assessment Questionnaire for Projects and Platforms | V59: Documentation (e.g. Datasheet; Drawing, FMEA,..) Covered by Platform/metiers Standards | W59: DU Classification and Approval
A60: 370 | B60: Undefined | C60: REGULATION | D60: Transversal/ Generic | E60: USA | F60: A | G60: Yes | H60: Covered by Valeo Process | J60: Export Control | K60: US Export Administration Regulation (EAR) | M60: Sections relevant: CCL3_Electronics CCL4_Computers CCL5_PT2_Information Security CCL6_Sensors and Lasers CCL7_Navigation and Avionics | N60: 2019-05-23 2018-10-29 2019-05-23 2019-05-23 2018-12-20 | R60: https://www.bis.doc.gov/index.php/regulations/export-administration-regulations-ear | S60: GSI-RD-679 https://sites.google.com/a/valeo.com/group-procedures/group-procedures?filterM=GSI-RD-H01-0679 | T60: Export Control Assessment Questionnaire for Projects and Platforms | V60: Documentation (e.g. Datasheet; Drawing, FMEA,..) Covered by Platform/metiers Standards | W60: DU Classification and Approval
A61: 226 | B61: Undefined | K61: 3.2 Radio & Laser Spectrum Matters
A62: 239 | B62: Undefined | K62: 3.2.1 Radio Regulations and Frequency Allocations
A63: 520 | B63: Undefined | C63: INTERNAL | D63: DRS - Radar | E63: Worldwide ITU Region 1 ITU Region 2 ITU Region 3 | F63: B | J63: Radio Emission | K63: World Wide Country List of Emission Limits for 77-81GHz | N63: 10.2022 | Q63: DRS_Radar_List of countries 77GHz_79GHz | V63: Product Marking Testing Documentation (e.g. Datasheet; Drawing, FMEA,..) Certification
A64: 319 | B64: Undefined | C64: REGULATION | D64: DRS - Radar | E64: ITU Region 3 | F64: B | J64: Radio Emission | K64: Infocomm Development Authority of Singapore | L64: RADIO SPECTRUM MASTER PLAN | M64: In Singapore, IDA as the telecommunication regulator, is charged with the responsibility of administering frequency management matters. The responsibility includes drawing up frequency allocation plans for various services, coordinating frequency assignments with neighbouring countries, monitoring spectrum usage and resolving radio interference. Annex 1 provides an overview of existing and planned services within the spectrum plan as well as the priority for review on an on-going basis. | N64: 41214 | Q64: 12146_SG_Master_Plan_Radio_Spectrum_2012-11_EN_2013-04-09 | R64: https://lis9-svdol10.vnet.valeo.com:1201/dwa/rm/urn:rational::1-43463251374b73b7-M-00081b51 | V64: Product Marking Testing Documentation (e.g. Datasheet; Drawing, FMEA,..) Certification
A65: 318 | B65: Undefined | C65: REGULATION | D65: DRS - Radar | E65: Taiwan ITU Region 3 | F65: B | J65: Radio Emission | K65: Telecom Technical Regulations Test Requirements | L65: Low-power Radio-frequency Devices Technical Regulations | M65: This regulation is formulated based on Section 1 of Article 50 of the Telecommunications Act. It consists of five chapters: Chapter 1 defines related terminology; Chapter 2 stipulates general requirements for the operating bands, radiated field intensity, performances and manufacture, installation, possession, import and sales of equipment. Low-power radio-frequency devices in this chapter are unrestricted unless otherwise stipulated by other laws codes; Chapter 3 and Chapter 4 outline specifications for conformity. As such these two chapters place limitations on the frequency bands and radiated field intensity and correspond to the relevant frequency bands and types of device. Those not stipulated in these two Chapters shall comply with the provisions of Chapter 2; Chapter 5 covers test requirements of type approvals on low-power radio-frequency devices. | N65: 43101 | Q65: 12147_2018-01-10_Taiwan_Low-power Radio-frequency Devices Technical Regulations | R65: https://lis9-svdol10.vnet.valeo.com:1201/dwa/rm/urn:rational::1-43463251374b73b7-M-00081b52 | V65: Product Marking Testing Documentation (e.g. Datasheet; Drawing, FMEA,..) Certification
A66: 142 | B66: Undefined | C66: REGULATION | D66: DRS - Radar ECU w WIFI/Bluetooth | E66: USA ITU Region 2 | F66: B | J66: Radio Emission | K66: Title 47 Chapter I Subchapter A Part 15 - Radio Frequency Devices | L66: Radio Frequency Devices | M66: (a) This part sets out the regulations under which an intentional, unintentional, or incidental radiator may be operated without an individual license. It also contains the technical specifications, administrative requirements and other conditions relating to the marketing of part 15 devices. (b) The operation of an intentional or unintentional radiator that is not in accordance with the regulations in this part must be licensed pursuant to the provisions of section 301 of the Communications Act of 1934, as amended, unless otherwise exempted from the licensing requirements elsewhere in this chapter. (c) Unless specifically exempted, the operation or marketing of an intentional or unintentional radiator that is ot in compliance with the administrative and technical provisions in this art, including prior Commission authorization or verification, as appropriate, is prohibited under section 302 f the Communications Act of 1934, as mended, and subpart I of part 2 of this chapter. The equipment authorization and verification procedures are detailed in subpart J of part 2 of this chapter. | N66: 42644 | Q66: 12121_FCC_Part15_Radio_frequency_Devices | R66: https://lis9-svdol10.vnet.valeo.com:1201/dwa/rm/urn:rational:67c31aaa-786d-11e4-943f-77f7170acf6c:1-43463251374b73b7-M-0006e53a | V66: Product Marking Testing Documentation (e.g. Datasheet; Drawing, FMEA,..) Certification
A67: 144 | B67: Undefined | C67: REGULATION | D67: DRS - Radar ECU w WIFI/Bluetooth | E67: USA ITU Region 2 | F67: A | J67: Radio Emission | K67: Title 47 §15.5 General conditions of operation | L67: §15.5 General conditions of operation | M67: (b) Operation of an intentional, unintentional, or incidental radiator is subject to the conditions that no harmful interference is caused and that interference must be accepted that may be caused by the operation of an authorized radio station, by another intentional or unintentional radiator, by industrial, scientific and medical (ISM) equipment, or by an incidental radiator. (c) The operator of a radio frequency device shall be required to cease operating the device upon notification by a Commission representative that the device is causing harmful interference. Operation shall not resume until the condition causing the harmful interference has been corrected. | N67: 42644 | R67: https://lis9-svdol10.vnet.valeo.com:1201/dwa/rm/urn:rational:67c31aaa-786d-11e4-943f-77f7170acf6c:1-43463251374b73b7-M-0006e53a | V67: Product Marking Testing Documentation (e.g. Datasheet; Drawing, FMEA,..) Certification
A68: 145 | B68: Undefined | C68: REGULATION | D68: DRS - Radar ECU w WIFI/Bluetooth | E68: USA ITU Region 2 | F68: A | J68: Radio Emission | K68: Title 47 §15.29 Inspection by the Commission | L68: §15.29 Inspection by the Commission | M68: Any equipment or device subject to the provisions of this part, together with any certificate, notice of registration or any technical data required to be kept on file by the operator, supplier or party responsible for compliance of the device shall be made available for inspection by a Commission representative upon reasonable request. | N68: 42644 | R68: https://lis9-svdol10.vnet.valeo.com:1201/dwa/rm/urn:rational:67c31aaa-786d-11e4-943f-77f7170acf6c:1-43463251374b73b7-M-0006e53a | V68: Product Marking Testing Documentation (e.g. Datasheet; Drawing, FMEA,..) Type Approval
A69: 143 | B69: Undefined | C69: REGULATION | D69: DRS - RLT DRS - ULS & ECU DVS - Vision System DVS - Viewing Camera DVS - ECU & Domain Controller DFC - Front Camera DRS - Solid State Lidar DRS - Laserscanner DFC - Zone Controller | E69: USA ITU Region 2 | F69: C | J69: EMC | K69: Title 47 §15.103 Exempted devices -- allocated devices do not need to apply FCC specific EMC requirements -- | L69: §15.103 Exempted devices | M69: The following devices are subject only to the general conditions of operation in §§15.5 and 15.29 and are exempt from the specific technical standards and other requirements contained in this part. ... Although not mandatory, it is strongly recommended that the manufacturer of an exempted device endeavor to have the device meet the specific technical standards in this part. (a) A digital device utilized exclusively in any transportation vehicle including motor vehicles and aircraft. | N69: 42644 | R69: https://lis9-svdol10.vnet.valeo.com:1201/dwa/rm/urn:rational:67c31aaa-786d-11e4-943f-77f7170acf6c:1-43463251374b73b7-M-0006e53a
A70: 199 | B70: Undefined | C70: REGULATION | D70: DRS - Radar ECU w WIFI/Bluetooth | E70: Europe ITU Region 1 | F70: C | J70: Radio Emission | K70: 2000/299/EC Classification of radio equipment | L70: 2000/299/EC: Commission Decision of 6 April 2000 establishing the initial classification of radio equipment and telecommunications terminal equipment and associated identifiers | M70: Definition of classes: Class 1: can be placed on the market and be put into service without restrictions Class 2: equipment where restrictians acc. to other legislations apply (e.g. Radio Equipment Directive) | N70: 36617 | O70: 36617 | Q70: - no module available - | R70: https://eur-lex.europa.eu/legal-content/EN/ALL/?uri=celex:32000D0299
A71: 190 | B71: Undefined | C71: REGULATION | D71: DRS - Radar ECU w WIFI/Bluetooth | E71: Europe ITU Region 1 | F71: B | J71: Radio Emission | K71: 2006/771/EC Radio Spectrum Short Range | L71: COMMISSION DECISION of 9 November 2006 on harmonisation of the radio spectrum for use by short-range devices | M71: The purpose of this Decision is to harmonise the frequency bands and the related technical parameters for the availability and efficient use of radio spectrum for short-range devices so that such devices may benefit from ‘Class 1’ classification under Commission Decision 2000/299/EC. | N71: 41609 | O71: 41883 | Q71: 12129_Decision 2006_771_EC_Radio Spectrum Short Range | R71: https://drive.google.com/file/d/1qPyPrxhVDzl2IQHg1kJES9F6-JvGe_aT/view | V71: Product Marking Testing Documentation (e.g. Datasheet; Drawing, FMEA,..)
A72: 65 | B72: Undefined | C72: REGULATION | D72: DRS - Radar ECU w WIFI/Bluetooth | E72: Europe ITU Region 1 | F72: B | J72: Radio Emission | K72: 2014/53/EU Radio Equipment Directive | L72: Directive 2014/53/EU of the European Parliament and of the Council of 16 April 2014 on the harmonisation of the laws of the Member States relating to the making available on the market of radio equipment and repealing Directive 1999/5/EC | M72: 1. This Directive establishes a regulatory framework for the making available on the market and putting into service in the Union of radio equipment. 2. This Directive shall not apply to equipment listed in Annex I. 3. This Directive shall not apply to radio equipment exclusively used for activities concerning public security, defence, State security, including the economic well-being of the State in the case of activities pertaining to State security matters, and the activities of the State in the area of criminal law. 4. Radio equipment falling within the scope of this Directive shall not be subject to Directive 2014/35/EU, except as set out in point (a) of Article 3(1) of this Directive. | N72: 41730 | O72: 42887 | Q72: 1216_Directive 2014-53-EU | R72: https://lis9-svdol10.vnet.valeo.com:1201/dwa/rm/urn:rational:67c31aaa-786d-11e4-943f-77f7170acf6c:1-43463251374b73b7-M-0006e525 | V72: Product Marking Testing Documentation (e.g. Datasheet; Drawing, FMEA,..)
A73: 69 | B73: Undefined | C73: GUIDELINE | D73: DRS - ULS & ECU DVS - Vision System DRS - Radar ECU w WIFI/Bluetooth | E73: Europe ITU Region 1 ITU Region 3 | F73: C | K73: Guide to the appl. of harmonised standards acc. directive 2014/53/EU | L73: Guide to the application of harmonised standards covering articles 3.1b and 3.2 of the Directive 2014/53/EU (RED) to multi-radio and combined radio and non-radio equipment | M73: The document provides guidance on the application of harmonised standards to multi-radio and combined equipment to demonstrate conformity with article 3.1b (EMC) and article 3.2 (effective and efficient use of the radio spectrum) of the Radio Equipment Directive (RED) i.1. | N73: 42522 | Q73: - no module available - | R73: http://www.etsi.org/deliver/etsi_eg/203300_203399/203367/01.01.01_60/eg_203367v010101p.pdf
A74: 240 | B74: Undefined | K74: 3.2.2 Short Range Radar 24 GHz Range
A75: 146 | B75: Undefined | C75: REGULATION | D75: DRS - Radar ECU w WIFI/Bluetooth | E75: USA ITU Region 2 | F75: B | J75: Radio Emission | K75: Title 47 §15.245 24 GHz range (24.075-24.175) | L75: Operation within the bands 902-928 MHz, 2435-2465 MHz, 5785-5815 MHz, 10500-10550 MHz, and 24075-24175 MHz | M75: 24 GHz range (24.075-24.175) | N75: 42644 | O75: 37865 | Q75: 12121_FCC_Part15_Radio_frequency_Devices | R75: https://lis9-svdol10.vnet.valeo.com:1201/dwa/rm/urn:rational:67c31aaa-786d-11e4-943f-77f7170acf6c:1-43463251374b73b7-M-0006e53a | V75: Testing Documentation (e.g. Datasheet; Drawing, FMEA,..)
A76: 147 | B76: Undefined | C76: REGULATION | D76: DRS - Radar ECU w WIFI/Bluetooth | E76: USA ITU Region 2 | F76: B | J76: Radio Emission | K76: Title 47 §15.249 24 GHz range (24.0-24.25) | L76: Operation within the bands 902-928 MHz, 2400-2483.5 MHz, 5725-5875 MHZ, and 24.0-24.25 GHz | M76: 24 GHz range (24.0-24.25) | N76: 42644 | O76: 40940 | Q76: 12121_FCC_Part15_Radio_frequency_Devices | R76: https://lis9-svdol10.vnet.valeo.com:1201/dwa/rm/urn:rational:67c31aaa-786d-11e4-943f-77f7170acf6c:1-43463251374b73b7-M-0006e53a | V76: Testing Documentation (e.g. Datasheet; Drawing, FMEA,..)
A77: 189 | B77: Undefined | C77: REGULATION | D77: DRS - Radar ECU w WIFI/Bluetooth | E77: Europe ITU Region 1 | F77: B | J77: Radio Emission | K77: 2005/50/EC 24GHz Range 24,15 +/– 2,50 GHz | L77: COMMISSION DECISION of 17 January 2005 on the harmonisation of the 24 GHz range radio spectrum band for the time-limited use by automotive short-range radar equipment in the Community | M77: The purpose of this Decision is to harmonise the conditions for the availability and efficient use of the 24 GHz range radio spectrum band for automotive short-range radar equipment. | N77: 43040 | O77: 43040 | Q77: 12139_Decision 2005_50_EC_24GHz_Range | R77: https://drive.google.com/file/d/1sjAs9WDwGIgzJQ1bCfBv5SEAmcKaE6Td/view | V77: Testing Documentation (e.g. Datasheet; Drawing, FMEA,..)
A78: 188 | B78: Undefined | C78: REGULATION | D78: DRS - Radar ECU w WIFI/Bluetooth | E78: Europe ITU Region 1 | F78: B | J78: Radio Emission | K78: 2013/752/EU Radio Spectrum amending 2006/771/EC | L78: COMMISSION IMPLEMENTING DECISION of 11 December 2013 amending Decision 2006/771/EC on harmonisation of the radio spectrum for use by short-range devices and repealing Decision 2005/928/EC | M78: Commission Decision 2006/771/EC (2) harmonises the technical conditions for use of spectrum for a wide variety of short-range devices, including applications such as alarms, local communications equipment, door openers, medical implants and for intelligent transport systems. Short-range devices are typically mass-market and/or portable products which can easily be taken and used across borders; | N78: 41609 | O78: 41883 | Q78: - no module available - | R78: https://drive.google.com/file/d/1NzU-kyRtgXUPqSEdGtw9gpl7Bxgk3dbn/view | V78: Testing Documentation (e.g. Datasheet; Drawing, FMEA,..)
A79: 241 | B79: Undefined | K79: 3.2.3 Short Range Radar 79 GHz Range
A80: 148 | B80: Undefined | C80: REGULATION | D80: DRS - Radar ECU w WIFI/Bluetooth | E80: USA ITU Region 2 | F80: B | J80: Radio Emission | K80: Title 47 §95 76-81 GHz range | L80: Subpart M The 76–81 GHz Band Radar Service | M80: This subpart sets out the regulations that apply to radar systems operating in the 76–81 GHz band. This subpart does not apply to Level Probing Radars that operate under part 15 of this title. | O80: 43009 | Q80: 12150_CFR 47 Part95 Subpart M_76-81 GHz Band Radar Service | R80: https://lis9-svdol10.vnet.valeo.com:1201/dwa/rm/urn:rational:67c31aaa-786d-11e4-943f-77f7170acf6c:1-43463251374b73b7-M-0006e535 | V80: Testing Documentation (e.g. Datasheet; Drawing, FMEA,..)
A81: 195 | B81: Undefined | C81: REGULATION | D81: DRS - Radar ECU w WIFI/Bluetooth | E81: Europe ITU Region 1 | F81: B | J81: Radio Emission | K81: 2004/545/EC 79GHz range 77-81 GHz | L81: COMMISSION DECISION of 8 July 2004 on the harmonisation of radio spectrum in the 79 GHz range for the use of automotive short-range radar equipment in the Community | M81: The purpose of this Decision is to harmonise the conditions for the availability and efficient use of the 79 GHz range radio spectrum band for automotive short-range radar equipment. "Article 3 The maximum mean power density shall be of – 3 dBm/MHz effective isotropic radiated power (e.i.r.p.) associated with a peak limit of 55 dBm e.i.r.p. The maximum mean power density outside a vehicle resulting from the operation of one short-range radar shall not exceed – 9 dBm/MHz e.i.r.p." | N81: 38139 | O81: 38139 | Q81: 12156_Decision_2004_545_EC_79GHz range | R81: https://lis9-svdol10.vnet.valeo.com:1201/dwa/rm/urn:rational::1-43463251374b73b7-M-00081b5b | V81: Testing Documentation (e.g. Datasheet; Drawing, FMEA,..)
A82: 302 | B82: Undefined | D82: DRS - Solid State Lidar DRS - Laserscanner | K82: 3.2.4 Laser Emissions
A83: 151 | B83: Undefined | C83: HN STANDARD | D83: DRS - Solid State Lidar DRS - Laserscanner | E83: Worldwide | F83: B | J83: Laser | K83: EN ISO 11252:2013 | L83: Lasers and laser-related equipment - Laser device - Minimum requirements for documentation (ISO 11252:2013) | M83: ISO 11252:2013 specifies the minimum documentation, marking and labelling for all laser products classified in accordance with IEC 60825-1 including laser diodes and all laser devices defined in ISO 11145. It is applicable to laser systems being integrated in a laser product in accordance with IEC 60825-1 and laser devices being integrated in a laser unit or processing machine in accordance with ISO 11553-1 and ISO 11553-2. ISO 11252:2013 specifies requirements for technical data sheets and information for the user. The requirements in ISO 11252:2013 augment but do not supersede any of the requirements in IEC 60825-1. | N83: 41487 | Q83: - only on Pronorm - | R83: http://lis9-svprp01.vnet.valeo.com:8092/mlogin.pl?search=e6:DE30051434 | V83: Documentation (e.g. Datasheet; Drawing, FMEA,..)
A84: 156 | B84: Undefined | C84: HN STANDARD | D84: DRS - Solid State Lidar DRS - Laserscanner | E84: Worldwide | F84: B | J84: Laser | K84: IEC 60825-1 Edition 3, 2014 | L84: Safety of laser products - Part 1: Equipment classification and requirements | M84: IEC 60825-1 is applicable to safety of laser products emitting laser radiation in the wavelength range 180 nm to 1 mm. | N84: 41760 | Q84: - only on Pronorm - | R84: http://lis9-svprp01.vnet.valeo.com:8092/mlogin.pl?search=e6:IX45628641 | V84: Product Marking Testing Documentation (e.g. Datasheet; Drawing, FMEA,..) Type Approval
A85: 193 | B85: Undefined | C85: REGULATION | D85: DRS - Solid State Lidar DRS - Laserscanner | E85: North America USA | F85: B | J85: Laser | K85: Title 21 §1040 Laser Products | L85: Laser Products | M85: The provisions of this section and §1040.11, as amended, are applicable as specified to all laser products manufactured or assembled after August 1, 1976, | N85: 42826 | O85: 40269 | Q85: 12138_CFR 21 Section 1040 Laser Products | R85: https://drive.google.com/file/d/1OItaKE4YQjV67tHzVrd-Ste2v6Tn_u--/view | S85: refer to FDA Laser Scanner Requirements https://docs.google.com/spreadsheets/d/1xR9PNiIQDzKieUCWsl16PUp2U-lixE5lYnRIvm4PjTI/edit?usp=drive_open&ouid=115910244335210838264 | V85: Product Marking Documentation (e.g. Datasheet; Drawing, FMEA,..)
A86: 227 | B86: Undefined | K86: 3.3 Product Safety Regulations
A87: 56 | B87: Undefined | C87: REGULATION | D87: DRS - ULS & ECU DRS - Radar ECU w WIFI/Bluetooth | E87: Europe | F87: A | J87: EMC | K87: 2014/30/EU Harmonisation of EMC laws | L87: Directive 2014/30/EU of the European Parliament and of the Council of 26 February 2014 on the harmonisation of the laws of the Member States relating to electromagnetic compatibility (recast) | M87: This Directive regulates the electromagnetic compatibility of equipment. It aims to ensure the functioning of the internal market by requiring equipment to comply with an adequate level of electromagnetic compatibility. Relevant only for Aftermarket Products | N87: 41671 | Q87: 1286_2014-30-EU_EMC | R87: https://lis9-svdol10.vnet.valeo.com:1201/dwa/rm/urn:rational:67c31aaa-786d-11e4-943f-77f7170acf6c:1-43463251374b73b7-M-0006e521 | V87: Documentation (e.g. Datasheet; Drawing, FMEA,..)
A88: 95 | B88: Undefined | C88: REGULATION | D88: DRS - Radar ECU w WIFI/Bluetooth | E88: Europe | F88: A | J88: Safety | K88: 2014/35/EU Harmonisation of electrical equipment within voltage limits | L88: Directive 2014/35/EU of the European Parliament and of the Council of 26 February 2014 on the harmonisation of the laws of the Member States relating to the making available on the market of electrical equipment designed for use within certain voltage limits | M88: The purpose of this Directive is to ensure that electrical equipment on the market fulfils the requirements providing for a high level of protection of health and safety of persons, and of domestic animals and property, while guaranteeing the functioning of the internal market. This Directive shall apply to electrical equipment designed for use with a voltage rating of between 50 and 1 000 V for alternating current and between 75 and 1 500 V for direct current, other than the equipment and phenomena listed in Annex II. | N88: 41671 | Q88: 1289_2014_34_EU_LowVoltage | R88: https://lis9-svdol10.vnet.valeo.com:1201/dwa/rm/urn:rational:67c31aaa-786d-11e4-943f-77f7170acf6c:1-43463251374b73b7-M-0006e524 | V88: Documentation (e.g. Datasheet; Drawing, FMEA,..)
A89: 177 | B89: Undefined | C89: REGULATION | D89: Transversal/ Generic | E89: Europe | F89: A | H89: Covered by Valeo Process | J89: Safety | K89: 2001/95/EC General Product Safety | L89: DIRECTIVE 2001/95/EC OF THE EUROPEAN PARLIAMENT AND OF THE COUNCIL of 3 December 2001 on general product safety | M89: Products placed on the EU market must be safe. They must bear information enabling them to be traced, such as the manufacturer’s identity and a product reference. Where necessary for safe use, products must be accompanied by warnings and information about any inherent risks. A product is considered safe if it meets specific national requirements or EU standards. If no such requirements or standards exist, the safety assessment must be based on: - Commission guidelines, - best practice in the sector concerned, - state of the art and technology, - reasonable consumer safety expectations. | N89: 39965 | Q89: 12127_2001_95_EC_General Product Safety | S89: Simple Process House https://siph.appengine.valeo.com/home | T89: [CDA] RD_<Project Name> Environmental Test Plan | V89: Documentation (e.g. Datasheet; Drawing, FMEA,..)
A90: 155 | B90: Undefined | C90: REGULATION | D90: DRS - ULS & ECU | E90: USA ITU Region 2 | F90: A | J90: Safety | K90: Title 47 §18 ISM Equipment | L90: INDUSTRIAL, SCIENTIFIC, AND MEDICAL EQUIPMENT | M90: ISM equipment shall be designed and constructed in accordance with good engineering practice with sufficient shielding and filtering to provide adequate suppression of emissions on frequencies outside the frequency bands specified in § 18.301. | N90: 42644 | O90: 42248 | Q90: 12114_FCC_Part18_ISM | V90: Documentation (e.g. Datasheet; Drawing, FMEA,..)
A91: 192 | B91: Undefined | C91: REGULATION | D91: DRS - Solid State Lidar DRS - Laserscanner | E91: North America USA | F91: A | J91: Safety | K91: Title 21 §1010 General | L91: PERFORMANCE STANDARDS FOR ELECTRONIC PRODUCTS: GENERAL | M91: The standards listed in this sub-chapter are prescribed pursuant to section 534 of Subchapter C—Electronic Product Radiation Control of the Federal Food, Drug, and Cosmetic Act (formerly the Radiation Control for Health and Safety Act of 1968) (21 U.S.C. 360kk) and are applicable to electronic products as specified herein, to control electronic product radiation from such products. Standards so prescribed are subject to amendment or revocation and additional standards may be prescribed as are determined necessary for the protection of the public health and safety. | N91: 42826 | O91: 39600 | Q91: 12152_CFR 21 Section 1010 General | R91: https://drive.google.com/file/d/1x7a0nCalJFtuGgpqtNGaX-uQh15vxpM4/view | V91: Documentation (e.g. Datasheet; Drawing, FMEA,..)
A92: 448 | B92: Undefined | C92: REGULATION | D92: DVS - Vision System DVS - Viewing Camera | E92: India | F92: B | J92: Safety | K92: IS 616 : 2017 / IEC 60065 : 2014 "Electronics and IT Goods (Requirement of Compulsory Registration) Order, 2012" | L92: Compulsory Registration Order (CRO) | M92: Specifically applicable to automotiv cameras: (iv) The finished cameras being used in automotive are covered under the scope of CRO. (v) The cameras, if imported as integral part of the vehicle, would not attract the provisions of CRO. (vi) The notified goods in open form /which do not have a specific model number are not covered under the Order. | V92: Product Marking Certification
A93: 244 | B93: Undefined | K93: 3.4 General Material Restrictions
A94: 89 | B94: Undefined | C94: REGULATION | D94: Transversal/ Generic | E94: Europe | F94: A | G94: Yes | H94: Covered by Valeo Process | J94: Materials | K94: 2011/65/EU Restriction of Hazardous Substances (RoHS) for electrical equipment | L94: DIRECTIVE 2011/65/EU OF THE EUROPEAN PARLIAMENT AND OF THE COUNCIL of 8 June 2011 on the restriction of the use of certain hazardous substances in electrical and electronic equipment | M94: This Directive lays down rules on the restriction of the use of hazardous substances in electrical and electronic equipment (EEE) with a view to contributing to the protection of human health and the environment, including the environmentally sound recovery and disposal of waste EEE. Restriction of following chemicals: - Cadmium(Cd) and its compounds: 0.01% - Mercury and its compounds: 0.1% - Lead(Pb) and its compounds : 0.1% - Hexavalent chromium (Cr6+) and its compounds: 0.1% - Polybrominated biphenyls (PBB): 0.1 %; - Polybrominated diphenyl ethers (PBDE): 0.1 % | N94: 40695 | Q94: 12116_2011_65_EU_RoHS | S94: (IMDS) GSP-RD-H01-0538 GSP-RD-H01-0538-C01_IMDS procedure_RELEASED | T94: IMDS REPORT from MDS -> export to be provided by Q PTM or Mech PTM | V94: Documentation (e.g. Datasheet; Drawing, FMEA,..) Covered by Platform/metiers Standards
A95: 161 | B95: Undefined | C95: REGULATION | D95: Transversal/ Generic | E95: Europe | F95: A | G95: Yes | H95: Covered by Valeo Process | J95: Materials | K95: EC 1907/2006 Registration, Evaluation, Authorisation and Restriction of Chemicals (REACH) | L95: Regulation (EC) No 1907/2006 of the European Parliament and of the Council of 18 December 2006 concerning the Registration, Evaluation, Authorisation and Restriction of Chemicals (REACH), establishing a European Chemicals Agency, amending Directive 1999/45/EC and repealing Council Regulation (EEC) No 793/93 and Commission Regulation (EC) No 1488/94 as well as Council Directive 76/769/EEC and Commission Directives 91/155/EEC, 93/67/EEC, 93/105/EC and 2000/21/EC | N95: 31.08.2017 | Q95: 1241_CE No 1907-2006 | S95: (IMDS) GSP-RD-H01-0538 GSP-RD-H01-0538-C01_IMDS procedure_RELEASED | T95: IMDS REPORT from MDS -> export to be provided by Q PTM or Mech PTM | V95: Documentation (e.g. Datasheet; Drawing, FMEA,..) Covered by Platform/metiers Standards
A96: 198 | B96: Undefined | C96: REGULATION | D96: Transversal/ Generic | E96: Europe | F96: A | G96: Yes | H96: Covered by Valeo Process | J96: Materials | K96: 2000/53/EC End of life vehicles | L96: DIRECTIVE 2000/53/EC OF THE EUROPEAN PARLIAMENT AND OF THE COUNCIL of 18 September 2000 on end-of life vehicles | M96: A maximum concentration value up to 0,1 % by weight in homogeneous material for lead, hexavalent chromium and mercury and up to 0,01 % by weight in homogeneous material for cadmium shall be tolerated. Spare parts put on the market after 1 July 2003 which are used for vehicles put on the market before 1 July 2003, except for wheel balance weights, carbon brushes for electric motors and brake linings, shall be exempted from the provisions of Article 4(2)(a) of Directive 2000/53/EC. | N96: 43040 | O96: 43070 | Q96: 12135_2000_53_EC_End of life vehicles_Consolidated Version 11-2017 | S96: (IMDS) GSP-RD-H01-0538 GSP-RD-H01-0538-C01_IMDS procedure_RELEASED | T96: IMDS REPORT from MDS -> export to be provided by Q PTM or Mech PTM | V96: Documentation (e.g. Datasheet; Drawing, FMEA,..) Covered by Platform/metiers Standards
A97: 376 | B97: Undefined | C97: REGULATION | D97: Transversal/ Generic | E97: Europe | F97: A | J97: Materials | K97: 2012/19/EU Directive, WEEE -- Aftermarket -- | L97: DIRECTIVE 2012/19/EU OF THE EUROPEAN PARLIAMENT AND OF THE COUNCIL of 4 July 2012 on waste electrical and electronic equipment (WEEE) | M97: This Directive lays down measures to protect the environment and human health by preventing or reducing the adverse impacts of the generation and management of waste from electrical and electronic equipment (WEEE) and by reducing overall impacts of resource use and improving the efficiency of such use in accordance with Articles 1 and 4 of Directive 2008/98/EC, thereby contributing to sustainable development. | N97: 43282 | V97: Product Marking Documentation (e.g. Datasheet; Drawing, FMEA,..)
A98: 303 | B98: Undefined | C98: REGULATION | D98: Transversal/ Generic | E98: China | F98: C | G98: Yes | H98: Covered By Platform | J98: Materials | K98: GB/T 26572-2011 China-RoHS - Covered via IMDS / EU RoHS - | L98: Requirements on concentration limits for certain restricted substances in electrical and electronic products | N98: 40878 | Q98: - no module available - | S98: (IMDS) GSP-RD-H01-0538 https://sites.google.com/a/valeo.com/group-procedures/group-procedures?filterM=GSP-RD-H01-0538 | V98: Covered by Platform/metiers Standards
A99: 228 | B99: Undefined | K99: 3.5 Automotive Specific
A100: 229 | B100: Undefined | K100: 3.5.1 Framework Regulations
A101: 116 | B101: Undefined | D101: Transversal/ Generic | E101: North America Canada | F101: C | K101: Canadian Motor Vehicle Safety Standards Related to the FMVSS of the United States of America. But deviations in legislations might be possible. For Canada also UN Regulations are recognized as alternative proof of compliance.
A102: 154 | B102: Undefined | C102: REGULATION | D102: Transversal/ Generic | E102: North America USA | F102: C | K102: Federal Motor Vehicle Safety Standards (FMVSS) Title 49 Transportation §566 Manufacturer Identification | L102: Manufacturer Identification | M102: This part requires manufacturers of motor vehicles, and of motor vehicle equipment to which a motor vehicle safety standard applies, to submit identifying information and a description of the items they produce. | Q102: - no module available -
A103: 351 | B103: Undefined | C103: REGULATION | D103: Transversal/ Generic | E103: Europe | F103: A | H103: Covered by Valeo Process | J103: Type Approval | K103: Regulation (EU) 2018/858 | L103: Regulation (EU) 2018/858 of the European Parliament and of the Council of 30 May 2018 on the approval and market surveillance of motor vehicles and their trailers, and of systems, components and separate technical units intended for such vehicles, amending Regulations (EC) No 715/2007 and (EC) No 595/2009 and repealing Directive 2007/46/EC | M103: This Regulation lays down the administrative provisions and technical requirements for the type-approval and placing on the market of all new vehicles, systems, components and separate technical units, referred to in Article 2(1), and for individual vehicle approvals. This Regulation also lays down provisions for the placing on the market and the entry into service of parts and equipment that may pose a serious risk to the correct functioning of the essential systems of the vehicles referred to in Article 2(1) | N103: 43221 | O103: 44075 | Q103: 12160_Regulation 2018_858_EU | S103: Type Approval Process Description https://sites.google.com/valeo.com/cdvnr/norms-regulations/processes-and-guidelines-areg-certifications?authuser=0 | T103: Conformity of Production/ Market Surveillance --> SPPC --> Tracking Sheet from Quality/ Test Lab [CDA] QA_<Project Name> SYS/SW QA Checklist | V103: Documentation (e.g. Datasheet; Drawing, FMEA,..) Type Approval
A104: 352 | B104: Yes | C104: REGULATION | D104: Transversal/ Generic | E104: Europe | F104: C | J104: Type Approval | K104: (EU) 2019/2144 Revision of the General Safety Regulation | L104: Regulation (EU) 2019/2144 of the European Parliament and of the Council of 27 November 2019 on type-approval requirements for motor vehicles and their trailers, and systems, components and separate technical units intended for such vehicles, as regards their general safety and the protection of vehicle occupants and vulnerable road users | M104: This Regulation applies to vehicles of categories M, N and O, as defined in Article 4 of Regulation (EU) 2018/858, and to systems, components and separate technical units designed and constructed for such vehicles. | O104: 44743 | Q104: 12169_Regulation _EU_2019_2144_General Safety Regulation | V104: Customer Responsibility (Customer Requirements reflect regulation) | W104: depends on project scope and related technical regulation of the specified function
A105: 305 | B105: Undefined | C105: REGULATION | D105: Transversal/ Generic | E105: India | F105: C | K105: The Central Motor Vehicles Rules, 1989 - compliance to India achieved via UN Regulations - | L105: CHAPTER V CONSTRUCTION, EQUIPMENT AND MAINTENANCE OF MOTOR VEHICLES | M105: 92. General.– ... (3) Whenever a part, component or assembly is used in a vehicle complying with standards in lieu of those notified in these rules such as an international standard (for example, EEC/ECE/IEC/ISO or such other standards) or a foreign national standard, permission for use of such parts, component or assembly complying with such standards shall be approved by the Central Government. In such cases, the compliance of parts, components or assemblies to such international or foreign national standards will be established for the purpose of rule1 26, by a certificate of compliance issued by an authorized certifying agency or by an accredited certifying agency of the country of origin for such international or foreign national standards and vetted by a testing agency as referred to in rule 126.] | N105: 43344 | Q105: - no module available - | W105: depends on project scope and related technical regulation of the specified function
A106: 395 | B106: Undefined | C106: REGULATION | D106: Transversal/ Generic | E106: Korea, Republik of | F106: C | K106: Korean Motor Vehicle Safety Standards (KMVSS) - Performance requirements equal UN Vehicle Regulations, exceptions possible - | L106: Regulations for Performance and Safety Standards of Motor Vehicle and Vehicle Parts | M106: The purpose of the Regulations is to establish the safety standards and self-certification standards for vehicles applicable to the structures and systems of motor vehicles and two-wheeled motor vehicles, and the standards and methods applicable to the safety and the Safety Compliance Test of vehicles, their parts or systems | N106: 43800 | Q106: 12180_KR_KMVSS_complete_EN_2020-06-05 | V106: Others | W106: depends on project scope and related technical regulation of the specified function
A107: 230 | B107: Undefined | K107: 3.5.2 Material Restrictions and Requirements
A108: 304 | B108: Undefined | C108: GUIDELINE | D108: DRS - RLT DRS - ULS & ECU DVS - Vision System DVS - Viewing Camera DVS - ECU & Domain Controller DRS - Radar DFC - Front Camera DRS - Solid State Lidar DRS - Laserscanner DFC - Zone Controller ECU w WIFI/Bluetooth | E108: Worldwide | F108: A | G108: Yes | H108: Covered by Valeo Process | J108: Materials | K108: Global Automotive Declarable Substance List (GADSL) -- covered via IMDS (International Material Data System) -- | L108: Global Automotive Declarable Substance List (GADSL) (Reference Document) | M108: Banned substances: General, comprehensive; Hazardous substances | Q108: - no module available - | S108: (IMDS) GSP-RD-H01-0538 GSP-RD-H01-0538-C01_IMDS procedure_RELEASED | T108: IMDS REPORT from MDS -> export to be provided by Q PTM or Mech PTM | V108: Documentation (e.g. Datasheet; Drawing, FMEA,..) Covered by Platform/metiers Standards
A109: 83 | B109: Yes | C109: REGULATION | D109: DRS - RLT DRS - ULS & ECU DVS - Vision System DVS - Viewing Camera DVS - ECU & Domain Controller DRS - Radar DFC - Front Camera DRS - Solid State Lidar DRS - Laserscanner DFC - Zone Controller ECU w WIFI/Bluetooth | E109: UN ECE | F109: C | J109: Materials | K109: UN Regulation No. 133 | L109: Uniform provisions concerning the approval of motor vehicles with regard to their reusability, recyclability and recoverability | M109: Regulation is addressed to vehicle manufacturer -> Vehicle mass and material management (85-95%)/ recyclbility of single E/E componentes not defined in detail "The vehicle manufacturer shall be required to demonstrate that, through contractual arrangements with his suppliers, management of material and substance restrictions for not allowed applications of lead, mercury, cadmium, hexavalent chromium is ensured." Electronic control units and sensors shall not be reused in new cars EU Directive 2000/53/EC defines specific limits of the restricted materials. | N109: 41791 | O109: 41791 | Q109: 1256_ECE R133 | S109: (IMDS) GSP-RD-H01-0538 https://sites.google.com/a/valeo.com/group-procedures/group-procedures?filterM=GSP-RD-H01-0538 | V109: Documentation (e.g. Datasheet; Drawing, FMEA,..)
A110: 361 | B110: Undefined | C110: REGULATION | D110: DRS - RLT DFC - Front Camera | E110: USA | F110: A | J110: Flammability | K110: Title 49 Transportation §571.302 Flammability | L110: Flammability of interior materials. | M110: This standard specifies burn resistance requirements for materials used in the occupant compartments of motor vehicles. | N110: 2011 | Q110: 1208_FMVSS 302 | V110: Testing Documentation (e.g. Datasheet; Drawing, FMEA,..) | W110: Testing is optional; Documentation about materials flammability is sufficient
A111: 521 | B111: Undefined | C111: REGULATION | D111: DRS - RLT DFC - Front Camera | F111: C | J111: Flammability | K111: UN Regulation No. 118 | L111: Uniform technical prescriptions concerning the burning behaviour and/or the capability to repel fuel or lubricant of materials used in the construction of certain categories of motor vehicles | M111: This Regulation applies to the burning behaviour (ignitibility, burning rate and melting behaviour) and to the capability to repel fuel or lubricants of materials used in vehicles of categories M3, Classes II and III1 | N111: 2018 | P111: M3 (Bus >5t) | Q111: - no module available - | V111: Testing Documentation (e.g. Datasheet; Drawing, FMEA,..) | W111: Testing is optional; Documentation about materials flammability is sufficient
A112: 362 | B112: Undefined | C112: REGULATION | D112: DRS - RLT DFC - Front Camera | E112: China | F112: A | J112: Flammability | K112: GB 8410-2006 | L112: Flammability of automotive interior materials | M112: This standard specifies the technical requirements and test methods of horizontal flammability of automotive interior materials. | Q112: 12123_GB 8410-2006_Flammability of Automotive Interior Materials | V112: Testing Documentation (e.g. Datasheet; Drawing, FMEA,..) | W112: Testing is optional; Documentation about materials flammability is sufficient
A113: 554 | B113: Yes | C113: REGULATION | D113: DRS - Laserscanner | E113: UN ECE | F113: B | J113: Materials | K113: UN Regulation No. 43 - Safety glazing | L113: Uniform provisions concerning the approval of safety glazing materials and their installation on vehicles | M113: Scope This Regulation applies to: (a) Safety glazing materials intended for installation as windscreens or other panes, or as partitioning, on vehicles of category L with bodywork, M, N, O, and T; 1) (b) Vehicles of categories M, N and O with regard to the installation of these materials; In both cases, to the exclusion of: (i) Glazing for lighting and light-signalling devices, instrument panels, special bullet-proof glazing and double-windows; (ii) Small plastic glazing that is not required for either the driver's forward or rearward field of vision. | N113: 03-2023 Suppl.10 to 01 | O113: 45078 | V113: Testing Documentation (e.g. Datasheet; Drawing, FMEA,..)
A114: 231 | B114: Undefined | K114: 3.5.3 General & passiv safety
A115: 261 | B115: Undefined | C115: REGULATION | D115: N/A | E115: UN ECE | F115: C | J115: Passive Safety | K115: UN Regulation No. 21 | L115: Uniform provisions concerning the approval of vehicles with regard to their interior fittings | M115: This regulation applies to the interior fittings of passenger cars with regard to the arrangement of controls, the roof and the sliding roof, and the seat-back and the rear parts of seats. - not applicable for CDV --> CIC Database | N115: Rev2 09-1986
A116: 176 | B116: Yes | C116: REGULATION | D116: DRS - ULS & ECU DVS - Vision System DVS - Viewing Camera DRS - Solid State Lidar DRS - Laserscanner | E116: UN ECE | F116: A | J116: Passive Safety | K116: UN Regulation No. 26 | L116: Uniform provisions concerning the approval of vehicles with regard to their external projections | M116: The purpose of this Regulation is to reduce the risk or seriousness of bodily injury to a person hit by the bodywork or brushing against it in the event of a collision. This is valid both when the vehicle is stationary and in motion | N116: Rev1 08-2013 | O116: 42217 | Q116: 12126_UN ECE R26r1 External Projections | V116: Documentation (e.g. Datasheet; Drawing, FMEA,..) Customer Responsibility (Customer Requirements reflect regulation) | W116: Depending on installation location on the vehicle body, product housing/ outer design should not have sharp edges
A117: 186 | B117: Yes | C117: REGULATION | D117: DRS - ULS & ECU DVS - Vision System DVS - Viewing Camera DRS - Solid State Lidar DRS - Laserscanner | E117: UN ECE | F117: C | J117: Passive Safety | K117: UN Regulation No. 26 Amendment 1 | L117: Uniform provisions concerning the approval of vehicles with regard to their external projections | M117: The purpose of this Regulation is to reduce the risk or seriousness of bodily injury to a person hit by the bodywork or brushing against it in the event of a collision. This is valid both when the vehicle is stationary and in motion | N117: Rev1_Am1 06-2016 | O117: 42522 | Q117: 12141_UN ECE R26r1 Am1 External Projections | V117: Documentation (e.g. Datasheet; Drawing, FMEA,..) Customer Responsibility (Customer Requirements reflect regulation) | W117: Depending on installation location on the vehicle body, product housing/ outer design should not have sharp edges
A118: 162 | B118: Undefined | C118: REGULATION | D118: Transversal/ Generic | E118: USA | F118: C | J118: Passive Safety | K118: Title 49 Transportation §581 Bumper Standard | L118: Bumper Standard | M118: This standard establishes requirements for the impact resistance of vehicles in low speed front and rear collisions. -- sensing equipment made as base equipment of vehicle located within or behind bumper need to consider the perpendicular test -- | N118: 43009 | O118: 35947 | Q118: 12158_CFR 49 Part 581 Bumber Standard | R118: https://drive.google.com/file/d/1srRO18LzjDr6JHCKg2HlNaZ3OJRmyLds/view | V118: Customer Responsibility (Customer Requirements reflect regulation) | W118: Mostly bracket dependend, regulation requirements do not define performance of sensing equipment after test. Passive Safety against vulnarable road users is the main scope.
A119: 134 | B119: Undefined | C119: REGULATION | D119: DVS - Vision System DVS - Viewing Camera | E119: China | F119: C | J119: Passive Safety | K119: GB 11552-2009 | L119: The Interior Fittings of Passenger Cars | M119: Adaption of UN R21 Revision 2 For compliance refer to UN R21 | N119: 40057 | O119: 40909 | Q119: - no module available -
A120: 135 | B120: Undefined | C120: REGULATION | D120: Transversal/ Generic | E120: China | F120: C | J120: Passive Safety | K120: GB 4208-2008 | L120: Degrees of Protection Provided by Enclosure (IP Code) | M120: Adaption of IEC 60529:2001 For compliance refer to IEC 60529:2001 | N120: 39508 | O120: 39814 | Q120: - no module available - | R120: http://lis9-svprp01.vnet.valeo.com:8092/mlogin.pl?search=e6:IX45963640
A121: 232 | B121: Undefined | K121: 3.5.4 In-Vehicle Data
A122: 420 | B122: Yes | C122: REGULATION | D122: DVS - ECU & Domain Controller DFC - Front Camera DSW - LSMS (low speed) DSW - ADSP | E122: UN ECE | F122: B | J122: EDR | K122: UN Regulation No. 160 - EDR | L122: UN Regulation on uniform provisions concerning the approval of motor vehicles with regard to the Event Data Recorder | M122: The provisions concern the minimum collection, storage and crash survivability of motor vehicle crash event data. It does not include specifications for data retrieval tools and methods as that is subject to national/regional level requirement. The purpose of these provisions is to ensure that EDRs record, in a readily usable manner, data valuable for effective crash investigations and for analysis of safety equipment performance (e.g., advanced restraint systems). These data will help provide a better understanding of the circumstances in which crashes and injuries occur and will facilitate the development of safer vehicle designs. | N122: Rev1 10-2022 | O122: 07/2022 (EU-GSR) Series 1 - 07/2024 | Q122: 12322_UN Regulation 160 EDR_Consolidated | V122: Documentation (e.g. Datasheet; Drawing, FMEA,..)
A123: 559 | B123: Undefined | C123: REGULATION | D123: DFC - Front Camera DSW - ADSP | E123: China | F123: B | J123: EDR | K123: GB 39732-2020 | L123: Vehicle Event Data Recorder System. | M123: This standard specifies the terms and definitions, technical requirements, test methods and requirements, appearance and marking, vehicle type extension, and instructions of the event data recorder system for Category M1 vehicles. This standard applies to Category M1 vehicles equipped with event data recorder system. Other vehicles can refer to this standard | N123: 44166 | O123: 44562 | V123: Documentation (e.g. Datasheet; Drawing, FMEA,..)
A124: 560 | B124: Undefined | C124: STANDARD | D124: DFC - Front Camera DSW - ADSP | E124: China | F124: C | I124: DFC Platform: Not a provided feature by Camera (e.g. resulotion is not matching the std) -> not applicable | J124: EDR/ DVR | K124: GB/T 38892-2020 | L124: On-board driving video recording system | M124: This standard stipulates the requirements and test methods of on-board driving video recording system. This standard is applicable for the on-board driving video recording system (hereinafter referred to as the system) of category M1 vehicles. For systems used on other categories of vehicles, this standard may also apply. | N124: 43983 | O124: 44166
A125: 234 | B125: Undefined | K125: 3.5.5 Controls and Displays
A126: 179 | B126: Undefined | C126: REGULATION | D126: DSW - LSMS (low speed) DSW - ADSP | E126: UN ECE | F126: C | J126: HMI | K126: UN Regulation No. 121 | L126: Uniform provisions concerning the approval of vehicles with regard to the location and identification of hand controls, tell-tales and indicators | M126: This Regulation applies to vehicles of categories M and N. It specifies requirements for the location, identification, colour, and illumination of motor vehicle hand controls, tell-tales and indicators. It is designed to ensure the accessibility and visibility of vehicle controls, tell-tales and indicators, and to facilitate their selection under daylight and night-time conditions, in order to reduce the safety hazards caused by the diversion of the driver's attention from the driving task and by mistakes in selecting controls. | N126: Rev2 11-2015 | O126: 43040 | Q126: 12125_UN ECE R121r2_HMI | V126: Customer Responsibility (Customer Requirements reflect regulation)
A127: 180 | B127: Undefined | C127: REGULATION | D127: DSW - LSMS (low speed) DSW - ADSP | E127: UN ECE | F127: C | J127: HMI | K127: UN Regulation No. 121 Amendment 1 | L127: Uniform provisions concerning the approval of vehicles with regard to the location and identification of hand controls, tell-tales and indicators | M127: In Table 1, lines Nos. 2. and 19., add a reference to existing note 18. | N127: Rev2_Am1 06-2017 | O127: 42887 | Q127: 12153_UN ECE R121r2 Am1_HMI | V127: Customer Responsibility (Customer Requirements reflect regulation)
A128: 200 | B128: Undefined | C128: REGULATION | D128: DVS - ECU & Domain Controller DSW - LSMS (low speed) DSW - ADSP | E128: USA | F128: C | J128: HMI | K128: Title 49 Transportation §571.101 FMVSS Standard No. 101 | L128: Controls and displays | M128: This standard specifies performance requirements for location, identification, color, and illumination of motor vehicle controls, telltales and indicators. Similarities to UN R 121 | N128: 42644 | O128: 41518 | Q128: 12113_FMVSS_571.101_Controls_Display 2016 Version__ | V128: Customer Responsibility (Customer Requirements reflect regulation)
A129: 233 | B129: Undefined | K129: 3.5.6 Electrical & Electronic
A130: 338 | B130: Undefined | K130: 3.5.6.1 Electromagnetic Compatibility
A131: 400 | B131: Yes | C131: REGULATION | D131: DRS - RLT DRS - ULS & ECU DVS - Vision System DVS - Viewing Camera DVS - ECU & Domain Controller DRS - Radar DFC - Front Camera DRS - Solid State Lidar DRS - Laserscanner DFC - Zone Controller ECU w WIFI/Bluetooth | E131: UN ECE | F131: A | G131: Yes | H131: Covered by Valeo Process | J131: EMC | K131: UN Regulation No. 10 | L131: Uniform provisions concerning the approval of vehicles with regard to electromagnetic compatibility | M131: It covers: (a) Requirements regarding the immunity to radiated and conducted disturbances for functions related to direct control of the vehicle, related to driver, passenger and other road users' protection, related to disturbances, which would cause confusion to the driver or other road users, related to vehicle data bus functionality, related to disturbances, which would affect vehicle statutory data; (b) Requirements regarding the control of unwanted radiated and conducted emissions to protect the intended use of electrical or electronic equipment at own or adjacent vehicles or nearby, and the control of disturbances from accessories that may be retrofitted to the vehicle. (c) Additional requirements for vehicles and ESAs providing coupling systems for charging the REESS regarding the control of emissions and immunity from this connection between vehicle and power grid. | N131: Rev6 10-2019 | O131: 44805 | Q131: 12176_UN Regulation 10_Rev.6_EMC | S131: GSI-RD-H01-0852 | T131: GEEDS_EMC-temp-PT-001-B | V131: Product Marking Testing Documentation (e.g. Datasheet; Drawing, FMEA,..) Customer Responsibility (Customer Requirements reflect regulation) Type Approval Covered by Platform/metiers Standards | W131: Responsibility for type approval needs to be clarified with customer, dependend on responsibility type approval might be necessary
A132: 309 | B132: Undefined | C132: REGULATION | D132: DRS - RLT DRS - ULS & ECU DVS - Vision System DVS - Viewing Camera DVS - ECU & Domain Controller DRS - Radar DFC - Front Camera DRS - Solid State Lidar DRS - Laserscanner DFC - Zone Controller | E132: China | F132: A | J132: EMC | K132: GB 34660-2017 | L132: Road vehicles – Requirements and test methods of electromagnetic compatibility | M132: This Standard specifies the electromagnetic emission limits, immunity performance and test procedures for vehicles and their electrical/electronic sub-assemblies. | N132: 43101 | O132: 44197 | Q132: 12144_CN_GB_34660-2017_EN_2018-09-03 | S132: GSI-RD-H01-0852 | V132: Testing Documentation (e.g. Datasheet; Drawing, FMEA,..) Customer Responsibility (Customer Requirements reflect regulation)
A133: 140 | B133: Undefined | C133: REGULATION | D133: DRS - RLT DRS - ULS & ECU DVS - Vision System DVS - Viewing Camera DVS - ECU & Domain Controller DRS - Radar DFC - Front Camera DRS - Solid State Lidar DFC - Zone Controller | E133: China | F133: C | J133: EMC | K133: GB/T 17619-1998 -- adaptaion of R10 -- | L133: Limits and Methods of Testing for Immunity of Electrical/Electronic Sub-assemblies in Vehicles to Electromagnetic Radiation. | M133: This Standard adopts the relevant specifications specified in the EEC Directive 95/54/EC (1995) “Electromagnetic Compatibility of Motor Vehicles”: the limits of immunity to electromagnetic radiation are equivalent to the immunity thresholds for the electrical/electronic sub-assemblies of vehicle set out in Annex 1, while the methods of measurement are equivalent to those specified in Annex IX. | N133: 36130 | O133: 36495 | Q133: - no module available - | S133: GSI-RD-H01-0852 | V133: Documentation (e.g. Datasheet; Drawing, FMEA,..) Customer Responsibility (Customer Requirements reflect regulation)
A134: 173 | B134: Undefined | C134: REGULATION | D134: DRS - RLT DRS - ULS & ECU DVS - Vision System DVS - Viewing Camera DVS - ECU & Domain Controller DRS - Radar DFC - Front Camera DRS - Solid State Lidar DRS - Laserscanner DFC - Zone Controller | E134: India | F134: C | J134: EMC | K134: AIS 004 (Part 3)/2009 incl. Amendment 1 | L134: Automotive Vehicles Requirements for Electromagnetic Compatibility | M134: This standard AIS-004 (Part 3) is prepared in line with R 10 Rev. 3. | N134: 07-2009 Am1_04-2015 | O134: 04_2015 | Q134: 12136_AIS-004 Part 3_EMC | S134: GSI-RD-H01-0852 | V134: Documentation (e.g. Datasheet; Drawing, FMEA,..) Customer Responsibility (Customer Requirements reflect regulation)
A135: 339 | B135: Undefined | K135: 3.5.6.2 Radio Disturbance Characteristics
A136: 136 | B136: Undefined | C136: REGULATION | D136: DRS - Radar | E136: China | F136: A | J136: EMC | K136: GB 14023-2011 -- relevant for aftermarket -- | L136: Radio Disturbance Characteristics Limits and Methods of Measurement (IEC/CISPR 12:2009, IDT) | M136: Adaption of IEC/ CISPR 12:2009 | N136: 40725 | O136: 40909 | Q136: 12131_GB 14023-2011 | S136: GSI-RD-H01-0852 | V136: Product Marking Testing Documentation (e.g. Datasheet; Drawing, FMEA,..) Type Approval
A137: 139 | B137: Undefined | C137: REGULATION | D137: N/A | E137: China | F137: C | J137: EMC | K137: GB/T 18387-2017 -- Only Applicable on Vehicle level -- | L137: Limits and Test Methods of Magnetic and Electric Field Strength from Electric Vehicles | M137: This Standard specifies the limits of the electric field and magnetic field emission intensity and the test methods for the vehicles. The test frequency shall be within the range of 150kHz to 30MHz. This Standard is applicable to the blade electric vehicles, hybrid electric vehicles, fuel cell electric vehicles and other types of electric vehicles. | N137: 42856 | O137: 43070 | Q137: - no module available - | V137: Customer Responsibility (Customer Requirements reflect regulation)
A138: 337 | B138: Undefined | C138: REGULATION | D138: Transversal/ Generic | E138: China | F138: C | J138: EMC | K138: GB/T 18655-2018 -- adaptation of CISPR 25:2016, MOD -- | L138: Radio disturbance characteristics – Limits and methods of measurement for the protection of on-board receivers | M138: This Standard specifies the disturbance limit and test methods of radio from 150 kHz - 2500MHz. This Standard is applicable to any electronic / electrical parts for vehicles, trailers and devices. The detailed frequency distribution stated in this Standard refers to the publications issued by the International Telecommunications Union (ITU) and its actual application in China. The limit specified in this Standard is intended to protect on-board receiver from the disturbance generated by the parts / modules inside the same vehicle | N138: 43497 | Q138: - no module available - | R138: http://lis9-svprp01.vnet.valeo.com:8092/mlogin.pl?search=e6:IX88459750 | V138: Customer Responsibility (Customer Requirements reflect regulation)
A139: 557 | B139: Undefined | K139: 3.5.7 Product/ Component Specific
A140: 558 | B140: Undefined | C140: STANDARD | D140: DRS - ULS & ECU | E140: China | F140: B | K140: GB/T 41484-2022 | L140: Automotive ultrasonic sensor assembly | M140: This document specifies the requirements, test methods and inspection rules for ultrasonic sensor assemblies for automobiles. This document is applicable to the ultrasonic sensor assembly (hereinafter referred to as assembly) used in automobiles. | N140: 44652 | O140: 44866 | V140: Testing Documentation (e.g. Datasheet; Drawing, FMEA,..)
A141: 548 | B141: Undefined | K141: 3.5.8 Other Vehicle Systems
...

Sheet Doc Overview
A1: m | C1: Regulations, norms and standards for DOORS transfer
Q2: GDRIVE | R2: AUREON | W2: ='CDV2 DTL'!A1 -> 14.08.2025 | X2: 03.03.2023 | AC2: Transversal | AD2: DVS System | AG2: DSW_Computer Vision | AJ2: DVS_Camera | AM2: Domain Controller/ECU (purly HW&Mechtronik) | AP2: DRS_RLT | AS2: DRS_ULS&ECU | AV2: DRS_Radar | AY2: DAS-Laser | BB2: DFC (Zone Controller) | BE2: DFC (Front Camera) | BH2: DSF_ADSP | BK2: DSF LSMS | BN2: Comment Status | BO2: Info
A3: Entry Date | B3: ID | C3: Item | D3: Priority | E3: Transfer Status | F3: Official Title/ Regulation Number | G3: Sub Title | H3: Scope | I3: Change information | J3: EU/GSR ADAS Marker | K3: Details | L3: Amendment Level | M3: Official Publication Date | N3: Legal Enforcement | O3: Vehicle Cat. | P3: Market | Q3: Document | R3: Aureon Link | S3: Pages | T3: Type of DOC: | U3: Module Name | V3: CDV1 | W3: CDV2 entered | X3: CDV 3 entered | Y3: Status | Z3: Comment Status | AA3: Plattform Allocation | AB3: Analyses/ Matrix | AC3: GENERIC | AD3: Applicable | AE3: deployed? | AF3: Responsible Expert | AG3: Applicable | AH3: deployed? | AI3: Responsible Expert | AJ3: Applicable | AK3: deployed? | AL3: Responsible Expert | AM3: Applicable | AN3: deployed?/ listed in TT metrics | AO3: Responsible Expert | AP3: Applicable | AQ3: deployed? | AR3: Responsible Expert | AS3: Applicable | AT3: deployed? | AU3: Responsible Expert | AV3: Applicable | AW3: deployed? | AX3: Responsible Expert | AY3: Applicable | AZ3: deployed? | BA3: Responsible Expert | BB3: Applicable | BC3: deployed? | BD3: Responsible Expert | BE3: Applicable | BF3: deployed? | BG3: Responsible Expert | BH3: Applicable | BI3: deployed? | BJ3: Responsible Expert | BK3: Applicable | BL3: deployed? | BM3: Responsible Expert
B4: REG_5 | C4: 1 | D4: high | E4: 10/10: Closed | H4: =VLOOKUP(U4,'CDV3 DTL'!E:G,2,FALSE) -> #N/A | O4: all | P4: UN | Q4: =HYPERLINK("https://drive.google.com/open?id=1jO2NDa-5_qi9OJp5wCn7zaV6xchAb5Uy","UN ECE R46_Devices for Indirect Vision Rev6") -> UN ECE R46_Devices for Indirect Vision Rev6 | S4: 90 | T4: Regulations | U4: 1205_ECE_R046 | W4: =IF(VLOOKUP(U4,'CDV2 DTL'!P:P,1,FALSE)=U4,"OK","Missing") -> OK | X4: =IF(VLOOKUP(U4,'CDV3 DTL'!E:E,1,FALSE)=U4,"OK","Missing") -> #N/A | AD4: x | AE4: =IF(AD4="x",VLOOKUP($U4,DVS!A:A,1,FALSE),"-") -> #N/A | AJ4: x | AN4: =IF(AM4="x",VLOOKUP($U4,'Domain ControllerECU'!A:A,1,FALSE),"-") -> - | AQ4: =IF(AP4="x",VLOOKUP($U4,RLT!A:A,1,FALSE),"-") -> - | AT4: =IF(AS4="x",VLOOKUP($U4,ULSECU!A:A,1,FALSE),"-") -> - | AW4: =IF(AV4="x",VLOOKUP($U4,'Radar 7779GHz'!A:A,1,FALSE),"-") -> - | AZ4: =IF(AY4="x",VLOOKUP($U4,LiDAR!A:A,1,FALSE),"-") -> - | BF4: =IF(BE4="x",VLOOKUP($U4,DFC!A:A,1,FALSE),"-") -> - | BI4: =IF(BH4="x",VLOOKUP(U4,'DSF ADSP'!A:A,1,FALSE),"-") -> - | BL4: =IF(BK4="x",VLOOKUP($U4,'DSF LSMS'!$A:$A,1,FALSE),"-") -> -
B5: REG_55 | C5: 2 | D5: normal | E5: Obsolete | H5: =VLOOKUP(U5,'CDV3 DTL'!E:G,2,FALSE) -> #N/A | P5: UN | Q5: =HYPERLINK("https://drive.google.com/open?id=1QOugWYCegJDbTpPi2fK5Sg6T0O0rPEba","UN ECE R10_EMC") -> UN ECE R10_EMC | S5: 140 | T5: Regulations | U5: (-) | W5: =IF(VLOOKUP(U5,'CDV2 DTL'!P:P,1,FALSE)=U5,"OK","Missing") -> #N/A | X5: =IF(VLOOKUP(U5,'CDV3 DTL'!E:E,1,FALSE)=U5,"OK","Missing") -> #N/A | AE5: =IF(AD5="x",VLOOKUP($U5,DVS!A:A,1,FALSE),"-") -> - | AN5: =IF(AM5="x",VLOOKUP($U5,'Domain ControllerECU'!A:A,1,FALSE),"-") -> - | AQ5: =IF(AP5="x",VLOOKUP($U5,RLT!A:A,1,FALSE),"-") -> - | AT5: =IF(AS5="x",VLOOKUP($U5,ULSECU!A:A,1,FALSE),"-") -> - | AW5: =IF(AV5="x",VLOOKUP($U5,'Radar 7779GHz'!A:A,1,FALSE),"-") -> - | AZ5: =IF(AY5="x",VLOOKUP($U5,LiDAR!A:A,1,FALSE),"-") -> - | BF5: =IF(BE5="x",VLOOKUP($U5,DFC!A:A,1,FALSE),"-") -> - | BI5: =IF(BH5="x",VLOOKUP(U5,'DSF ADSP'!A:A,1,FALSE),"-") -> - | BL5: =IF(BK5="x",VLOOKUP($U5,'DSF LSMS'!$A:$A,1,FALSE),"-") -> -
B6: REG_62 | C6: 3 | D6: low | E6: Obsolete | H6: =VLOOKUP(U6,'CDV3 DTL'!E:G,2,FALSE) -> #N/A | P6: EU | Q6: ETSI EN 301 091-1 V2.1.1 | S6: 18 | T6: HN-Std | U6: (-) | W6: =IF(VLOOKUP(U6,'CDV2 DTL'!P:P,1,FALSE)=U6,"OK","Missing") -> #N/A | X6: =IF(VLOOKUP(U6,'CDV3 DTL'!E:E,1,FALSE)=U6,"OK","Missing") -> #N/A | AE6: =IF(AD6="x",VLOOKUP($U6,DVS!A:A,1,FALSE),"-") -> - | AN6: =IF(AM6="x",VLOOKUP($U6,'Domain ControllerECU'!A:A,1,FALSE),"-") -> - | AQ6: =IF(AP6="x",VLOOKUP($U6,RLT!A:A,1,FALSE),"-") -> - | AT6: =IF(AS6="x",VLOOKUP($U6,ULSECU!A:A,1,FALSE),"-") -> - | AV6: x | AW6: =IF(AV6="x",VLOOKUP($U6,'Radar 7779GHz'!A:A,1,FALSE),"-") -> #N/A | AZ6: =IF(AY6="x",VLOOKUP($U6,LiDAR!A:A,1,FALSE),"-") -> - | BF6: =IF(BE6="x",VLOOKUP($U6,DFC!A:A,1,FALSE),"-") -> - | BI6: =IF(BH6="x",VLOOKUP(U6,'DSF ADSP'!A:A,1,FALSE),"-") -> - | BL6: =IF(BK6="x",VLOOKUP($U6,'DSF LSMS'!$A:$A,1,FALSE),"-") -> -
B7: REG_68 | C7: 4 | D7: high | E7: 10/10: Closed | H7: =VLOOKUP(U7,'CDV3 DTL'!E:G,2,FALSE) -> #N/A | O7: all | P7: UN | Q7: =HYPERLINK("https://drive.google.com/open?id=1DlHEwJ8yZ1ogHpl0J_JCfQ9Rsq2ueyvV","UN ECE R48_Light&Signaling") -> UN ECE R48_Light&Signaling | S7: 131 | T7: Regulations | U7: 1268_UN ECE R48_Light_Signaling | W7: =IF(VLOOKUP(U7,'CDV2 DTL'!P:P,1,FALSE)=U7,"OK","Missing") -> #N/A | X7: =IF(VLOOKUP(U7,'CDV3 DTL'!E:E,1,FALSE)=U7,"OK","Missing") -> #N/A | AE7: =IF(AD7="x",VLOOKUP($U7,DVS!A:A,1,FALSE),"-") -> - | AN7: =IF(AM7="x",VLOOKUP($U7,'Domain ControllerECU'!A:A,1,FALSE),"-") -> - | AP7: x | AQ7: =IF(AP7="x",VLOOKUP($U7,RLT!A:A,1,FALSE),"-") -> #N/A | AT7: =IF(AS7="x",VLOOKUP($U7,ULSECU!A:A,1,FALSE),"-") -> - | AW7: =IF(AV7="x",VLOOKUP($U7,'Radar 7779GHz'!A:A,1,FALSE),"-") -> - | AZ7: =IF(AY7="x",VLOOKUP($U7,LiDAR!A:A,1,FALSE),"-") -> - | BE7: x | BF7: =IF(BE7="x",VLOOKUP($U7,DFC!A:A,1,FALSE),"-") -> #N/A | BI7: =IF(BH7="x",VLOOKUP(U7,'DSF ADSP'!A:A,1,FALSE),"-") -> - | BL7: =IF(BK7="x",VLOOKUP($U7,'DSF LSMS'!$A:$A,1,FALSE),"-") -> -
B8: REG_86 | C8: 5 | D8: low | E8: 10/10: Closed | H8: =VLOOKUP(U8,'CDV3 DTL'!E:G,2,FALSE) -> #N/A | P8: EU | Q8: =HYPERLINK("https://drive.google.com/open?id=1RvzHOhWplUUiBHJr2H1-ReL0h44JniRM","2014/30/EU_EMC") -> 2014/30/EU_EMC | S8: 28 | T8: Regulations | U8: 1286_2014-30-EU_EMC | W8: =IF(VLOOKUP(U8,'CDV2 DTL'!P:P,1,FALSE)=U8,"OK","Missing") -> OK | X8: =IF(VLOOKUP(U8,'CDV3 DTL'!E:E,1,FALSE)=U8,"OK","Missing") -> #N/A | AE8: =IF(AD8="x",VLOOKUP($U8,DVS!A:A,1,FALSE),"-") -> - | AN8: =IF(AM8="x",VLOOKUP($U8,'Domain ControllerECU'!A:A,1,FALSE),"-") -> - | AQ8: =IF(AP8="x",VLOOKUP($U8,RLT!A:A,1,FALSE),"-") -> - | AT8: =IF(AS8="x",VLOOKUP($U8,ULSECU!A:A,1,FALSE),"-") -> - | AW8: =IF(AV8="x",VLOOKUP($U8,'Radar 7779GHz'!A:A,1,FALSE),"-") -> - | AZ8: =IF(AY8="x",VLOOKUP($U8,LiDAR!A:A,1,FALSE),"-") -> - | BF8: =IF(BE8="x",VLOOKUP($U8,DFC!A:A,1,FALSE)," ") | BI8: =IF(BH8="x",VLOOKUP(U8,'DSF ADSP'!A:A,1,FALSE),"-") -> - | BL8: =IF(BK8="x",VLOOKUP($U8,'DSF LSMS'!$A:$A,1,FALSE),"-") -> -
B9: REG_88 | C9: 6 | D9: low | E9: Obsolete | H9: =VLOOKUP(U9,'CDV3 DTL'!E:G,2,FALSE) -> #N/A | P9: EU | Q9: ETSI EN 302 264 V2.1.1 | S9: 17 | T9: HN-Std | U9: (-) | W9: =IF(VLOOKUP(U9,'CDV2 DTL'!P:P,1,FALSE)=U9,"OK","Missing") -> #N/A | X9: =IF(VLOOKUP(U9,'CDV3 DTL'!E:E,1,FALSE)=U9,"OK","Missing") -> #N/A | AE9: =IF(AD9="x",VLOOKUP($U9,DVS!A:A,1,FALSE),"-") -> - | AN9: =IF(AM9="x",VLOOKUP($U9,'Domain ControllerECU'!A:A,1,FALSE),"-") -> - | AQ9: =IF(AP9="x",VLOOKUP($U9,RLT!A:A,1,FALSE),"-") -> - | AT9: =IF(AS9="x",VLOOKUP($U9,ULSECU!A:A,1,FALSE),"-") -> - | AV9: x | AW9: =IF(AV9="x",VLOOKUP($U9,'Radar 7779GHz'!A:A,1,FALSE),"-") -> #N/A | AZ9: =IF(AY9="x",VLOOKUP($U9,LiDAR!A:A,1,FALSE),"-") -> - | BF9: =IF(BE9="x",VLOOKUP($U9,DFC!A:A,1,FALSE),"-") -> - | BI9: =IF(BH9="x",VLOOKUP(U9,'DSF ADSP'!A:A,1,FALSE),"-") -> - | BL9: =IF(BK9="x",VLOOKUP($U9,'DSF LSMS'!$A:$A,1,FALSE),"-") -> -
B10: REG_89 | C10: 7 | D10: low | E10: 10/10: Closed | H10: =VLOOKUP(U10,'CDV3 DTL'!E:G,2,FALSE) -> #N/A | P10: EU | Q10: =HYPERLINK("https://drive.google.com/open?id=1fC1zpmhiQ9jxEyqhVR-AbvhsINmXYOYI","2014/35/EU_LowVoltage") -> 2014/35/EU_LowVoltage | S10: 18 | T10: Regulations | U10: 1289_2014_34_EU_LowVoltage | W10: =IF(VLOOKUP(U10,'CDV2 DTL'!P:P,1,FALSE)=U10,"OK","Missing") -> OK | X10: =IF(VLOOKUP(U10,'CDV3 DTL'!E:E,1,FALSE)=U10,"OK","Missing") -> #N/A | AE10: =IF(AD10="x",VLOOKUP($U10,DVS!A:A,1,FALSE),"-") -> - | AN10: =IF(AM10="x",VLOOKUP($U10,'Domain ControllerECU'!A:A,1,FALSE),"-") -> - | AQ10: =IF(AP10="x",VLOOKUP($U10,RLT!A:A,1,FALSE),"-") -> - | AT10: =IF(AS10="x",VLOOKUP($U10,ULSECU!A:A,1,FALSE),"-") -> - | AW10: =IF(AV10="x",VLOOKUP($U10,'Radar 7779GHz'!A:A,1,FALSE),"-") -> - | AZ10: =IF(AY10="x",VLOOKUP($U10,LiDAR!A:A,1,FALSE),"-") -> - | BF10: =IF(BE10="x",VLOOKUP($U10,DFC!A:A,1,FALSE),"-") -> - | BI10: =IF(BH10="x",VLOOKUP(U10,'DSF ADSP'!A:A,1,FALSE),"-") -> - | BL10: =IF(BK10="x",VLOOKUP($U10,'DSF LSMS'!$A:$A,1,FALSE),"-") -> -
B11: REG_90 | C11: 8 | D11: low | E11: 10/10: Closed | H11: =VLOOKUP(U11,'CDV3 DTL'!E:G,2,FALSE) -> #N/A | K11: Annex 8 for safety assessment, to be applied if breaking function is not related to AEB | O11: all | P11: UN | Q11: =HYPERLINK("https://drive.google.com/open?id=1VuiQ3S3nKkfKCPEmNCSu-7QjNbIVSaSe","UN ECE R13_Braking") -> UN ECE R13_Braking | S11: 97 | T11: Regulations | U11: 1290_UN ECE R13_Braking | W11: =IF(VLOOKUP(U11,'CDV2 DTL'!P:P,1,FALSE)=U11,"OK","Missing") -> OK | X11: =IF(VLOOKUP(U11,'CDV3 DTL'!E:E,1,FALSE)=U11,"OK","Missing") -> #N/A | AA11: DSF | AD11: X | AE11: =IF(AD11="x",VLOOKUP($U11,DVS!A:A,1,FALSE),"-") -> #N/A | AN11: =IF(AM11="x",VLOOKUP($U11,'Domain ControllerECU'!A:A,1,FALSE),"-") -> - | AQ11: =IF(AP11="x",VLOOKUP($U11,RLT!A:A,1,FALSE),"-") -> - | AT11: =IF(AS11="x",VLOOKUP($U11,ULSECU!A:A,1,FALSE),"-") -> - | AW11: =IF(AV11="x",VLOOKUP($U11,'Radar 7779GHz'!A:A,1,FALSE),"-") -> - | AZ11: =IF(AY11="x",VLOOKUP($U11,LiDAR!A:A,1,FALSE),"-") -> - | BE11: x | BF11: =IF(BE11="x",VLOOKUP($U11,DFC!A:A,1,FALSE),"-") -> #N/A | BH11: x | BI11: =IF(BH11="x",VLOOKUP(U11,'DSF ADSP'!A:A,1,FALSE),"-") -> #N/A | BK11: x | BL11: =IF(BK11="x",VLOOKUP($U11,'DSF LSMS'!$A:$A,1,FALSE),"-") -> #N/A | BM11: DSF LSMS Braking Team akram.ghadieh@valeo.com
B12: REG_91 | C12: 9 | D12: low | E12: Obsolete | H12: =VLOOKUP(U12,'CDV3 DTL'!E:G,2,FALSE) -> #N/A | P12: China | Q12: =HYPERLINK("https://drive.google.com/open?id=1vRlOc7Za6XRNeLV4n9mkTkxmGaSo2nDa","GB/T 18655-2010") -> GB/T 18655-2010 | S12: 136 | T12: Standard | U12: (-) | W12: =IF(VLOOKUP(U12,'CDV2 DTL'!P:P,1,FALSE)=U12,"OK","Missing") -> #N/A | X12: =IF(VLOOKUP(U12,'CDV3 DTL'!E:E,1,FALSE)=U12,"OK","Missing") -> #N/A | AE12: =IF(AD12="x",VLOOKUP($U12,DVS!A:A,1,FALSE),"-") -> - | AN12: =IF(AM12="x",VLOOKUP($U12,'Domain ControllerECU'!A:A,1,FALSE),"-") -> - | AQ12: =IF(AP12="x",VLOOKUP($U12,RLT!A:A,1,FALSE),"-") -> - | AT12: =IF(AS12="x",VLOOKUP($U12,ULSECU!A:A,1,FALSE),"-") -> - | AW12: =IF(AV12="x",VLOOKUP($U12,'Radar 7779GHz'!A:A,1,FALSE),"-") -> - | AZ12: =IF(AY12="x",VLOOKUP($U12,LiDAR!A:A,1,FALSE),"-") -> - | BF12: =IF(BE12="x",VLOOKUP($U12,DFC!A:A,1,FALSE),"-") -> - | BI12: =IF(BH12="x",VLOOKUP(U12,'DSF ADSP'!A:A,1,FALSE),"-") -> - | BL12: =IF(BK12="x",VLOOKUP($U12,'DSF LSMS'!$A:$A,1,FALSE),"-") -> -
B13: REG_92 | C13: 10 | D13: low | E13: Obsolete | H13: =VLOOKUP(U13,'CDV3 DTL'!E:G,2,FALSE) -> #N/A | P13: EU | Q13: =HYPERLINK("https://drive.google.com/open?id=1BtYMnrBX3F77DDYbynUSu4GCbPcTpSjJ","REGULATION (EC) No 78/2009") -> REGULATION (EC) No 78/2009 | S13: 38 | T13: Regulations | U13: (-) | W13: =IF(VLOOKUP(U13,'CDV2 DTL'!P:P,1,FALSE)=U13,"OK","Missing") -> #N/A | X13: =IF(VLOOKUP(U13,'CDV3 DTL'!E:E,1,FALSE)=U13,"OK","Missing") -> #N/A | AE13: =IF(AD13="x",VLOOKUP($U13,DVS!A:A,1,FALSE),"-") -> - | AN13: =IF(AM13="x",VLOOKUP($U13,'Domain ControllerECU'!A:A,1,FALSE),"-") -> - | AQ13: =IF(AP13="x",VLOOKUP($U13,RLT!A:A,1,FALSE),"-") -> - | AT13: =IF(AS13="x",VLOOKUP($U13,ULSECU!A:A,1,FALSE),"-") -> - | AV13: x | AW13: =IF(AV13="x",VLOOKUP($U13,'Radar 7779GHz'!A:A,1,FALSE),"-") -> #N/A | AZ13: =IF(AY13="x",VLOOKUP($U13,LiDAR!A:A,1,FALSE),"-") -> - | BF13: =IF(BE13="x",VLOOKUP($U13,DFC!A:A,1,FALSE),"-") -> - | BI13: =IF(BH13="x",VLOOKUP(U13,'DSF ADSP'!A:A,1,FALSE),"-") -> - | BL13: =IF(BK13="x",VLOOKUP($U13,'DSF LSMS'!$A:$A,1,FALSE),"-") -> -
B14: REG_93 | C14: 11 | D14: low | E14: 10/10: Closed | H14: =VLOOKUP(U14,'CDV3 DTL'!E:G,2,FALSE) -> #N/A | P14: EU | Q14: =HYPERLINK("https://drive.google.com/open?id=1NzU-kyRtgXUPqSEdGtw9gpl7Bxgk3dbn","Decision 2013/752/EU_ Radio Spectrum") -> Decision 2013/752/EU_ Radio Spectrum | S14: 20 | T14: Regulations | U14: 12146_SG_Master_Plan_Radio_Spectrum_2012-11_EN_2013-04-09 | W14: =IF(VLOOKUP(U14,'CDV2 DTL'!P:P,1,FALSE)=U14,"OK","Missing") -> OK | X14: =IF(VLOOKUP(U14,'CDV3 DTL'!E:E,1,FALSE)=U14,"OK","Missing") -> #N/A | AE14: =IF(AD14="x",VLOOKUP($U14,DVS!A:A,1,FALSE),"-") -> - | AN14: =IF(AM14="x",VLOOKUP($U14,'Domain ControllerECU'!A:A,1,FALSE),"-") -> - | AQ14: =IF(AP14="x",VLOOKUP($U14,RLT!A:A,1,FALSE),"-") -> - | AT14: =IF(AS14="x",VLOOKUP($U14,ULSECU!A:A,1,FALSE),"-") -> - | AV14: x | AW14: =IF(AV14="x",VLOOKUP($U14,'Radar 7779GHz'!A:A,1,FALSE),"-") -> #N/A | AZ14: =IF(AY14="x",VLOOKUP($U14,LiDAR!A:A,1,FALSE),"-") -> - | BF14: =IF(BE14="x",VLOOKUP($U14,DFC!A:A,1,FALSE),"-") -> - | BI14: =IF(BH14="x",VLOOKUP(U14,'DSF ADSP'!A:A,1,FALSE),"-") -> - | BL14: =IF(BK14="x",VLOOKUP($U14,'DSF LSMS'!$A:$A,1,FALSE),"-") -> -
B15: REG_94 | C15: 12 | D15: low | E15: 10/10: Closed | H15: =VLOOKUP(U15,'CDV3 DTL'!E:G,2,FALSE) -> #N/A | P15: UN | Q15: UN ECE R133_Recyclability | T15: Regulations | U15: 1256_ECE R133 | W15: =IF(VLOOKUP(U15,'CDV2 DTL'!P:P,1,FALSE)=U15,"OK","Missing") -> OK | X15: =IF(VLOOKUP(U15,'CDV3 DTL'!E:E,1,FALSE)=U15,"OK","Missing") -> #N/A | AE15: =IF(AD15="x",VLOOKUP($U15,DVS!A:A,1,FALSE),"-") -> - | AN15: =IF(AM15="x",VLOOKUP($U15,'Domain ControllerECU'!A:A,1,FALSE),"-") -> - | AQ15: =IF(AP15="x",VLOOKUP($U15,RLT!A:A,1,FALSE),"-") -> - | AT15: =IF(AS15="x",VLOOKUP($U15,ULSECU!A:A,1,FALSE),"-") -> - | AW15: =IF(AV15="x",VLOOKUP($U15,'Radar 7779GHz'!A:A,1,FALSE),"-") -> - | AZ15: =IF(AY15="x",VLOOKUP($U15,LiDAR!A:A,1,FALSE),"-") -> - | BF15: =IF(BE15="x",VLOOKUP($U15,DFC!A:A,1,FALSE),"-") -> - | BI15: =IF(BH15="x",VLOOKUP(U15,'DSF ADSP'!A:A,1,FALSE),"-") -> - | BL15: =IF(BK15="x",VLOOKUP($U15,'DSF LSMS'!$A:$A,1,FALSE),"-") -> -
B16: REG_95 | C16: 13 | D16: low | E16: Obsolete | H16: =VLOOKUP(U16,'CDV3 DTL'!E:G,2,FALSE) -> #N/A | P16: WW | Q16: =HYPERLINK("https://drive.google.com/open?id=1uuROqt9ClY44W6gkNpnPzbOCSLbDkG2B","IEC 60825-1_Edition3_Laser_Safety_Classification") -> IEC 60825-1_Edition3_Laser_Safety_Classification | S16: 224 | T16: Standard | W16: =IF(VLOOKUP(U16,'CDV2 DTL'!P:P,1,FALSE)=U16,"OK","Missing") -> #N/A | X16: =IF(VLOOKUP(U16,'CDV3 DTL'!E:E,1,FALSE)=U16,"OK","Missing") -> #N/A | AE16: =IF(AD16="x",VLOOKUP($U16,DVS!A:A,1,FALSE),"-") -> - | AN16: =IF(AM16="x",VLOOKUP($U16,'Domain ControllerECU'!A:A,1,FALSE),"-") -> - | AQ16: =IF(AP16="x",VLOOKUP($U16,RLT!A:A,1,FALSE),"-") -> - | AT16: =IF(AS16="x",VLOOKUP($U16,ULSECU!A:A,1,FALSE),"-") -> - | AW16: =IF(AV16="x",VLOOKUP($U16,'Radar 7779GHz'!A:A,1,FALSE),"-") -> - | AZ16: =IF(AY16="x",VLOOKUP($U16,LiDAR!A:A,1,FALSE),"-") -> - | BF16: =IF(BE16="x",VLOOKUP($U16,DFC!A:A,1,FALSE),"-") -> - | BI16: =IF(BH16="x",VLOOKUP(U16,'DSF ADSP'!A:A,1,FALSE),"-") -> - | BL16: =IF(BK16="x",VLOOKUP($U16,'DSF LSMS'!$A:$A,1,FALSE),"-") -> -
B17: REG_96 | C17: 14 | D17: low | E17: Obsolete | H17: =VLOOKUP(U17,'CDV3 DTL'!E:G,2,FALSE) -> #N/A | P17: EU | Q17: Restriction of Chemicals (REACH) Regulation EC1907/2006 | T17: Regulations | U17: (-) | W17: =IF(VLOOKUP(U17,'CDV2 DTL'!P:P,1,FALSE)=U17,"OK","Missing") -> #N/A | X17: =IF(VLOOKUP(U17,'CDV3 DTL'!E:E,1,FALSE)=U17,"OK","Missing") -> #N/A | AE17: =IF(AD17="x",VLOOKUP($U17,DVS!A:A,1,FALSE),"-") -> - | AN17: =IF(AM17="x",VLOOKUP($U17,'Domain ControllerECU'!A:A,1,FALSE),"-") -> - | AQ17: =IF(AP17="x",VLOOKUP($U17,RLT!A:A,1,FALSE),"-") -> - | AT17: =IF(AS17="x",VLOOKUP($U17,ULSECU!A:A,1,FALSE),"-") -> - | AW17: =IF(AV17="x",VLOOKUP($U17,'Radar 7779GHz'!A:A,1,FALSE),"-") -> - | AZ17: =IF(AY17="x",VLOOKUP($U17,LiDAR!A:A,1,FALSE),"-") -> - | BF17: =IF(BE17="x",VLOOKUP($U17,DFC!A:A,1,FALSE),"-") -> - | BI17: =IF(BH17="x",VLOOKUP(U17,'DSF ADSP'!A:A,1,FALSE),"-") -> - | BL17: =IF(BK17="x",VLOOKUP($U17,'DSF LSMS'!$A:$A,1,FALSE),"-") -> -
B18: REG_97 | C18: 15 | D18: low | E18: Obsolete | H18: =VLOOKUP(U18,'CDV3 DTL'!E:G,2,FALSE) -> #N/A | P18: Australia | Q18: =HYPERLINK("https://drive.google.com/open?id=19caAdQ0JNtoC6id-RD8m0sK4MmUIS46G","ANCAP AEB Vulnerable Road User Systems v2.0.2_Jan2018") -> ANCAP AEB Vulnerable Road User Systems v2.0.2_Jan2018 | S18: 37 | T18: Standard | W18: =IF(VLOOKUP(U18,'CDV2 DTL'!P:P,1,FALSE)=U18,"OK","Missing") -> #N/A | X18: =IF(VLOOKUP(U18,'CDV3 DTL'!E:E,1,FALSE)=U18,"OK","Missing") -> #N/A | AE18: =IF(AD18="x",VLOOKUP($U18,DVS!A:A,1,FALSE),"-") -> - | AN18: =IF(AM18="x",VLOOKUP($U18,'Domain ControllerECU'!A:A,1,FALSE),"-") -> - | AQ18: =IF(AP18="x",VLOOKUP($U18,RLT!A:A,1,FALSE),"-") -> - | AT18: =IF(AS18="x",VLOOKUP($U18,ULSECU!A:A,1,FALSE),"-") -> - | AW18: =IF(AV18="x",VLOOKUP($U18,'Radar 7779GHz'!A:A,1,FALSE),"-") -> - | AZ18: =IF(AY18="x",VLOOKUP($U18,LiDAR!A:A,1,FALSE),"-") -> - | BF18: =IF(BE18="x",VLOOKUP($U18,DFC!A:A,1,FALSE),"-") -> - | BI18: =IF(BH18="x",VLOOKUP(U18,'DSF ADSP'!A:A,1,FALSE),"-") -> - | BL18: =IF(BK18="x",VLOOKUP($U18,'DSF LSMS'!$A:$A,1,FALSE),"-") -> -
B19: REG_98 | C19: 16 | D19: low | E19: Obsolete | H19: =VLOOKUP(U19,'CDV3 DTL'!E:G,2,FALSE) -> #N/A | P19: Australia | Q19: =HYPERLINK("https://drive.google.com/open?id=168pfJavcMAOhVhjGtUsjU7OqJuG_yFBN","ANCAP Test Protocol_AEB_Car2Car_V2.0.1_Jan2018") -> ANCAP Test Protocol_AEB_Car2Car_V2.0.1_Jan2018 | S19: 25 | T19: Standard | W19: =IF(VLOOKUP(U19,'CDV2 DTL'!P:P,1,FALSE)=U19,"OK","Missing") -> #N/A | X19: =IF(VLOOKUP(U19,'CDV3 DTL'!E:E,1,FALSE)=U19,"OK","Missing") -> #N/A | AE19: =IF(AD19="x",VLOOKUP($U19,DVS!A:A,1,FALSE),"-") -> - | AN19: =IF(AM19="x",VLOOKUP($U19,'Domain ControllerECU'!A:A,1,FALSE),"-") -> - | AQ19: =IF(AP19="x",VLOOKUP($U19,RLT!A:A,1,FALSE),"-") -> - | AT19: =IF(AS19="x",VLOOKUP($U19,ULSECU!A:A,1,FALSE),"-") -> - | AW19: =IF(AV19="x",VLOOKUP($U19,'Radar 7779GHz'!A:A,1,FALSE),"-") -> - | AZ19: =IF(AY19="x",VLOOKUP($U19,LiDAR!A:A,1,FALSE),"-") -> - | BF19: =IF(BE19="x",VLOOKUP($U19,DFC!A:A,1,FALSE),"-") -> - | BI19: =IF(BH19="x",VLOOKUP(U19,'DSF ADSP'!A:A,1,FALSE),"-") -> - | BL19: =IF(BK19="x",VLOOKUP($U19,'DSF LSMS'!$A:$A,1,FALSE),"-") -> -
B20: REG_99 | C20: 17 | D20: low | E20: Obsolete | H20: =VLOOKUP(U20,'CDV3 DTL'!E:G,2,FALSE) -> #N/A | P20: Australia | Q20: =HYPERLINK("https://drive.google.com/open?id=1lQ8u3uH9pr--oSmj3BAofidQtOksEDBa","ANCAP Test Protocol_Lane Support Systems v2.0.1_Jan2018") -> ANCAP Test Protocol_Lane Support Systems v2.0.1_Jan2018 | S20: 19 | T20: Standard | W20: =IF(VLOOKUP(U20,'CDV2 DTL'!P:P,1,FALSE)=U20,"OK","Missing") -> #N/A | X20: =IF(VLOOKUP(U20,'CDV3 DTL'!E:E,1,FALSE)=U20,"OK","Missing") -> #N/A | AE20: =IF(AD20="x",VLOOKUP($U20,DVS!A:A,1,FALSE),"-") -> - | AN20: =IF(AM20="x",VLOOKUP($U20,'Domain ControllerECU'!A:A,1,FALSE),"-") -> - | AQ20: =IF(AP20="x",VLOOKUP($U20,RLT!A:A,1,FALSE),"-") -> - | AT20: =IF(AS20="x",VLOOKUP($U20,ULSECU!A:A,1,FALSE),"-") -> - | AW20: =IF(AV20="x",VLOOKUP($U20,'Radar 7779GHz'!A:A,1,FALSE),"-") -> - | AZ20: =IF(AY20="x",VLOOKUP($U20,LiDAR!A:A,1,FALSE),"-") -> - | BF20: =IF(BE20="x",VLOOKUP($U20,DFC!A:A,1,FALSE),"-") -> - | BI20: =IF(BH20="x",VLOOKUP(U20,'DSF ADSP'!A:A,1,FALSE),"-") -> - | BL20: =IF(BK20="x",VLOOKUP($U20,'DSF LSMS'!$A:$A,1,FALSE),"-") -> -
B21: REG_100 | C21: 18 | D21: low | E21: Obsolete | H21: =VLOOKUP(U21,'CDV3 DTL'!E:G,2,FALSE) -> #N/A | P21: Australia | Q21: =HYPERLINK("https://drive.google.com/open?id=1DgOYbbLfNavDnwmrKW718ntLNKMujrAi","ANCAP Test Protocol_Speed Assist Systems v2.0_Jan2018") -> ANCAP Test Protocol_Speed Assist Systems v2.0_Jan2018 | S21: 7 | T21: Standard | W21: =IF(VLOOKUP(U21,'CDV2 DTL'!P:P,1,FALSE)=U21,"OK","Missing") -> #N/A | X21: =IF(VLOOKUP(U21,'CDV3 DTL'!E:E,1,FALSE)=U21,"OK","Missing") -> #N/A | AE21: =IF(AD21="x",VLOOKUP($U21,DVS!A:A,1,FALSE),"-") -> - | AN21: =IF(AM21="x",VLOOKUP($U21,'Domain ControllerECU'!A:A,1,FALSE),"-") -> - | AQ21: =IF(AP21="x",VLOOKUP($U21,RLT!A:A,1,FALSE),"-") -> - | AT21: =IF(AS21="x",VLOOKUP($U21,ULSECU!A:A,1,FALSE),"-") -> - | AW21: =IF(AV21="x",VLOOKUP($U21,'Radar 7779GHz'!A:A,1,FALSE),"-") -> - | AZ21: =IF(AY21="x",VLOOKUP($U21,LiDAR!A:A,1,FALSE),"-") -> - | BF21: =IF(BE21="x",VLOOKUP($U21,DFC!A:A,1,FALSE),"-") -> - | BI21: =IF(BH21="x",VLOOKUP(U21,'DSF ADSP'!A:A,1,FALSE),"-") -> - | BL21: =IF(BK21="x",VLOOKUP($U21,'DSF LSMS'!$A:$A,1,FALSE),"-") -> -
B22: REG_101 | C22: 19 | D22: normal | E22: Obsolete | H22: =VLOOKUP(U22,'CDV3 DTL'!E:G,2,FALSE) -> #N/A | P22: USA | Q22: =HYPERLINK("https://drive.google.com/open?id=1ZkI7jtCOlc2mVVfwWxqpJvcPNbldq_gL","CNCAP_Regulation_2018") -> CNCAP_Regulation_2018 | S22: 223 | T22: Standard | W22: =IF(VLOOKUP(U22,'CDV2 DTL'!P:P,1,FALSE)=U22,"OK","Missing") -> #N/A | X22: =IF(VLOOKUP(U22,'CDV3 DTL'!E:E,1,FALSE)=U22,"OK","Missing") -> #N/A | AE22: =IF(AD22="x",VLOOKUP($U22,DVS!A:A,1,FALSE),"-") -> - | AN22: =IF(AM22="x",VLOOKUP($U22,'Domain ControllerECU'!A:A,1,FALSE),"-") -> - | AQ22: =IF(AP22="x",VLOOKUP($U22,RLT!A:A,1,FALSE),"-") -> - | AT22: =IF(AS22="x",VLOOKUP($U22,ULSECU!A:A,1,FALSE),"-") -> - | AW22: =IF(AV22="x",VLOOKUP($U22,'Radar 7779GHz'!A:A,1,FALSE),"-") -> - | AZ22: =IF(AY22="x",VLOOKUP($U22,LiDAR!A:A,1,FALSE),"-") -> - | BF22: =IF(BE22="x",VLOOKUP($U22,DFC!A:A,1,FALSE),"-") -> - | BI22: =IF(BH22="x",VLOOKUP(U22,'DSF ADSP'!A:A,1,FALSE),"-") -> - | BL22: =IF(BK22="x",VLOOKUP($U22,'DSF LSMS'!$A:$A,1,FALSE),"-") -> -
B23: REG_102 | C23: 20 | D23: normal | E23: Obsolete | H23: =VLOOKUP(U23,'CDV3 DTL'!E:G,2,FALSE) -> #N/A | P23: EU | Q23: =HYPERLINK("https://drive.google.com/open?id=1amwulMWQhSmoR9EFmpN89AUMkVlj8OCu","EUNCAP_AEB VRU V2.0.2") -> EUNCAP_AEB VRU V2.0.2 | S23: 43 | T23: Standard | W23: =IF(VLOOKUP(U23,'CDV2 DTL'!P:P,1,FALSE)=U23,"OK","Missing") -> #N/A | X23: =IF(VLOOKUP(U23,'CDV3 DTL'!E:E,1,FALSE)=U23,"OK","Missing") -> #N/A | AE23: =IF(AD23="x",VLOOKUP($U23,DVS!A:A,1,FALSE),"-") -> - | AN23: =IF(AM23="x",VLOOKUP($U23,'Domain ControllerECU'!A:A,1,FALSE),"-") -> - | AQ23: =IF(AP23="x",VLOOKUP($U23,RLT!A:A,1,FALSE),"-") -> - | AT23: =IF(AS23="x",VLOOKUP($U23,ULSECU!A:A,1,FALSE),"-") -> - | AW23: =IF(AV23="x",VLOOKUP($U23,'Radar 7779GHz'!A:A,1,FALSE),"-") -> - | AZ23: =IF(AY23="x",VLOOKUP($U23,LiDAR!A:A,1,FALSE),"-") -> - | BF23: =IF(BE23="x",VLOOKUP($U23,DFC!A:A,1,FALSE),"-") -> - | BI23: =IF(BH23="x",VLOOKUP(U23,'DSF ADSP'!A:A,1,FALSE),"-") -> - | BL23: =IF(BK23="x",VLOOKUP($U23,'DSF LSMS'!$A:$A,1,FALSE),"-") -> -
B24: REG_103 | C24: 21 | D24: normal | E24: Obsolete | H24: =VLOOKUP(U24,'CDV3 DTL'!E:G,2,FALSE) -> #N/A | P24: EU | Q24: =HYPERLINK("https://drive.google.com/open?id=1Wj6902mRWWgL9bmqup4pihgGhsopR6M5","EUNCAP_Lane Support Systems V2.0.1") -> EUNCAP_Lane Support Systems V2.0.1 | S24: 25 | T24: Standard | W24: =IF(VLOOKUP(U24,'CDV2 DTL'!P:P,1,FALSE)=U24,"OK","Missing") -> #N/A | X24: =IF(VLOOKUP(U24,'CDV3 DTL'!E:E,1,FALSE)=U24,"OK","Missing") -> #N/A | AE24: =IF(AD24="x",VLOOKUP($U24,DVS!A:A,1,FALSE),"-") -> - | AN24: =IF(AM24="x",VLOOKUP($U24,'Domain ControllerECU'!A:A,1,FALSE),"-") -> - | AQ24: =IF(AP24="x",VLOOKUP($U24,RLT!A:A,1,FALSE),"-") -> - | AT24: =IF(AS24="x",VLOOKUP($U24,ULSECU!A:A,1,FALSE),"-") -> - | AW24: =IF(AV24="x",VLOOKUP($U24,'Radar 7779GHz'!A:A,1,FALSE),"-") -> - | AZ24: =IF(AY24="x",VLOOKUP($U24,LiDAR!A:A,1,FALSE),"-") -> - | BF24: =IF(BE24="x",VLOOKUP($U24,DFC!A:A,1,FALSE),"-") -> - | BI24: =IF(BH24="x",VLOOKUP(U24,'DSF ADSP'!A:A,1,FALSE),"-") -> - | BL24: =IF(BK24="x",VLOOKUP($U24,'DSF LSMS'!$A:$A,1,FALSE),"-") -> -
B25: REG_104 | C25: 22 | D25: normal | E25: Obsolete | H25: =VLOOKUP(U25,'CDV3 DTL'!E:G,2,FALSE) -> #N/A | P25: EU | Q25: =HYPERLINK("https://drive.google.com/open?id=1YPT-qpgt6qIVv9pFfbW-ej32F3tT2Mvk","EUNCAP_Speed Assistant Systems V.2.0") -> EUNCAP_Speed Assistant Systems V.2.0 | S25: 7 | T25: Standard | W25: =IF(VLOOKUP(U25,'CDV2 DTL'!P:P,1,FALSE)=U25,"OK","Missing") -> #N/A | X25: =IF(VLOOKUP(U25,'CDV3 DTL'!E:E,1,FALSE)=U25,"OK","Missing") -> #N/A | AE25: =IF(AD25="x",VLOOKUP($U25,DVS!A:A,1,FALSE),"-") -> - | AN25: =IF(AM25="x",VLOOKUP($U25,'Domain ControllerECU'!A:A,1,FALSE),"-") -> - | AQ25: =IF(AP25="x",VLOOKUP($U25,RLT!A:A,1,FALSE),"-") -> - | AT25: =IF(AS25="x",VLOOKUP($U25,ULSECU!A:A,1,FALSE),"-") -> - | AW25: =IF(AV25="x",VLOOKUP($U25,'Radar 7779GHz'!A:A,1,FALSE),"-") -> - | AZ25: =IF(AY25="x",VLOOKUP($U25,LiDAR!A:A,1,FALSE),"-") -> - | BF25: =IF(BE25="x",VLOOKUP($U25,DFC!A:A,1,FALSE),"-") -> - | BI25: =IF(BH25="x",VLOOKUP(U25,'DSF ADSP'!A:A,1,FALSE),"-") -> - | BL25: =IF(BK25="x",VLOOKUP($U25,'DSF LSMS'!$A:$A,1,FALSE),"-") -> -
B26: REG_105 | C26: 23 | D26: normal | E26: Obsolete | H26: =VLOOKUP(U26,'CDV3 DTL'!E:G,2,FALSE) -> #N/A | P26: USA | Q26: =HYPERLINK("https://drive.google.com/open?id=1_qPEXc59JtE_pSdpFJKTU5jD9qT3wjQW","USNCAP_Crash imminent braking system ") -> USNCAP_Crash imminent braking system | S26: 60 | T26: Standard | W26: =IF(VLOOKUP(U26,'CDV2 DTL'!P:P,1,FALSE)=U26,"OK","Missing") -> #N/A | X26: =IF(VLOOKUP(U26,'CDV3 DTL'!E:E,1,FALSE)=U26,"OK","Missing") -> #N/A | AE26: =IF(AD26="x",VLOOKUP($U26,DVS!A:A,1,FALSE),"-") -> - | AN26: =IF(AM26="x",VLOOKUP($U26,'Domain ControllerECU'!A:A,1,FALSE),"-") -> - | AQ26: =IF(AP26="x",VLOOKUP($U26,RLT!A:A,1,FALSE),"-") -> - | AT26: =IF(AS26="x",VLOOKUP($U26,ULSECU!A:A,1,FALSE),"-") -> - | AW26: =IF(AV26="x",VLOOKUP($U26,'Radar 7779GHz'!A:A,1,FALSE),"-") -> - | AZ26: =IF(AY26="x",VLOOKUP($U26,LiDAR!A:A,1,FALSE),"-") -> - | BF26: =IF(BE26="x",VLOOKUP($U26,DFC!A:A,1,FALSE),"-") -> - | BI26: =IF(BH26="x",VLOOKUP(U26,'DSF ADSP'!A:A,1,FALSE),"-") -> - | BL26: =IF(BK26="x",VLOOKUP($U26,'DSF LSMS'!$A:$A,1,FALSE),"-") -> -
B27: REG_106 | C27: 24 | D27: normal | E27: Obsolete | H27: =VLOOKUP(U27,'CDV3 DTL'!E:G,2,FALSE) -> #N/A | P27: USA | Q27: =HYPERLINK("https://drive.google.com/open?id=166QXXED4Nwo7rOYuacaKvO0_16BUm0KC","USNCAP_Forward Collision Warning System") -> USNCAP_Forward Collision Warning System | S27: 40 | T27: Standard | W27: =IF(VLOOKUP(U27,'CDV2 DTL'!P:P,1,FALSE)=U27,"OK","Missing") -> #N/A | X27: =IF(VLOOKUP(U27,'CDV3 DTL'!E:E,1,FALSE)=U27,"OK","Missing") -> #N/A | AE27: =IF(AD27="x",VLOOKUP($U27,DVS!A:A,1,FALSE),"-") -> - | AN27: =IF(AM27="x",VLOOKUP($U27,'Domain ControllerECU'!A:A,1,FALSE),"-") -> - | AQ27: =IF(AP27="x",VLOOKUP($U27,RLT!A:A,1,FALSE),"-") -> - | AT27: =IF(AS27="x",VLOOKUP($U27,ULSECU!A:A,1,FALSE),"-") -> - | AW27: =IF(AV27="x",VLOOKUP($U27,'Radar 7779GHz'!A:A,1,FALSE),"-") -> - | AZ27: =IF(AY27="x",VLOOKUP($U27,LiDAR!A:A,1,FALSE),"-") -> - | BF27: =IF(BE27="x",VLOOKUP($U27,DFC!A:A,1,FALSE),"-") -> - | BI27: =IF(BH27="x",VLOOKUP(U27,'DSF ADSP'!A:A,1,FALSE),"-") -> - | BL27: =IF(BK27="x",VLOOKUP($U27,'DSF LSMS'!$A:$A,1,FALSE),"-") -> -
B28: REG_107 | C28: 25 | D28: normal | E28: Obsolete | H28: =VLOOKUP(U28,'CDV3 DTL'!E:G,2,FALSE) -> #N/A | P28: USA | Q28: =HYPERLINK("https://drive.google.com/open?id=1UFuW_JhZRpIhFBJn4s1JmsQPoCxvC1RG","USNCAP_Rearview Video Systems") -> USNCAP_Rearview Video Systems | S28: 38 | T28: Standard | W28: =IF(VLOOKUP(U28,'CDV2 DTL'!P:P,1,FALSE)=U28,"OK","Missing") -> #N/A | X28: =IF(VLOOKUP(U28,'CDV3 DTL'!E:E,1,FALSE)=U28,"OK","Missing") -> #N/A | AE28: =IF(AD28="x",VLOOKUP($U28,DVS!A:A,1,FALSE),"-") -> - | AN28: =IF(AM28="x",VLOOKUP($U28,'Domain ControllerECU'!A:A,1,FALSE),"-") -> - | AQ28: =IF(AP28="x",VLOOKUP($U28,RLT!A:A,1,FALSE),"-") -> - | AT28: =IF(AS28="x",VLOOKUP($U28,ULSECU!A:A,1,FALSE),"-") -> - | AW28: =IF(AV28="x",VLOOKUP($U28,'Radar 7779GHz'!A:A,1,FALSE),"-") -> - | AZ28: =IF(AY28="x",VLOOKUP($U28,LiDAR!A:A,1,FALSE),"-") -> - | BF28: =IF(BE28="x",VLOOKUP($U28,DFC!A:A,1,FALSE),"-") -> - | BI28: =IF(BH28="x",VLOOKUP(U28,'DSF ADSP'!A:A,1,FALSE),"-") -> - | BL28: =IF(BK28="x",VLOOKUP($U28,'DSF LSMS'!$A:$A,1,FALSE),"-") -> -
B29: REG_108 | C29: 26 | D29: normal | E29: Obsolete | H29: =VLOOKUP(U29,'CDV3 DTL'!E:G,2,FALSE) -> #N/A | P29: USA | Q29: =HYPERLINK("https://drive.google.com/open?id=15p0WaVSVWQMpkiyfjXzBwze8_V5qQO8y","USNCAP_LDW & LKS Test Procedure") -> USNCAP_LDW & LKS Test Procedure | S29: 39 | T29: Standard | W29: =IF(VLOOKUP(U29,'CDV2 DTL'!P:P,1,FALSE)=U29,"OK","Missing") -> #N/A | X29: =IF(VLOOKUP(U29,'CDV3 DTL'!E:E,1,FALSE)=U29,"OK","Missing") -> #N/A | AE29: =IF(AD29="x",VLOOKUP($U29,DVS!A:A,1,FALSE),"-") -> - | AN29: =IF(AM29="x",VLOOKUP($U29,'Domain ControllerECU'!A:A,1,FALSE),"-") -> - | AQ29: =IF(AP29="x",VLOOKUP($U29,RLT!A:A,1,FALSE),"-") -> - | AT29: =IF(AS29="x",VLOOKUP($U29,ULSECU!A:A,1,FALSE),"-") -> - | AW29: =IF(AV29="x",VLOOKUP($U29,'Radar 7779GHz'!A:A,1,FALSE),"-") -> - | AZ29: =IF(AY29="x",VLOOKUP($U29,LiDAR!A:A,1,FALSE),"-") -> - | BF29: =IF(BE29="x",VLOOKUP($U29,DFC!A:A,1,FALSE),"-") -> - | BI29: =IF(BH29="x",VLOOKUP(U29,'DSF ADSP'!A:A,1,FALSE),"-") -> - | BL29: =IF(BK29="x",VLOOKUP($U29,'DSF LSMS'!$A:$A,1,FALSE),"-") -> -
B30: REG_109 | C30: 27 | D30: normal | E30: Obsolete | H30: =VLOOKUP(U30,'CDV3 DTL'!E:G,2,FALSE) -> #N/A | P30: USA | Q30: =HYPERLINK("https://drive.google.com/open?id=1VKrn6FONSApJx7pV67brWQ-Qy1AVx5R4","US-NCAP Rear AEB *draft*") -> US-NCAP Rear AEB *draft* | S30: 22 | T30: NCAP | W30: =IF(VLOOKUP(U30,'CDV2 DTL'!P:P,1,FALSE)=U30,"OK","Missing") -> #N/A | X30: =IF(VLOOKUP(U30,'CDV3 DTL'!E:E,1,FALSE)=U30,"OK","Missing") -> #N/A | AE30: =IF(AD30="x",VLOOKUP($U30,DVS!A:A,1,FALSE),"-") -> - | AN30: =IF(AM30="x",VLOOKUP($U30,'Domain ControllerECU'!A:A,1,FALSE),"-") -> - | AQ30: =IF(AP30="x",VLOOKUP($U30,RLT!A:A,1,FALSE),"-") -> - | AT30: =IF(AS30="x",VLOOKUP($U30,ULSECU!A:A,1,FALSE),"-") -> - | AW30: =IF(AV30="x",VLOOKUP($U30,'Radar 7779GHz'!A:A,1,FALSE),"-") -> - | AZ30: =IF(AY30="x",VLOOKUP($U30,LiDAR!A:A,1,FALSE),"-") -> - | BF30: =IF(BE30="x",VLOOKUP($U30,DFC!A:A,1,FALSE),"-") -> - | BI30: =IF(BH30="x",VLOOKUP(U30,'DSF ADSP'!A:A,1,FALSE),"-") -> - | BL30: =IF(BK30="x",VLOOKUP($U30,'DSF LSMS'!$A:$A,1,FALSE),"-") -> -
B31: REG_110 | C31: 28 | D31: normal | E31: Obsolete | H31: =VLOOKUP(U31,'CDV3 DTL'!E:G,2,FALSE) -> #N/A | P31: Japan | Q31: =HYPERLINK("https://drive.google.com/open?id=1nU5aV6q81jeP-bmy23kdfVolbYUDzaE4","JNCAP_AEB_Car2Car_Test Procedure_2014") -> JNCAP_AEB_Car2Car_Test Procedure_2014 | S31: 18 | T31: Standard | W31: =IF(VLOOKUP(U31,'CDV2 DTL'!P:P,1,FALSE)=U31,"OK","Missing") -> #N/A | X31: =IF(VLOOKUP(U31,'CDV3 DTL'!E:E,1,FALSE)=U31,"OK","Missing") -> #N/A | AE31: =IF(AD31="x",VLOOKUP($U31,DVS!A:A,1,FALSE),"-") -> - | AN31: =IF(AM31="x",VLOOKUP($U31,'Domain ControllerECU'!A:A,1,FALSE),"-") -> - | AQ31: =IF(AP31="x",VLOOKUP($U31,RLT!A:A,1,FALSE),"-") -> - | AT31: =IF(AS31="x",VLOOKUP($U31,ULSECU!A:A,1,FALSE),"-") -> - | AW31: =IF(AV31="x",VLOOKUP($U31,'Radar 7779GHz'!A:A,1,FALSE),"-") -> - | AZ31: =IF(AY31="x",VLOOKUP($U31,LiDAR!A:A,1,FALSE),"-") -> - | BF31: =IF(BE31="x",VLOOKUP($U31,DFC!A:A,1,FALSE),"-") -> - | BI31: =IF(BH31="x",VLOOKUP(U31,'DSF ADSP'!A:A,1,FALSE),"-") -> - | BL31: =IF(BK31="x",VLOOKUP($U31,'DSF LSMS'!$A:$A,1,FALSE),"-") -> -
B32: REG_111 | C32: 29 | D32: normal | E32: Obsolete | H32: =VLOOKUP(U32,'CDV3 DTL'!E:G,2,FALSE) -> #N/A | P32: Japan | Q32: =HYPERLINK("https://drive.google.com/open?id=1jR_ppbradcbpA1_suiunbXn0yHY7-tia","JNCAP_Lane Departure Warning System") -> JNCAP_Lane Departure Warning System | S32: 8 | T32: Standard | W32: =IF(VLOOKUP(U32,'CDV2 DTL'!P:P,1,FALSE)=U32,"OK","Missing") -> #N/A | X32: =IF(VLOOKUP(U32,'CDV3 DTL'!E:E,1,FALSE)=U32,"OK","Missing") -> #N/A | AE32: =IF(AD32="x",VLOOKUP($U32,DVS!A:A,1,FALSE),"-") -> - | AN32: =IF(AM32="x",VLOOKUP($U32,'Domain ControllerECU'!A:A,1,FALSE),"-") -> - | AQ32: =IF(AP32="x",VLOOKUP($U32,RLT!A:A,1,FALSE),"-") -> - | AT32: =IF(AS32="x",VLOOKUP($U32,ULSECU!A:A,1,FALSE),"-") -> - | AW32: =IF(AV32="x",VLOOKUP($U32,'Radar 7779GHz'!A:A,1,FALSE),"-") -> - | AZ32: =IF(AY32="x",VLOOKUP($U32,LiDAR!A:A,1,FALSE),"-") -> - | BF32: =IF(BE32="x",VLOOKUP($U32,DFC!A:A,1,FALSE),"-") -> - | BI32: =IF(BH32="x",VLOOKUP(U32,'DSF ADSP'!A:A,1,FALSE),"-") -> - | BL32: =IF(BK32="x",VLOOKUP($U32,'DSF LSMS'!$A:$A,1,FALSE),"-") -> -
B33: REG_113 | C33: 30 | D33: low | E33: 10/10: Closed | H33: =VLOOKUP(U33,'CDV3 DTL'!E:G,2,FALSE) -> #N/A | P33: Japan | Q33: =HYPERLINK("https://drive.google.com/open?id=0B41cx_IVa9ynZHFON1dwWDJNRHRnTHpJdGJiY0xSOFV0Rmhr","BlueBook Japan_Article 44_Mirror_2017") -> BlueBook Japan_Article 44_Mirror_2017 | S33: 3 | T33: Regulations | U33: 12157_BlueBook Japan_Article 44_Mirror_2017 | W33: =IF(VLOOKUP(U33,'CDV2 DTL'!P:P,1,FALSE)=U33,"OK","Missing") -> OK | X33: =IF(VLOOKUP(U33,'CDV3 DTL'!E:E,1,FALSE)=U33,"OK","Missing") -> #N/A | AD33: x | AE33: =IF(AD33="x",VLOOKUP($U33,DVS!A:A,1,FALSE),"-") -> #N/A | AG33: x | AJ33: x | AN33: =IF(AM33="x",VLOOKUP($U33,'Domain ControllerECU'!A:A,1,FALSE),"-") -> - | AQ33: =IF(AP33="x",VLOOKUP($U33,RLT!A:A,1,FALSE),"-") -> - | AT33: =IF(AS33="x",VLOOKUP($U33,ULSECU!A:A,1,FALSE),"-") -> - | AW33: =IF(AV33="x",VLOOKUP($U33,'Radar 7779GHz'!A:A,1,FALSE),"-") -> - | AZ33: =IF(AY33="x",VLOOKUP($U33,LiDAR!A:A,1,FALSE),"-") -> - | BF33: =IF(BE33="x",VLOOKUP($U33,DFC!A:A,1,FALSE),"-") -> - | BI33: =IF(BH33="x",VLOOKUP(U33,'DSF ADSP'!A:A,1,FALSE),"-") -> - | BL33: =IF(BK33="x",VLOOKUP($U33,'DSF LSMS'!$A:$A,1,FALSE),"-") -> -
B34: REG_114 | C34: 31 | D34: normal | E34: 10/10: Closed | H34: =VLOOKUP(U34,'CDV3 DTL'!E:G,2,FALSE) -> #N/A | P34: USA | Q34: FMVSS 302_Flammability of materials used in the occupant compartments of motor vehicles | U34: 1208_FMVSS 302 | W34: =IF(VLOOKUP(U34,'CDV2 DTL'!P:P,1,FALSE)=U34,"OK","Missing") -> OK | X34: =IF(VLOOKUP(U34,'CDV3 DTL'!E:E,1,FALSE)=U34,"OK","Missing") -> #N/A | AE34: =IF(AD34="x",VLOOKUP($U34,DVS!A:A,1,FALSE),"-") -> - | AN34: =IF(AM34="x",VLOOKUP($U34,'Domain ControllerECU'!A:A,1,FALSE),"-") -> - | AQ34: =IF(AP34="x",VLOOKUP($U34,RLT!A:A,1,FALSE),"-") -> - | AT34: =IF(AS34="x",VLOOKUP($U34,ULSECU!A:A,1,FALSE),"-") -> - | AW34: =IF(AV34="x",VLOOKUP($U34,'Radar 7779GHz'!A:A,1,FALSE),"-") -> - | AZ34: =IF(AY34="x",VLOOKUP($U34,LiDAR!A:A,1,FALSE),"-") -> - | BF34: =IF(BE34="x",VLOOKUP($U34,DFC!A:A,1,FALSE),"-") -> - | BI34: =IF(BH34="x",VLOOKUP(U34,'DSF ADSP'!A:A,1,FALSE),"-") -> - | BL34: =IF(BK34="x",VLOOKUP($U34,'DSF LSMS'!$A:$A,1,FALSE),"-") -> -
B35: REG_115 | C35: 32 | D35: low | E35: Obsolete | H35: =VLOOKUP(U35,'CDV3 DTL'!E:G,2,FALSE) -> #N/A | P35: EU | Q35: ETSI EN 301 489-1 V1.9.2 | S35: 45 | T35: HN-Std | U35: (-) | W35: =IF(VLOOKUP(U35,'CDV2 DTL'!P:P,1,FALSE)=U35,"OK","Missing") -> #N/A | X35: =IF(VLOOKUP(U35,'CDV3 DTL'!E:E,1,FALSE)=U35,"OK","Missing") -> #N/A | AE35: =IF(AD35="x",VLOOKUP($U35,DVS!A:A,1,FALSE),"-") -> - | AN35: =IF(AM35="x",VLOOKUP($U35,'Domain ControllerECU'!A:A,1,FALSE),"-") -> - | AQ35: =IF(AP35="x",VLOOKUP($U35,RLT!A:A,1,FALSE),"-") -> - | AT35: =IF(AS35="x",VLOOKUP($U35,ULSECU!A:A,1,FALSE),"-") -> - | AV35: x | AW35: =IF(AV35="x",VLOOKUP($U35,'Radar 7779GHz'!A:A,1,FALSE),"-") -> #N/A | AZ35: =IF(AY35="x",VLOOKUP($U35,LiDAR!A:A,1,FALSE),"-") -> - | BF35: =IF(BE35="x",VLOOKUP($U35,DFC!A:A,1,FALSE),"-") -> - | BI35: =IF(BH35="x",VLOOKUP(U35,'DSF ADSP'!A:A,1,FALSE),"-") -> - | BL35: =IF(BK35="x",VLOOKUP($U35,'DSF LSMS'!$A:$A,1,FALSE),"-") -> -
B36: REG_116 | C36: 33 | D36: low | E36: Obsolete | H36: =VLOOKUP(U36,'CDV3 DTL'!E:G,2,FALSE) -> #N/A | P36: EU | Q36: ETSI EN 301 489-3 V1.6.1 | S36: 18 | T36: HN-Std | U36: (-) | W36: =IF(VLOOKUP(U36,'CDV2 DTL'!P:P,1,FALSE)=U36,"OK","Missing") -> #N/A | X36: =IF(VLOOKUP(U36,'CDV3 DTL'!E:E,1,FALSE)=U36,"OK","Missing") -> #N/A | AE36: =IF(AD36="x",VLOOKUP($U36,DVS!A:A,1,FALSE),"-") -> - | AN36: =IF(AM36="x",VLOOKUP($U36,'Domain ControllerECU'!A:A,1,FALSE),"-") -> - | AQ36: =IF(AP36="x",VLOOKUP($U36,RLT!A:A,1,FALSE),"-") -> - | AT36: =IF(AS36="x",VLOOKUP($U36,ULSECU!A:A,1,FALSE),"-") -> - | AV36: x | AW36: =IF(AV36="x",VLOOKUP($U36,'Radar 7779GHz'!A:A,1,FALSE),"-") -> #N/A | AZ36: =IF(AY36="x",VLOOKUP($U36,LiDAR!A:A,1,FALSE),"-") -> - | BF36: =IF(BE36="x",VLOOKUP($U36,DFC!A:A,1,FALSE),"-") -> - | BI36: =IF(BH36="x",VLOOKUP(U36,'DSF ADSP'!A:A,1,FALSE),"-") -> - | BL36: =IF(BK36="x",VLOOKUP($U36,'DSF LSMS'!$A:$A,1,FALSE),"-") -> -
B37: REG_117 | C37: 34 | D37: low | E37: Obsolete | H37: =VLOOKUP(U37,'CDV3 DTL'!E:G,2,FALSE) -> #N/A | P37: EU | Q37: ETSI EN 302 858-2 V1.3.1 | S37: 14 | T37: HN-Std | U37: (-) | W37: =IF(VLOOKUP(U37,'CDV2 DTL'!P:P,1,FALSE)=U37,"OK","Missing") -> #N/A | X37: =IF(VLOOKUP(U37,'CDV3 DTL'!E:E,1,FALSE)=U37,"OK","Missing") -> #N/A | AE37: =IF(AD37="x",VLOOKUP($U37,DVS!A:A,1,FALSE),"-") -> - | AN37: =IF(AM37="x",VLOOKUP($U37,'Domain ControllerECU'!A:A,1,FALSE),"-") -> - | AQ37: =IF(AP37="x",VLOOKUP($U37,RLT!A:A,1,FALSE),"-") -> - | AT37: =IF(AS37="x",VLOOKUP($U37,ULSECU!A:A,1,FALSE),"-") -> - | AV37: x | AW37: =IF(AV37="x",VLOOKUP($U37,'Radar 7779GHz'!A:A,1,FALSE),"-") -> #N/A | AZ37: =IF(AY37="x",VLOOKUP($U37,LiDAR!A:A,1,FALSE),"-") -> - | BF37: =IF(BE37="x",VLOOKUP($U37,DFC!A:A,1,FALSE),"-") -> - | BI37: =IF(BH37="x",VLOOKUP(U37,'DSF ADSP'!A:A,1,FALSE),"-") -> - | BL37: =IF(BK37="x",VLOOKUP($U37,'DSF LSMS'!$A:$A,1,FALSE),"-") -> -
B38: REG_118 | C38: 35 | D38: low | E38: Obsolete | H38: =VLOOKUP(U38,'CDV3 DTL'!E:G,2,FALSE) -> #N/A | P38: EU | Q38: ETSI EN 301 091-2 V1.3.2 | S38: 13 | T38: HN-Std | U38: (-) | W38: =IF(VLOOKUP(U38,'CDV2 DTL'!P:P,1,FALSE)=U38,"OK","Missing") -> #N/A | X38: =IF(VLOOKUP(U38,'CDV3 DTL'!E:E,1,FALSE)=U38,"OK","Missing") -> #N/A | AE38: =IF(AD38="x",VLOOKUP($U38,DVS!A:A,1,FALSE),"-") -> - | AN38: =IF(AM38="x",VLOOKUP($U38,'Domain ControllerECU'!A:A,1,FALSE),"-") -> - | AQ38: =IF(AP38="x",VLOOKUP($U38,RLT!A:A,1,FALSE),"-") -> - | AT38: =IF(AS38="x",VLOOKUP($U38,ULSECU!A:A,1,FALSE),"-") -> - | AV38: x | AW38: =IF(AV38="x",VLOOKUP($U38,'Radar 7779GHz'!A:A,1,FALSE),"-") -> #N/A | AZ38: =IF(AY38="x",VLOOKUP($U38,LiDAR!A:A,1,FALSE),"-") -> - | BF38: =IF(BE38="x",VLOOKUP($U38,DFC!A:A,1,FALSE),"-") -> - | BI38: =IF(BH38="x",VLOOKUP(U38,'DSF ADSP'!A:A,1,FALSE),"-") -> - | BL38: =IF(BK38="x",VLOOKUP($U38,'DSF LSMS'!$A:$A,1,FALSE),"-") -> -
B39: REG_119 | C39: 36 | D39: high | E39: 10/10: Closed | H39: =VLOOKUP(U39,'CDV3 DTL'!E:G,2,FALSE) -> #N/A | O39: M1, N1 | P39: USA | Q39: =HYPERLINK("https://drive.google.com/open?id=1uhJORQdxUiQ9ECTtQNxUcJUK4TZ6srLJ","FMVSS_571.111_Rear Visibilty 2016 Version!") -> FMVSS_571.111_Rear Visibilty 2016 Version! | S39: 16 | T39: Regulations | U39: 12112_FMVSS_571.111_Rear Visibilty 2016 Version_ | W39: =IF(VLOOKUP(U39,'CDV2 DTL'!P:P,1,FALSE)=U39,"OK","Missing") -> OK | X39: =IF(VLOOKUP(U39,'CDV3 DTL'!E:E,1,FALSE)=U39,"OK","Missing") -> #N/A | AD39: x | AE39: =IF(AD39="x",VLOOKUP($U39,DVS!A:A,1,FALSE),"-") -> #N/A | AJ39: x | AM39: x | AN39: =IF(AM39="x",VLOOKUP($U39,'Domain ControllerECU'!A:A,1,FALSE),"-") -> #N/A | AQ39: =IF(AP39="x",VLOOKUP($U39,RLT!A:A,1,FALSE),"-") -> - | AT39: =IF(AS39="x",VLOOKUP($U39,ULSECU!A:A,1,FALSE),"-") -> - | AW39: =IF(AV39="x",VLOOKUP($U39,'Radar 7779GHz'!A:A,1,FALSE),"-") -> - | AZ39: =IF(AY39="x",VLOOKUP($U39,LiDAR!A:A,1,FALSE),"-") -> - | BF39: =IF(BE39="x",VLOOKUP($U39,DFC!A:A,1,FALSE),"-") -> - | BI39: =IF(BH39="x",VLOOKUP(U39,'DSF ADSP'!A:A,1,FALSE),"-") -> - | BL39: =IF(BK39="x",VLOOKUP($U39,'DSF LSMS'!$A:$A,1,FALSE),"-") -> -
B40: REG_120 | C40: 37 | D40: low | E40: 10/10: Closed | H40: =VLOOKUP(U40,'CDV3 DTL'!E:G,2,FALSE) -> #N/A | O40: M1, N1 | P40: USA | Q40: =HYPERLINK("https://drive.google.com/open?id=1oSYsQd3IMOvgJXSP4m1e_gwWPLulaxoS","FMVSS_571.101_Controls&Display 2016 Version!!") -> FMVSS_571.101_Controls&Display 2016 Version!! | S40: 11 | T40: Regulations | U40: 12113_FMVSS_571.101_Controls_Display 2016 Version__ | W40: =IF(VLOOKUP(U40,'CDV2 DTL'!P:P,1,FALSE)=U40,"OK","Missing") -> OK | X40: =IF(VLOOKUP(U40,'CDV3 DTL'!E:E,1,FALSE)=U40,"OK","Missing") -> #N/A | AE40: =IF(AD40="x",VLOOKUP($U40,DVS!A:A,1,FALSE),"-") -> - | AN40: =IF(AM40="x",VLOOKUP($U40,'Domain ControllerECU'!A:A,1,FALSE),"-") -> - | AQ40: =IF(AP40="x",VLOOKUP($U40,RLT!A:A,1,FALSE),"-") -> - | AT40: =IF(AS40="x",VLOOKUP($U40,ULSECU!A:A,1,FALSE),"-") -> - | AW40: =IF(AV40="x",VLOOKUP($U40,'Radar 7779GHz'!A:A,1,FALSE),"-") -> - | AZ40: =IF(AY40="x",VLOOKUP($U40,LiDAR!A:A,1,FALSE),"-") -> - | BF40: =IF(BE40="x",VLOOKUP($U40,DFC!A:A,1,FALSE),"-") -> - | BI40: =IF(BH40="x",VLOOKUP(U40,'DSF ADSP'!A:A,1,FALSE),"-") -> - | BL40: =IF(BK40="x",VLOOKUP($U40,'DSF LSMS'!$A:$A,1,FALSE),"-") -> -
B41: REG_121 | C41: 38 | D41: normal | E41: 10/10: Closed | H41: =VLOOKUP(U41,'CDV3 DTL'!E:G,2,FALSE) -> #N/A | P41: USA | Q41: =HYPERLINK("https://drive.google.com/open?id=1qlmMF3a9NDgjcVZNVZzrNXL4xcFM54h-","FCC_Part18_ISM") -> FCC_Part18_ISM | S41: 8 | T41: Regulations | U41: 12114_FCC_Part18_ISM | W41: =IF(VLOOKUP(U41,'CDV2 DTL'!P:P,1,FALSE)=U41,"OK","Missing") -> OK | X41: =IF(VLOOKUP(U41,'CDV3 DTL'!E:E,1,FALSE)=U41,"OK","Missing") -> #N/A | AE41: =IF(AD41="x",VLOOKUP($U41,DVS!A:A,1,FALSE),"-") -> - | AN41: =IF(AM41="x",VLOOKUP($U41,'Domain ControllerECU'!A:A,1,FALSE),"-") -> - | AQ41: =IF(AP41="x",VLOOKUP($U41,RLT!A:A,1,FALSE),"-") -> - | AT41: =IF(AS41="x",VLOOKUP($U41,ULSECU!A:A,1,FALSE),"-") -> - | AV41: x | AW41: =IF(AV41="x",VLOOKUP($U41,'Radar 7779GHz'!A:A,1,FALSE),"-") -> #N/A | AZ41: =IF(AY41="x",VLOOKUP($U41,LiDAR!A:A,1,FALSE),"-") -> - | BF41: =IF(BE41="x",VLOOKUP($U41,DFC!A:A,1,FALSE),"-") -> - | BI41: =IF(BH41="x",VLOOKUP(U41,'DSF ADSP'!A:A,1,FALSE),"-") -> - | BL41: =IF(BK41="x",VLOOKUP($U41,'DSF LSMS'!$A:$A,1,FALSE),"-") -> -
B42: REG_122 | C42: 39 | D42: normal | E42: Obsolete | H42: =VLOOKUP(U42,'CDV3 DTL'!E:G,2,FALSE) -> #N/A | P42: USA | Q42: =HYPERLINK("https://drive.google.com/open?id=1_e0xzOM_HWUrfZ_sVmRc6j7wBXKG1vQV","FCC_Part90_76-81GHz") -> FCC_Part90_76-81GHz | S42: 8 | T42: Regulations | U42: 12115_FCC_Part90_76-81GHz | W42: =IF(VLOOKUP(U42,'CDV2 DTL'!P:P,1,FALSE)=U42,"OK","Missing") -> #N/A | X42: =IF(VLOOKUP(U42,'CDV3 DTL'!E:E,1,FALSE)=U42,"OK","Missing") -> #N/A | AE42: =IF(AD42="x",VLOOKUP($U42,DVS!A:A,1,FALSE),"-") -> - | AN42: =IF(AM42="x",VLOOKUP($U42,'Domain ControllerECU'!A:A,1,FALSE),"-") -> - | AQ42: =IF(AP42="x",VLOOKUP($U42,RLT!A:A,1,FALSE),"-") -> - | AT42: =IF(AS42="x",VLOOKUP($U42,ULSECU!A:A,1,FALSE),"-") -> - | AV42: x | AW42: =IF(AV42="x",VLOOKUP($U42,'Radar 7779GHz'!A:A,1,FALSE),"-") -> #N/A | AZ42: =IF(AY42="x",VLOOKUP($U42,LiDAR!A:A,1,FALSE),"-") -> - | BF42: =IF(BE42="x",VLOOKUP($U42,DFC!A:A,1,FALSE),"-") -> - | BI42: =IF(BH42="x",VLOOKUP(U42,'DSF ADSP'!A:A,1,FALSE),"-") -> - | BL42: =IF(BK42="x",VLOOKUP($U42,'DSF LSMS'!$A:$A,1,FALSE),"-") -> -
B43: REG_123 | C43: 40 | D43: low | E43: 10/10: Closed | H43: =VLOOKUP(U43,'CDV3 DTL'!E:G,2,FALSE) -> #N/A | P43: EU | Q43: =HYPERLINK("https://drive.google.com/open?id=1evOCMoYbS_fXFZ6GDFfSpgmSJziOxH3y","2011/65/EU_RoHS") -> 2011/65/EU_RoHS | S43: 35 | T43: Regulations | U43: 12116_2011_65_EU_RoHS | W43: =IF(VLOOKUP(U43,'CDV2 DTL'!P:P,1,FALSE)=U43,"OK","Missing") -> OK | X43: =IF(VLOOKUP(U43,'CDV3 DTL'!E:E,1,FALSE)=U43,"OK","Missing") -> #N/A | AE43: =IF(AD43="x",VLOOKUP($U43,DVS!A:A,1,FALSE),"-") -> - | AN43: =IF(AM43="x",VLOOKUP($U43,'Domain ControllerECU'!A:A,1,FALSE),"-") -> - | AQ43: =IF(AP43="x",VLOOKUP($U43,RLT!A:A,1,FALSE),"-") -> - | AT43: =IF(AS43="x",VLOOKUP($U43,ULSECU!A:A,1,FALSE),"-") -> - | AW43: =IF(AV43="x",VLOOKUP($U43,'Radar 7779GHz'!A:A,1,FALSE),"-") -> - | AZ43: =IF(AY43="x",VLOOKUP($U43,LiDAR!A:A,1,FALSE),"-") -> - | BF43: =IF(BE43="x",VLOOKUP($U43,DFC!A:A,1,FALSE),"-") -> - | BI43: =IF(BH43="x",VLOOKUP(U43,'DSF ADSP'!A:A,1,FALSE),"-") -> - | BL43: =IF(BK43="x",VLOOKUP($U43,'DSF LSMS'!$A:$A,1,FALSE),"-") -> -
B44: REG_124 | C44: 41 | D44: low | E44: Obsolete | H44: =VLOOKUP(U44,'CDV3 DTL'!E:G,2,FALSE) -> #N/A | P44: EU | Q44: ETSI EN 302 264-1 V1.1.1 | S44: 39 | T44: HN-Std | U44: (-) | W44: =IF(VLOOKUP(U44,'CDV2 DTL'!P:P,1,FALSE)=U44,"OK","Missing") -> #N/A | X44: =IF(VLOOKUP(U44,'CDV3 DTL'!E:E,1,FALSE)=U44,"OK","Missing") -> #N/A | AE44: =IF(AD44="x",VLOOKUP($U44,DVS!A:A,1,FALSE),"-") -> - | AN44: =IF(AM44="x",VLOOKUP($U44,'Domain ControllerECU'!A:A,1,FALSE),"-") -> - | AQ44: =IF(AP44="x",VLOOKUP($U44,RLT!A:A,1,FALSE),"-") -> - | AT44: =IF(AS44="x",VLOOKUP($U44,ULSECU!A:A,1,FALSE),"-") -> - | AV44: x | AW44: =IF(AV44="x",VLOOKUP($U44,'Radar 7779GHz'!A:A,1,FALSE),"-") -> #N/A | AZ44: =IF(AY44="x",VLOOKUP($U44,LiDAR!A:A,1,FALSE),"-") -> - | BF44: =IF(BE44="x",VLOOKUP($U44,DFC!A:A,1,FALSE),"-") -> - | BI44: =IF(BH44="x",VLOOKUP(U44,'DSF ADSP'!A:A,1,FALSE),"-") -> - | BL44: =IF(BK44="x",VLOOKUP($U44,'DSF LSMS'!$A:$A,1,FALSE),"-") -> -
B45: REG_126 | C45: 42 | D45: normal | E45: Obsolete | H45: =VLOOKUP(U45,'CDV3 DTL'!E:G,2,FALSE) -> #N/A | O45: all | P45: UN | Q45: =HYPERLINK("https://drive.google.com/open?id=1yEKJMiwIrfd8MprQpgCAV8W_0MIGkNE3","UN ECE R46_Devices for Indirect Vision Rev6 A1") -> UN ECE R46_Devices for Indirect Vision Rev6 A1 | S45: 2 | T45: Regulations | U45: 12119_UN ECE R46_Devices for Indirect Vision Rev6 A1 | W45: =IF(VLOOKUP(U45,'CDV2 DTL'!P:P,1,FALSE)=U45,"OK","Missing") -> #N/A | X45: =IF(VLOOKUP(U45,'CDV3 DTL'!E:E,1,FALSE)=U45,"OK","Missing") -> #N/A | Z45: TO be merged | AD45: x | AE45: =IF(AD45="x",VLOOKUP($U45,DVS!A:A,1,FALSE),"-") -> #N/A | AG45: x | AJ45: x | AN45: =IF(AM45="x",VLOOKUP($U45,'Domain ControllerECU'!A:A,1,FALSE),"-") -> - | AQ45: =IF(AP45="x",VLOOKUP($U45,RLT!A:A,1,FALSE),"-") -> - | AT45: =IF(AS45="x",VLOOKUP($U45,ULSECU!A:A,1,FALSE),"-") -> - | AW45: =IF(AV45="x",VLOOKUP($U45,'Radar 7779GHz'!A:A,1,FALSE),"-") -> - | AZ45: =IF(AY45="x",VLOOKUP($U45,LiDAR!A:A,1,FALSE),"-") -> - | BF45: =IF(BE45="x",VLOOKUP($U45,DFC!A:A,1,FALSE),"-") -> - | BI45: =IF(BH45="x",VLOOKUP(U45,'DSF ADSP'!A:A,1,FALSE),"-") -> - | BL45: =IF(BK45="x",VLOOKUP($U45,'DSF LSMS'!$A:$A,1,FALSE),"-") -> -
B46: REG_127 | C46: 43 | D46: normal | E46: Obsolete | H46: =VLOOKUP(U46,'CDV3 DTL'!E:G,2,FALSE) -> #N/A | O46: all | P46: UN | Q46: =HYPERLINK("https://drive.google.com/open?id=1Qdfj8e8gcvzmU9abUJ1I0c9VJsJVgLz4","UN ECE R46_Devices for Indirect Vision Rev6 A2") -> UN ECE R46_Devices for Indirect Vision Rev6 A2 | S46: 2 | T46: Regulations | U46: 12120_UN ECE R46_Devices for Indirect Vision Rev6 A2 | W46: =IF(VLOOKUP(U46,'CDV2 DTL'!P:P,1,FALSE)=U46,"OK","Missing") -> #N/A | X46: =IF(VLOOKUP(U46,'CDV3 DTL'!E:E,1,FALSE)=U46,"OK","Missing") -> #N/A | Z46: TO be merged | AD46: x | AE46: =IF(AD46="x",VLOOKUP($U46,DVS!A:A,1,FALSE),"-") -> #N/A | AG46: x | AJ46: x | AN46: =IF(AM46="x",VLOOKUP($U46,'Domain ControllerECU'!A:A,1,FALSE),"-") -> - | AQ46: =IF(AP46="x",VLOOKUP($U46,RLT!A:A,1,FALSE),"-") -> - | AT46: =IF(AS46="x",VLOOKUP($U46,ULSECU!A:A,1,FALSE),"-") -> - | AW46: =IF(AV46="x",VLOOKUP($U46,'Radar 7779GHz'!A:A,1,FALSE),"-") -> - | AZ46: =IF(AY46="x",VLOOKUP($U46,LiDAR!A:A,1,FALSE),"-") -> - | BF46: =IF(BE46="x",VLOOKUP($U46,DFC!A:A,1,FALSE),"-") -> - | BI46: =IF(BH46="x",VLOOKUP(U46,'DSF ADSP'!A:A,1,FALSE),"-") -> - | BL46: =IF(BK46="x",VLOOKUP($U46,'DSF LSMS'!$A:$A,1,FALSE),"-") -> -
B47: REG_128 | C47: 44 | D47: normal | E47: 10/10: Closed | H47: =VLOOKUP(U47,'CDV3 DTL'!E:G,2,FALSE) -> #N/A | P47: USA | Q47: =HYPERLINK("https://drive.google.com/open?id=1_S29cKZktZuC2lQAA7ZaxWZx32Ye7zB1","FCC_Part15_Radio_frequency_Devices") -> FCC_Part15_Radio_frequency_Devices | S47: 120 | T47: Regulations | U47: 12121_FCC_Part15_Radio_frequency_Devices | W47: =IF(VLOOKUP(U47,'CDV2 DTL'!P:P,1,FALSE)=U47,"OK","Missing") -> OK | X47: =IF(VLOOKUP(U47,'CDV3 DTL'!E:E,1,FALSE)=U47,"OK","Missing") -> #N/A | AE47: =IF(AD47="x",VLOOKUP($U47,DVS!A:A,1,FALSE),"-") -> - | AN47: =IF(AM47="x",VLOOKUP($U47,'Domain ControllerECU'!A:A,1,FALSE),"-") -> - | AQ47: =IF(AP47="x",VLOOKUP($U47,RLT!A:A,1,FALSE),"-") -> - | AT47: =IF(AS47="x",VLOOKUP($U47,ULSECU!A:A,1,FALSE),"-") -> - | AV47: x | AW47: =IF(AV47="x",VLOOKUP($U47,'Radar 7779GHz'!A:A,1,FALSE),"-") -> #N/A | AZ47: =IF(AY47="x",VLOOKUP($U47,LiDAR!A:A,1,FALSE),"-") -> - | BF47: =IF(BE47="x",VLOOKUP($U47,DFC!A:A,1,FALSE),"-") -> - | BI47: =IF(BH47="x",VLOOKUP(U47,'DSF ADSP'!A:A,1,FALSE),"-") -> - | BL47: =IF(BK47="x",VLOOKUP($U47,'DSF LSMS'!$A:$A,1,FALSE),"-") -> -
B48: REG_129 | C48: 45 | D48: low | E48: Obsolete | H48: =VLOOKUP(U48,'CDV3 DTL'!E:G,2,FALSE) -> #N/A | P48: EU | Q48: =HYPERLINK("https://drive.google.com/open?id=1arCpXHrHlsKxNf2wVacnG0YUPnDoAfiu","2007/46/EC_TypeApproval") -> 2007/46/EC_TypeApproval | S48: 407 | T48: Regulations | U48: outdated | W48: =IF(VLOOKUP(U48,'CDV2 DTL'!P:P,1,FALSE)=U48,"OK","Missing") -> #N/A | X48: =IF(VLOOKUP(U48,'CDV3 DTL'!E:E,1,FALSE)=U48,"OK","Missing") -> #N/A | AE48: =IF(AD48="x",VLOOKUP($U48,DVS!A:A,1,FALSE),"-") -> - | AN48: =IF(AM48="x",VLOOKUP($U48,'Domain ControllerECU'!A:A,1,FALSE),"-") -> - | AQ48: =IF(AP48="x",VLOOKUP($U48,RLT!A:A,1,FALSE),"-") -> - | AT48: =IF(AS48="x",VLOOKUP($U48,ULSECU!A:A,1,FALSE),"-") -> - | AW48: =IF(AV48="x",VLOOKUP($U48,'Radar 7779GHz'!A:A,1,FALSE),"-") -> - | AZ48: =IF(AY48="x",VLOOKUP($U48,LiDAR!A:A,1,FALSE),"-") -> - | BF48: =IF(BE48="x",VLOOKUP($U48,DFC!A:A,1,FALSE),"-") -> - | BI48: =IF(BH48="x",VLOOKUP(U48,'DSF ADSP'!A:A,1,FALSE),"-") -> - | BL48: =IF(BK48="x",VLOOKUP($U48,'DSF LSMS'!$A:$A,1,FALSE),"-") -> -
B49: REG_130 | C49: 46 | D49: low | E49: 10/10: Closed | H49: =VLOOKUP(U49,'CDV3 DTL'!E:G,2,FALSE) -> #N/A | O49: M1, N1 | P49: China | Q49: =HYPERLINK("https://drive.google.com/open?id=1-TEmYWBakGy13e2r6c8zg-ggRW-1qn7K","GB 8410-2006_Flammability of Automotive Interior Materials") -> GB 8410-2006_Flammability of Automotive Interior Materials | S49: 11 | T49: Regulations | U49: 12123_GB 8410-2006_Flammability of Automotive Interior Materials | W49: =IF(VLOOKUP(U49,'CDV2 DTL'!P:P,1,FALSE)=U49,"OK","Missing") -> OK | X49: =IF(VLOOKUP(U49,'CDV3 DTL'!E:E,1,FALSE)=U49,"OK","Missing") -> #N/A | AE49: =IF(AD49="x",VLOOKUP($U49,DVS!A:A,1,FALSE),"-") -> - | AN49: =IF(AM49="x",VLOOKUP($U49,'Domain ControllerECU'!A:A,1,FALSE),"-") -> - | AQ49: =IF(AP49="x",VLOOKUP($U49,RLT!A:A,1,FALSE),"-") -> - | AT49: =IF(AS49="x",VLOOKUP($U49,ULSECU!A:A,1,FALSE),"-") -> - | AW49: =IF(AV49="x",VLOOKUP($U49,'Radar 7779GHz'!A:A,1,FALSE),"-") -> - | AZ49: =IF(AY49="x",VLOOKUP($U49,LiDAR!A:A,1,FALSE),"-") -> - | BF49: =IF(BE49="x",VLOOKUP($U49,DFC!A:A,1,FALSE),"-") -> - | BI49: =IF(BH49="x",VLOOKUP(U49,'DSF ADSP'!A:A,1,FALSE),"-") -> - | BL49: =IF(BK49="x",VLOOKUP($U49,'DSF LSMS'!$A:$A,1,FALSE),"-") -> -
B50: REG_131 | C50: 47 | D50: low | E50: 10/10: Closed | H50: =VLOOKUP(U50,'CDV3 DTL'!E:G,2,FALSE) -> #N/A | P50: China | Q50: =HYPERLINK("https://drive.google.com/open?id=1lf5IoLyxnI5CzWzahEBevFQ_iV7LYCOa","GB/T 17619-1998") -> GB/T 17619-1998 | S50: 19 | T50: Standard | U50: 12124_GB_T 17619-1998 | W50: =IF(VLOOKUP(U50,'CDV2 DTL'!P:P,1,FALSE)=U50,"OK","Missing") -> OK | X50: =IF(VLOOKUP(U50,'CDV3 DTL'!E:E,1,FALSE)=U50,"OK","Missing") -> #N/A | AE50: =IF(AD50="x",VLOOKUP($U50,DVS!A:A,1,FALSE),"-") -> - | AN50: =IF(AM50="x",VLOOKUP($U50,'Domain ControllerECU'!A:A,1,FALSE),"-") -> - | AQ50: =IF(AP50="x",VLOOKUP($U50,RLT!A:A,1,FALSE),"-") -> - | AT50: =IF(AS50="x",VLOOKUP($U50,ULSECU!A:A,1,FALSE),"-") -> - | AW50: =IF(AV50="x",VLOOKUP($U50,'Radar 7779GHz'!A:A,1,FALSE),"-") -> - | AZ50: =IF(AY50="x",VLOOKUP($U50,LiDAR!A:A,1,FALSE),"-") -> - | BF50: =IF(BE50="x",VLOOKUP($U50,DFC!A:A,1,FALSE),"-") -> - | BI50: =IF(BH50="x",VLOOKUP(U50,'DSF ADSP'!A:A,1,FALSE),"-") -> - | BL50: =IF(BK50="x",VLOOKUP($U50,'DSF LSMS'!$A:$A,1,FALSE),"-") -> -
B51: REG_132 | C51: 48 | D51: low | E51: 10/10: Closed | H51: =VLOOKUP(U51,'CDV3 DTL'!E:G,2,FALSE) -> #N/A | P51: UN | Q51: =HYPERLINK("https://drive.google.com/open?id=1JkWi782BHR8N74Dyy0DN-wU_JaBwX7Ui","UN ECE R121r2_HMI") -> UN ECE R121r2_HMI | S51: 19 | T51: Regulations | U51: 12125_UN ECE R121r2_HMI | W51: =IF(VLOOKUP(U51,'CDV2 DTL'!P:P,1,FALSE)=U51,"OK","Missing") -> OK | X51: =IF(VLOOKUP(U51,'CDV3 DTL'!E:E,1,FALSE)=U51,"OK","Missing") -> #N/A | AE51: =IF(AD51="x",VLOOKUP($U51,DVS!A:A,1,FALSE),"-") -> - | AN51: =IF(AM51="x",VLOOKUP($U51,'Domain ControllerECU'!A:A,1,FALSE),"-") -> - | AQ51: =IF(AP51="x",VLOOKUP($U51,RLT!A:A,1,FALSE),"-") -> - | AT51: =IF(AS51="x",VLOOKUP($U51,ULSECU!A:A,1,FALSE),"-") -> - | AW51: =IF(AV51="x",VLOOKUP($U51,'Radar 7779GHz'!A:A,1,FALSE),"-") -> - | AZ51: =IF(AY51="x",VLOOKUP($U51,LiDAR!A:A,1,FALSE),"-") -> - | BF51: =IF(BE51="x",VLOOKUP($U51,DFC!A:A,1,FALSE),"-") -> - | BI51: =IF(BH51="x",VLOOKUP(U51,'DSF ADSP'!A:A,1,FALSE),"-") -> - | BL51: =IF(BK51="x",VLOOKUP($U51,'DSF LSMS'!$A:$A,1,FALSE),"-") -> -
B52: REG_133 | C52: 49 | D52: low | E52: 10/10: Closed | H52: =VLOOKUP(U52,'CDV3 DTL'!E:G,2,FALSE) -> #N/A | O52: all | P52: UN | Q52: =HYPERLINK("https://drive.google.com/open?id=17XA3jxgjDYhOHTrxo8AAMacVwMv6Wfxe","UN ECE R26r1 External Projections") -> UN ECE R26r1 External Projections | S52: 25 | T52: Regulations | U52: 12126_UN ECE R26r1 External Projections | W52: =IF(VLOOKUP(U52,'CDV2 DTL'!P:P,1,FALSE)=U52,"OK","Missing") -> OK | X52: =IF(VLOOKUP(U52,'CDV3 DTL'!E:E,1,FALSE)=U52,"OK","Missing") -> #N/A | AA52: DFC (Front Camera) | AD52: x | AE52: =IF(AD52="x",VLOOKUP($U52,DVS!A:A,1,FALSE),"-") -> #N/A | AJ52: x | AN52: =IF(AM52="x",VLOOKUP($U52,'Domain ControllerECU'!A:A,1,FALSE),"-") -> - | AQ52: =IF(AP52="x",VLOOKUP($U52,RLT!A:A,1,FALSE),"-") -> - | AT52: =IF(AS52="x",VLOOKUP($U52,ULSECU!A:A,1,FALSE),"-") -> - | AW52: =IF(AV52="x",VLOOKUP($U52,'Radar 7779GHz'!A:A,1,FALSE),"-") -> - | AZ52: =IF(AY52="x",VLOOKUP($U52,LiDAR!A:A,1,FALSE),"-") -> - | BF52: =IF(BE52="x",VLOOKUP($U52,DFC!A:A,1,FALSE),"-") -> - | BI52: =IF(BH52="x",VLOOKUP(U52,'DSF ADSP'!A:A,1,FALSE),"-") -> - | BL52: =IF(BK52="x",VLOOKUP($U52,'DSF LSMS'!$A:$A,1,FALSE),"-") -> -
B53: REG_134 | C53: 50 | D53: low | E53: 10/10: Closed | H53: =VLOOKUP(U53,'CDV3 DTL'!E:G,2,FALSE) -> #N/A | P53: EU | Q53: =HYPERLINK("https://drive.google.com/open?id=1YmJIm_bltKQJI5VGrgA8SQKjbFC8IYht","2001/95/EC_General Product Safety ") -> 2001/95/EC_General Product Safety | S53: 23 | T53: Regulations | U53: 12127_2001_95_EC_General Product Safety | W53: =IF(VLOOKUP(U53,'CDV2 DTL'!P:P,1,FALSE)=U53,"OK","Missing") -> OK | X53: =IF(VLOOKUP(U53,'CDV3 DTL'!E:E,1,FALSE)=U53,"OK","Missing") -> #N/A | AE53: =IF(AD53="x",VLOOKUP($U53,DVS!A:A,1,FALSE),"-") -> - | AN53: =IF(AM53="x",VLOOKUP($U53,'Domain ControllerECU'!A:A,1,FALSE),"-") -> - | AQ53: =IF(AP53="x",VLOOKUP($U53,RLT!A:A,1,FALSE),"-") -> - | AT53: =IF(AS53="x",VLOOKUP($U53,ULSECU!A:A,1,FALSE),"-") -> - | AW53: =IF(AV53="x",VLOOKUP($U53,'Radar 7779GHz'!A:A,1,FALSE),"-") -> - | AZ53: =IF(AY53="x",VLOOKUP($U53,LiDAR!A:A,1,FALSE),"-") -> - | BF53: =IF(BE53="x",VLOOKUP($U53,DFC!A:A,1,FALSE),"-") -> - | BI53: =IF(BH53="x",VLOOKUP(U53,'DSF ADSP'!A:A,1,FALSE),"-") -> - | BL53: =IF(BK53="x",VLOOKUP($U53,'DSF LSMS'!$A:$A,1,FALSE),"-") -> -
B54: REG_135 | C54: 51 | D54: low | E54: 10/10: Closed | H54: =VLOOKUP(U54,'CDV3 DTL'!E:G,2,FALSE) -> #N/A | J54: x | K54: Lane departure warning, definition of lane markings included | O54: N2-N3; M2-M3 | P54: UN | Q54: =HYPERLINK("https://drive.google.com/open?id=1leclR7Isxn0-1-IqsjJbpPZK3PrFA1SG","UN ECE R130_LDWS_Trucks") -> UN ECE R130_LDWS_Trucks | S54: 25 | T54: Regulations | U54: 12128_UN ECE R130_LDWS_Trucks | W54: =IF(VLOOKUP(U54,'CDV2 DTL'!P:P,1,FALSE)=U54,"OK","Missing") -> OK | X54: =IF(VLOOKUP(U54,'CDV3 DTL'!E:E,1,FALSE)=U54,"OK","Missing") -> #N/A | AE54: =IF(AD54="x",VLOOKUP($U54,DVS!A:A,1,FALSE),"-") -> - | AN54: =IF(AM54="x",VLOOKUP($U54,'Domain ControllerECU'!A:A,1,FALSE),"-") -> - | AQ54: =IF(AP54="x",VLOOKUP($U54,RLT!A:A,1,FALSE),"-") -> - | AT54: =IF(AS54="x",VLOOKUP($U54,ULSECU!A:A,1,FALSE),"-") -> - | AW54: =IF(AV54="x",VLOOKUP($U54,'Radar 7779GHz'!A:A,1,FALSE),"-") -> - | AZ54: =IF(AY54="x",VLOOKUP($U54,LiDAR!A:A,1,FALSE),"-") -> - | BF54: =IF(BE54="x",VLOOKUP($U54,DFC!A:A,1,FALSE),"-") -> - | BH54: x | BI54: =IF(BH54="x",VLOOKUP(U54,'DSF ADSP'!A:A,1,FALSE),"-") -> #N/A | BL54: =IF(BK54="x",VLOOKUP($U54,'DSF LSMS'!$A:$A,1,FALSE),"-") -> -
B55: REG_136 | C55: 52 | D55: low | E55: 10/10: Closed | H55: =VLOOKUP(U55,'CDV3 DTL'!E:G,2,FALSE) -> #N/A | P55: EU | Q55: =HYPERLINK("https://drive.google.com/open?id=1qPyPrxhVDzl2IQHg1kJES9F6-JvGe_aT","Decision 2006/771/EC_Radio Spectrum Short Range") -> Decision 2006/771/EC_Radio Spectrum Short Range | S55: 28 | T55: Regulations | U55: 12129_Decision 2006_771_EC_Radio Spectrum Short Range | W55: =IF(VLOOKUP(U55,'CDV2 DTL'!P:P,1,FALSE)=U55,"OK","Missing") -> OK | X55: =IF(VLOOKUP(U55,'CDV3 DTL'!E:E,1,FALSE)=U55,"OK","Missing") -> #N/A | AE55: =IF(AD55="x",VLOOKUP($U55,DVS!A:A,1,FALSE),"-") -> - | AN55: =IF(AM55="x",VLOOKUP($U55,'Domain ControllerECU'!A:A,1,FALSE),"-") -> - | AQ55: =IF(AP55="x",VLOOKUP($U55,RLT!A:A,1,FALSE),"-") -> - | AT55: =IF(AS55="x",VLOOKUP($U55,ULSECU!A:A,1,FALSE),"-") -> - | AV55: x | AW55: =IF(AV55="x",VLOOKUP($U55,'Radar 7779GHz'!A:A,1,FALSE),"-") -> #N/A | AZ55: =IF(AY55="x",VLOOKUP($U55,LiDAR!A:A,1,FALSE),"-") -> - | BF55: =IF(BE55="x",VLOOKUP($U55,DFC!A:A,1,FALSE),"-") -> - | BI55: =IF(BH55="x",VLOOKUP(U55,'DSF ADSP'!A:A,1,FALSE),"-") -> - | BL55: =IF(BK55="x",VLOOKUP($U55,'DSF LSMS'!$A:$A,1,FALSE),"-") -> -
B56: REG_137 | C56: 53 | D56: low | E56: 10/10: Closed | H56: =VLOOKUP(U56,'CDV3 DTL'!E:G,2,FALSE) -> #N/A | J56: x | K56: AEB for heavy commercial vehicles N2-N3; M2-M3 | M56: 2014 | O56: N2-N3; M2-M3 | P56: UN | Q56: =HYPERLINK("https://drive.google.com/open?id=1hgrWDIqlwFgVYRIi8IfofLzNPf8KuMWW","UN ECE R 131 r1_AEBS_Trucks") -> UN ECE R 131 r1_AEBS_Trucks | S56: 23 | T56: Regulations | U56: 12130_UN ECE R131r1_AEBS_Trucks | W56: OK | X56: =IF(VLOOKUP(U56,'CDV3 DTL'!E:E,1,FALSE)=U56,"OK","Missing") -> #N/A | AE56: =IF(AD56="x",VLOOKUP($U56,DVS!A:A,1,FALSE),"-") -> - | AN56: =IF(AM56="x",VLOOKUP($U56,'Domain ControllerECU'!A:A,1,FALSE),"-") -> - | AQ56: =IF(AP56="x",VLOOKUP($U56,RLT!A:A,1,FALSE),"-") -> - | AT56: =IF(AS56="x",VLOOKUP($U56,ULSECU!A:A,1,FALSE),"-") -> - | AV56: x | AW56: =IF(AV56="x",VLOOKUP($U56,'Radar 7779GHz'!A:A,1,FALSE),"-") -> #N/A | AZ56: =IF(AY56="x",VLOOKUP($U56,LiDAR!A:A,1,FALSE),"-") -> - | BE56: x | BF56: =IF(BE56="x",VLOOKUP($U56,DFC!A:A,1,FALSE),"-") -> #N/A | BI56: =IF(BH56="x",VLOOKUP(U56,'DSF ADSP'!A:A,1,FALSE),"-") -> - | BL56: =IF(BK56="x",VLOOKUP($U56,'DSF LSMS'!$A:$A,1,FALSE),"-") -> -
B57: REG_138 | C57: 54 | D57: low | E57: 10/10: Closed | H57: =VLOOKUP(U57,'CDV3 DTL'!E:G,2,FALSE) -> #N/A | K57: CISPR 12:2009 “Vehicles, boats and internal combustion engines — Radio disturbance Characteristics — Limits and methods of measurement for the protection of off-board receivers” (Edition 6.1) | P57: China | Q57: =HYPERLINK("https://drive.google.com/open?id=1q0O0Wp-L5u226PjV_AKwN1LIKN76QXY5","GB 14023-2011") -> GB 14023-2011 | S57: 60 | T57: Regulations | U57: 12131_GB 14023-2011 | W57: =IF(VLOOKUP(U57,'CDV2 DTL'!P:P,1,FALSE)=U57,"OK","Missing") -> OK | X57: =IF(VLOOKUP(U57,'CDV3 DTL'!E:E,1,FALSE)=U57,"OK","Missing") -> #N/A | AE57: =IF(AD57="x",VLOOKUP($U57,DVS!A:A,1,FALSE),"-") -> - | AN57: =IF(AM57="x",VLOOKUP($U57,'Domain ControllerECU'!A:A,1,FALSE),"-") -> - | AQ57: =IF(AP57="x",VLOOKUP($U57,RLT!A:A,1,FALSE),"-") -> - | AT57: =IF(AS57="x",VLOOKUP($U57,ULSECU!A:A,1,FALSE),"-") -> - | AW57: =IF(AV57="x",VLOOKUP($U57,'Radar 7779GHz'!A:A,1,FALSE),"-") -> - | AZ57: =IF(AY57="x",VLOOKUP($U57,LiDAR!A:A,1,FALSE),"-") -> - | BF57: =IF(BE57="x",VLOOKUP($U57,DFC!A:A,1,FALSE),"-") -> - | BI57: =IF(BH57="x",VLOOKUP(U57,'DSF ADSP'!A:A,1,FALSE),"-") -> - | BL57: =IF(BK57="x",VLOOKUP($U57,'DSF LSMS'!$A:$A,1,FALSE),"-") -> -
B58: REG_139 | C58: 55 | D58: low | E58: 10/10: Closed | H58: =VLOOKUP(U58,'CDV3 DTL'!E:G,2,FALSE) -> #N/A | P58: USA | Q58: =HYPERLINK("https://drive.google.com/open?id=1SD2-bO4ok7NTTLrKOc26_TUv1uqRrbWM","NHTSA_Active Park Assist_DRAFT_April18") -> NHTSA_Active Park Assist_DRAFT_April18 | S58: 30 | T58: Standard | U58: 12132_NHTSA_Active Park Assist_DRAFT_April18 | W58: =IF(VLOOKUP(U58,'CDV2 DTL'!P:P,1,FALSE)=U58,"OK","Missing") -> #N/A | X58: =IF(VLOOKUP(U58,'CDV3 DTL'!E:E,1,FALSE)=U58,"OK","Missing") -> #N/A | Z58: 17.12.2024 Potentially Obsolete to be checked | AE58: =IF(AD58="x",VLOOKUP($U58,DVS!A:A,1,FALSE),"-") -> - | AN58: =IF(AM58="x",VLOOKUP($U58,'Domain ControllerECU'!A:A,1,FALSE),"-") -> - | AQ58: =IF(AP58="x",VLOOKUP($U58,RLT!A:A,1,FALSE),"-") -> - | AT58: =IF(AS58="x",VLOOKUP($U58,ULSECU!A:A,1,FALSE),"-") -> - | AW58: =IF(AV58="x",VLOOKUP($U58,'Radar 7779GHz'!A:A,1,FALSE),"-") -> - | AZ58: =IF(AY58="x",VLOOKUP($U58,LiDAR!A:A,1,FALSE),"-") -> - | BF58: =IF(BE58="x",VLOOKUP($U58,DFC!A:A,1,FALSE),"-") -> - | BI58: =IF(BH58="x",VLOOKUP(U58,'DSF ADSP'!A:A,1,FALSE),"-") -> - | BL58: =IF(BK58="x",VLOOKUP($U58,'DSF LSMS'!$A:$A,1,FALSE),"-") -> -
B59: REG_140 | C59: 56 | D59: normal | E59: Obsolete | H59: =VLOOKUP(U59,'CDV3 DTL'!E:G,2,FALSE) -> #N/A | P59: China | Q59: =HYPERLINK("https://drive.google.com/open?id=144cP_ju01XKIwIahiohYrdwxwlytkNYj","GB 15084-2013") -> GB 15084-2013 | S59: 51 | T59: Regulations | U59: 12133_GB 15084-2013 | W59: =IF(VLOOKUP(U59,'CDV2 DTL'!P:P,1,FALSE)=U59,"OK","Missing") -> #N/A | X59: =IF(VLOOKUP(U59,'CDV3 DTL'!E:E,1,FALSE)=U59,"OK","Missing") -> #N/A | AD59: NA | AE59: =IF(AD59="x",VLOOKUP($U59,DVS!A:A,1,FALSE),"-") -> - | AG59: NA | AJ59: NA | AM59: NA | AN59: =IF(AM59="x",VLOOKUP($U59,'Domain ControllerECU'!A:A,1,FALSE),"-") -> - | AQ59: =IF(AP59="x",VLOOKUP($U59,RLT!A:A,1,FALSE),"-") -> - | AT59: =IF(AS59="x",VLOOKUP($U59,ULSECU!A:A,1,FALSE),"-") -> - | AW59: =IF(AV59="x",VLOOKUP($U59,'Radar 7779GHz'!A:A,1,FALSE),"-") -> - | AZ59: =IF(AY59="x",VLOOKUP($U59,LiDAR!A:A,1,FALSE),"-") -> - | BF59: =IF(BE59="x",VLOOKUP($U59,DFC!A:A,1,FALSE),"-") -> - | BI59: =IF(BH59="x",VLOOKUP(U59,'DSF ADSP'!A:A,1,FALSE),"-") -> - | BL59: =IF(BK59="x",VLOOKUP($U59,'DSF LSMS'!$A:$A,1,FALSE),"-") -> - | BM59: 20.02.2023 CLeanup in the regulation/ move to Obsolete
B60: REG_141 | C60: 57 | D60: low | E60: N/A | H60: =VLOOKUP(U60,'CDV3 DTL'!E:G,2,FALSE) -> #N/A | P60: UN | Q60: =HYPERLINK("https://drive.google.com/open?id=1CjqbtuzSEdxsg9CkpvYLHpMnP_Pu7ECs","UN ECE R6r6 Direction indicators") -> UN ECE R6r6 Direction indicators | S60: 39 | T60: Regulations | U60: 12134_UN ECE R6r6 Direction indicators | W60: =IF(VLOOKUP(U60,'CDV2 DTL'!P:P,1,FALSE)=U60,"OK","Missing") -> #N/A | X60: =IF(VLOOKUP(U60,'CDV3 DTL'!E:E,1,FALSE)=U60,"OK","Missing") -> #N/A | AE60: =IF(AD60="x",VLOOKUP($U60,DVS!A:A,1,FALSE),"-") -> - | AN60: =IF(AM60="x",VLOOKUP($U60,'Domain ControllerECU'!A:A,1,FALSE),"-") -> - | AQ60: =IF(AP60="x",VLOOKUP($U60,RLT!A:A,1,FALSE),"-") -> - | AT60: =IF(AS60="x",VLOOKUP($U60,ULSECU!A:A,1,FALSE),"-") -> - | AW60: =IF(AV60="x",VLOOKUP($U60,'Radar 7779GHz'!A:A,1,FALSE),"-") -> - | AZ60: =IF(AY60="x",VLOOKUP($U60,LiDAR!A:A,1,FALSE),"-") -> - | BF60: =IF(BE60="x",VLOOKUP($U60,DFC!A:A,1,FALSE),"-") -> - | BI60: =IF(BH60="x",VLOOKUP(U60,'DSF ADSP'!A:A,1,FALSE),"-") -> - | BL60: =IF(BK60="x",VLOOKUP($U60,'DSF LSMS'!$A:$A,1,FALSE),"-") -> -
B61: REG_142 | C61: 58 | D61: low | E61: N/A | H61: =VLOOKUP(U61,'CDV3 DTL'!E:G,2,FALSE) -> #N/A | N61: v | P61: EU | Q61: =HYPERLINK("https://drive.google.com/open?id=1E-f_0lwoQ3SCIibwJWfroOT6SujxJrnr","2000/53/EC_End of life vehicles_Consolidated Version 11-2017") -> 2000/53/EC_End of life vehicles_Consolidated Version 11-2017 | S61: 19 | T61: Regulations | U61: (-) | W61: =IF(VLOOKUP(U61,'CDV2 DTL'!P:P,1,FALSE)=U61,"OK","Missing") -> #N/A | X61: =IF(VLOOKUP(U61,'CDV3 DTL'!E:E,1,FALSE)=U61,"OK","Missing") -> #N/A | AE61: =IF(AD61="x",VLOOKUP($U61,DVS!A:A,1,FALSE),"-") -> - | AN61: =IF(AM61="x",VLOOKUP($U61,'Domain ControllerECU'!A:A,1,FALSE),"-") -> - | AQ61: =IF(AP61="x",VLOOKUP($U61,RLT!A:A,1,FALSE),"-") -> - | AT61: =IF(AS61="x",VLOOKUP($U61,ULSECU!A:A,1,FALSE),"-") -> - | AW61: =IF(AV61="x",VLOOKUP($U61,'Radar 7779GHz'!A:A,1,FALSE),"-") -> - | AZ61: =IF(AY61="x",VLOOKUP($U61,LiDAR!A:A,1,FALSE),"-") -> - | BF61: =IF(BE61="x",VLOOKUP($U61,DFC!A:A,1,FALSE),"-") -> - | BI61: =IF(BH61="x",VLOOKUP(U61,'DSF ADSP'!A:A,1,FALSE),"-") -> - | BL61: =IF(BK61="x",VLOOKUP($U61,'DSF LSMS'!$A:$A,1,FALSE),"-") -> -
B62: REG_143 | C62: 59 | D62: low | E62: N/A | H62: =VLOOKUP(#REF!,'CDV3 DTL'!E:G,2,FALSE) -> #REF! | P62: India | Q62: =HYPERLINK("https://drive.google.com/open?id=1sN-nMsPqZIXrf6kGuIeZxcygBPlSB1A9","AIS-004 Part 3_EMC") -> AIS-004 Part 3_EMC | S62: 67 | T62: Regulations | U62: (-) | W62: =IF(VLOOKUP(U62,'CDV2 DTL'!P:P,1,FALSE)=U62,"OK","Missing") -> #N/A | X62: =IF(VLOOKUP(#REF!,'CDV3 DTL'!E:E,1,FALSE)=#REF!,"OK","Missing") -> #REF! | AE62: =IF(AD62="x",VLOOKUP(#REF!,DVS!A:A,1,FALSE),"-") -> - | AN62: =IF(AM62="x",VLOOKUP(#REF!,'Domain ControllerECU'!A:A,1,FALSE),"-") -> - | AQ62: =IF(AP62="x",VLOOKUP(#REF!,RLT!A:A,1,FALSE),"-") -> - | AT62: =IF(AS62="x",VLOOKUP(#REF!,ULSECU!A:A,1,FALSE),"-") -> - | AW62: =IF(AV62="x",VLOOKUP(#REF!,'Radar 7779GHz'!A:A,1,FALSE),"-") -> - | AZ62: =IF(AY62="x",VLOOKUP(#REF!,LiDAR!A:A,1,FALSE),"-") -> - | BF62: =IF(BE62="x",VLOOKUP(#REF!,DFC!A:A,1,FALSE),"-") -> - | BI62: =IF(BH62="x",VLOOKUP(#REF!,'DSF ADSP'!A:A,1,FALSE),"-") -> - | BL62: =IF(BK62="x",VLOOKUP(#REF!,'DSF LSMS'!$A:$A,1,FALSE),"-") -> -
B63: REG_144 | C63: 60 | D63: low | E63: 10/10: Closed | H63: =VLOOKUP(U63,'CDV3 DTL'!E:G,2,FALSE) -> #N/A | P63: UN | Q63: =HYPERLINK("https://drive.google.com/open?id=13RORc-QEj7TQxbctrziWouyemvQhhOB0","UN ECE R123_ Adaptive Front-lighting systems") -> UN ECE R123_ Adaptive Front-lighting systems | S63: 83 | T63: Regulations | U63: 12137_UN ECE R123_ Adaptive Front-lighting systems | W63: =IF(VLOOKUP(U63,'CDV2 DTL'!P:P,1,FALSE)=U63,"OK","Missing") -> OK | X63: =IF(VLOOKUP(U63,'CDV3 DTL'!E:E,1,FALSE)=U63,"OK","Missing") -> #N/A | AE63: =IF(AD63="x",VLOOKUP($U63,DVS!A:A,1,FALSE),"-") -> - | AN63: =IF(AM63="x",VLOOKUP($U63,'Domain ControllerECU'!A:A,1,FALSE),"-") -> - | AP63: x | AQ63: =IF(AP63="x",VLOOKUP($U63,RLT!A:A,1,FALSE),"-") -> #N/A | AT63: =IF(AS63="x",VLOOKUP($U63,ULSECU!A:A,1,FALSE),"-") -> - | AW63: =IF(AV63="x",VLOOKUP($U63,'Radar 7779GHz'!A:A,1,FALSE),"-") -> - | AZ63: =IF(AY63="x",VLOOKUP($U63,LiDAR!A:A,1,FALSE),"-") -> - | BE63: ? | BF63: =IF(BE63="x",VLOOKUP($U63,DFC!A:A,1,FALSE),"-") -> - | BI63: =IF(BH63="x",VLOOKUP(U63,'DSF ADSP'!A:A,1,FALSE),"-") -> - | BL63: =IF(BK63="x",VLOOKUP($U63,'DSF LSMS'!$A:$A,1,FALSE),"-") -> -
B64: REG_145 | C64: 61 | D64: normal | E64: 10/10: Closed | H64: =VLOOKUP(U62,'CDV3 DTL'!E:G,2,FALSE) -> #N/A | P64: USA | Q64: =HYPERLINK("https://drive.google.com/open?id=1OItaKE4YQjV67tHzVrd-Ste2v6Tn_u--","CFR 21 Section 1040 Laser Products") -> CFR 21 Section 1040 Laser Products | S64: 18 | T64: Regulations | U64: 12138_CFR 21 Section 1040 Laser Products | W64: =IF(VLOOKUP(U64,'CDV2 DTL'!P:P,1,FALSE)=U64,"OK","Missing") -> OK | X64: =IF(VLOOKUP(U62,'CDV3 DTL'!E:E,1,FALSE)=U62,"OK","Missing") -> #N/A | AE64: =IF(AD64="x",VLOOKUP($U62,DVS!A:A,1,FALSE),"-") -> - | AN64: =IF(AM64="x",VLOOKUP($U62,'Domain ControllerECU'!A:A,1,FALSE),"-") -> - | AQ64: =IF(AP64="x",VLOOKUP($U62,RLT!A:A,1,FALSE),"-") -> - | AT64: =IF(AS64="x",VLOOKUP($U62,ULSECU!A:A,1,FALSE),"-") -> - | AW64: =IF(AV64="x",VLOOKUP($U62,'Radar 7779GHz'!A:A,1,FALSE),"-") -> - | AY64: x | AZ64: =IF(AY64="x",VLOOKUP($U62,LiDAR!A:A,1,FALSE),"-") -> #N/A | BF64: =IF(BE64="x",VLOOKUP($U62,DFC!A:A,1,FALSE),"-") -> - | BI64: =IF(BH64="x",VLOOKUP(U62,'DSF ADSP'!A:A,1,FALSE),"-") -> - | BL64: =IF(BK64="x",VLOOKUP($U62,'DSF LSMS'!$A:$A,1,FALSE),"-") -> -
B65: REG_146 | C65: 62 | D65: low | E65: 10/10: Closed | H65: =VLOOKUP(U65,'CDV3 DTL'!E:G,2,FALSE) -> #N/A | P65: EU | Q65: =HYPERLINK("https://drive.google.com/open?id=1sjAs9WDwGIgzJQ1bCfBv5SEAmcKaE6Td","Decision 2005/50/EC_24GHz_Range") -> Decision 2005/50/EC_24GHz_Range | S65: 6 | T65: Regulations | U65: 12139_Decision 2005_50_EC_24GHz_Range | W65: =IF(VLOOKUP(U65,'CDV2 DTL'!P:P,1,FALSE)=U65,"OK","Missing") -> OK | X65: =IF(VLOOKUP(U65,'CDV3 DTL'!E:E,1,FALSE)=U65,"OK","Missing") -> #N/A | AE65: =IF(AD65="x",VLOOKUP($U65,DVS!A:A,1,FALSE),"-") -> - | AN65: =IF(AM65="x",VLOOKUP($U65,'Domain ControllerECU'!A:A,1,FALSE),"-") -> - | AQ65: =IF(AP65="x",VLOOKUP($U65,RLT!A:A,1,FALSE),"-") -> - | AT65: =IF(AS65="x",VLOOKUP($U65,ULSECU!A:A,1,FALSE),"-") -> - | AV65: x | AW65: =IF(AV65="x",VLOOKUP($U65,'Radar 7779GHz'!A:A,1,FALSE),"-") -> #N/A | AZ65: =IF(AY65="x",VLOOKUP($U65,LiDAR!A:A,1,FALSE),"-") -> - | BF65: =IF(BE65="x",VLOOKUP($U65,DFC!A:A,1,FALSE),"-") -> - | BI65: =IF(BH65="x",VLOOKUP(U65,'DSF ADSP'!A:A,1,FALSE),"-") -> - | BL65: =IF(BK65="x",VLOOKUP($U65,'DSF LSMS'!$A:$A,1,FALSE),"-") -> -
B66: REG_147 | C66: 63 | D66: low | E66: N/A | H66: =VLOOKUP(U66,'CDV3 DTL'!E:G,2,FALSE) -> #N/A | P66: China | Q66: =HYPERLINK("https://drive.google.com/open?id=1B3hk-lHpNjsDZcQx7CLQsLtmWY8EIk3b","GB 17675-1999_ Steering Systems") -> GB 17675-1999_ Steering Systems | S66: 4 | T66: Regulations | U66: 12140_GB 17675-1999_ Steering Systems | W66: =IF(VLOOKUP(U66,'CDV2 DTL'!P:P,1,FALSE)=U66,"OK","Missing") -> #N/A | X66: =IF(VLOOKUP(U66,'CDV3 DTL'!E:E,1,FALSE)=U66,"OK","Missing") -> #N/A | AE66: =IF(AD66="x",VLOOKUP($U66,DVS!A:A,1,FALSE),"-") -> - | AN66: =IF(AM66="x",VLOOKUP($U66,'Domain ControllerECU'!A:A,1,FALSE),"-") -> - | AQ66: =IF(AP66="x",VLOOKUP($U66,RLT!A:A,1,FALSE),"-") -> - | AT66: =IF(AS66="x",VLOOKUP($U66,ULSECU!A:A,1,FALSE),"-") -> - | AW66: =IF(AV66="x",VLOOKUP($U66,'Radar 7779GHz'!A:A,1,FALSE),"-") -> - | AZ66: =IF(AY66="x",VLOOKUP($U66,LiDAR!A:A,1,FALSE),"-") -> - | BF66: =IF(BE66="x",VLOOKUP($U66,DFC!A:A,1,FALSE),"-") -> - | BI66: =IF(BH66="x",VLOOKUP(U66,'DSF ADSP'!A:A,1,FALSE),"-") -> - | BL66: =IF(BK66="x",VLOOKUP($U66,'DSF LSMS'!$A:$A,1,FALSE),"-") -> -
B67: REG_148 | C67: 64 | D67: low | E67: 10/10: Closed | H67: =VLOOKUP(U67,'CDV3 DTL'!E:G,2,FALSE) -> #N/A | O67: all | P67: UN | Q67: =HYPERLINK("https://drive.google.com/open?id=10iKtlZaO-_RHS7KTJm8StCcN1OAfnZF5","UN ECE R26r1 Am1 External Projections") -> UN ECE R26r1 Am1 External Projections | S67: 2 | T67: Regulations | U67: 12141_UN ECE R26r1 Am1 External Projections | W67: =IF(VLOOKUP(U67,'CDV2 DTL'!P:P,1,FALSE)=U67,"OK","Missing") -> OK | X67: =IF(VLOOKUP(U67,'CDV3 DTL'!E:E,1,FALSE)=U67,"OK","Missing") -> #N/A | AE67: =IF(AD67="x",VLOOKUP($U67,DVS!A:A,1,FALSE),"-") -> - | AN67: =IF(AM67="x",VLOOKUP($U67,'Domain ControllerECU'!A:A,1,FALSE),"-") -> - | AQ67: =IF(AP67="x",VLOOKUP($U67,RLT!A:A,1,FALSE),"-") -> - | AT67: =IF(AS67="x",VLOOKUP($U67,ULSECU!A:A,1,FALSE),"-") -> - | AW67: =IF(AV67="x",VLOOKUP($U67,'Radar 7779GHz'!A:A,1,FALSE),"-") -> - | AZ67: =IF(AY67="x",VLOOKUP($U67,LiDAR!A:A,1,FALSE),"-") -> - | BF67: =IF(BE67="x",VLOOKUP($U67,DFC!A:A,1,FALSE),"-") -> - | BI67: =IF(BH67="x",VLOOKUP(U67,'DSF ADSP'!A:A,1,FALSE),"-") -> - | BL67: =IF(BK67="x",VLOOKUP($U67,'DSF LSMS'!$A:$A,1,FALSE),"-") -> -
B68: REG_149 | C68: 65 | D68: high | E68: 10/10: Closed | H68: =VLOOKUP(U68,'CDV3 DTL'!E:G,2,FALSE) -> #N/A | P68: Japan | Q68: =HYPERLINK("https://drive.google.com/open?id=0B41cx_IVa9ynOUFTbXJ5VGM2Nml4YXB6eHJzMHp1bnBENFpz","BlueBook_Japan_Attachment 81_2017") -> BlueBook_Japan_Attachment 81_2017 | S68: 10 | T68: Regulations | U68: 12143_BlueBook_2017-11-15_Attachment 81_Mirrors_immediate front and left side | W68: =IF(VLOOKUP(U68,'CDV2 DTL'!P:P,1,FALSE)=U68,"OK","Missing") -> OK | X68: =IF(VLOOKUP(U68,'CDV3 DTL'!E:E,1,FALSE)=U68,"OK","Missing") -> #N/A | AD68: x | AE68: =IF(AD68="x",VLOOKUP($U68,DVS!A:A,1,FALSE),"-") -> #N/A | AG68: x | AJ68: x | AN68: =IF(AM68="x",VLOOKUP($U68,'Domain ControllerECU'!A:A,1,FALSE),"-") -> - | AQ68: =IF(AP68="x",VLOOKUP($U68,RLT!A:A,1,FALSE),"-") -> - | AT68: =IF(AS68="x",VLOOKUP($U68,ULSECU!A:A,1,FALSE),"-") -> - | AW68: =IF(AV68="x",VLOOKUP($U68,'Radar 7779GHz'!A:A,1,FALSE),"-") -> - | AZ68: =IF(AY68="x",VLOOKUP($U68,LiDAR!A:A,1,FALSE),"-") -> - | BF68: =IF(BE68="x",VLOOKUP($U68,DFC!A:A,1,FALSE),"-") -> - | BI68: =IF(BH68="x",VLOOKUP(U68,'DSF ADSP'!A:A,1,FALSE),"-") -> - | BL68: =IF(BK68="x",VLOOKUP($U68,'DSF LSMS'!$A:$A,1,FALSE),"-") -> -
B69: REG_150 | C69: 66 | D69: normal | E69: 10/10: Closed | H69: =VLOOKUP(U69,'CDV3 DTL'!E:G,2,FALSE) -> #N/A | P69: China | Q69: =HYPERLINK("https://drive.google.com/open?id=1bMcr521yb8fpmQVQMMhQwptbaeYzjm51","CN_GB_34660-2017_EN_2018-09-03") -> CN_GB_34660-2017_EN_2018-09-03 | S69: 24 | T69: Regulations | U69: 12144_CN_GB_34660-2017_EN_2018-09-03 | W69: =IF(VLOOKUP(U69,'CDV2 DTL'!P:P,1,FALSE)=U69,"OK","Missing") -> OK | X69: =IF(VLOOKUP(U69,'CDV3 DTL'!E:E,1,FALSE)=U69,"OK","Missing") -> #N/A | AE69: =IF(AD69="x",VLOOKUP($U69,DVS!A:A,1,FALSE),"-") -> - | AN69: =IF(AM69="x",VLOOKUP($U69,'Domain ControllerECU'!A:A,1,FALSE),"-") -> - | AQ69: =IF(AP69="x",VLOOKUP($U69,RLT!A:A,1,FALSE),"-") -> - | AT69: =IF(AS69="x",VLOOKUP($U69,ULSECU!A:A,1,FALSE),"-") -> - | AW69: =IF(AV69="x",VLOOKUP($U69,'Radar 7779GHz'!A:A,1,FALSE),"-") -> - | AZ69: =IF(AY69="x",VLOOKUP($U69,LiDAR!A:A,1,FALSE),"-") -> - | BF69: =IF(BE69="x",VLOOKUP($U69,DFC!A:A,1,FALSE),"-") -> - | BI69: =IF(BH69="x",VLOOKUP(U69,'DSF ADSP'!A:A,1,FALSE),"-") -> - | BL69: =IF(BK69="x",VLOOKUP($U69,'DSF LSMS'!$A:$A,1,FALSE),"-") -> -
B70: REG_151 | C70: 67 | D70: high | E70: 10/10: Closed | H70: =VLOOKUP(U70,'CDV3 DTL'!E:G,2,FALSE) -> #N/A | P70: India | Q70: =HYPERLINK("https://drive.google.com/open?id=1AG9m8Z23mhEBixeiNP7ZLcOYn1TUM9i-","AIS-145_2018-04_Additional Safety features for Category M & N Vehicles") -> AIS-145_2018-04_Additional Safety features for Category M & N Vehicles | S70: 29 | T70: Regulations | U70: 12145_AIS_145_2018_04_Additional Safety features for Category M and N Vehicles | W70: =IF(VLOOKUP(U70,'CDV2 DTL'!P:P,1,FALSE)=U70,"OK","Missing") -> OK | X70: =IF(VLOOKUP(U70,'CDV3 DTL'!E:E,1,FALSE)=U70,"OK","Missing") -> #N/A | AA70: DUS_ULS&ECU, DVS_System | AB70: https://docs.google.com/spreadsheets/d/1lnGus5DlN99pf0619_v7O7hj86kqNdFG/edit?usp=sharing&ouid=115910244335210838264&rtpof=true&sd=true | AD70: X | AE70: =IF(AD70="x",VLOOKUP($U70,DVS!A:A,1,FALSE),"-") -> #N/A | AJ70: X | AN70: =IF(AM70="x",VLOOKUP($U70,'Domain ControllerECU'!A:A,1,FALSE),"-") -> - | AQ70: =IF(AP70="x",VLOOKUP($U70,RLT!A:A,1,FALSE),"-") -> - | AS70: x | AT70: =IF(AS70="x",VLOOKUP($U70,ULSECU!A:A,1,FALSE),"-") -> #N/A | AW70: =IF(AV70="x",VLOOKUP($U70,'Radar 7779GHz'!A:A,1,FALSE),"-") -> - | AZ70: =IF(AY70="x",VLOOKUP($U70,LiDAR!A:A,1,FALSE),"-") -> - | BF70: =IF(BE70="x",VLOOKUP($U70,DFC!A:A,1,FALSE),"-") -> - | BI70: =IF(BH70="x",VLOOKUP(U70,'DSF ADSP'!A:A,1,FALSE),"-") -> - | BK70: x | BL70: =IF(BK70="x",VLOOKUP($U70,'DSF LSMS'!$A:$A,1,FALSE),"-") -> #N/A | BM70: DSF LSMS Warning Team dina.abdel-hamid@valeo.com
B71: REG_152 | C71: 68 | D71: normal | E71: 10/10: Closed | H71: =VLOOKUP(U71,'CDV3 DTL'!E:G,2,FALSE) -> #N/A | P71: Singapur | Q71: =HYPERLINK("https://drive.google.com/open?id=1_y823l7iNlZf-CHn0w-hWNQRHgVW8R4d","SG_Master_Plan_Radio_Spectrum_2012-11_EN_2013-04-09") -> SG_Master_Plan_Radio_Spectrum_2012-11_EN_2013-04-09 | S71: 21 | T71: Regulations | U71: 12146_SG_Master_Plan_Radio_Spectrum_2012-11_EN_2013-04-09 | W71: =IF(VLOOKUP(U71,'CDV2 DTL'!P:P,1,FALSE)=U71,"OK","Missing") -> OK | X71: =IF(VLOOKUP(U71,'CDV3 DTL'!E:E,1,FALSE)=U71,"OK","Missing") -> #N/A | AE71: =IF(AD71="x",VLOOKUP($U71,DVS!A:A,1,FALSE),"-") -> - | AN71: =IF(AM71="x",VLOOKUP($U71,'Domain ControllerECU'!A:A,1,FALSE),"-") -> - | AQ71: =IF(AP71="x",VLOOKUP($U71,RLT!A:A,1,FALSE),"-") -> - | AT71: =IF(AS71="x",VLOOKUP($U71,ULSECU!A:A,1,FALSE),"-") -> - | AV71: x | AW71: =IF(AV71="x",VLOOKUP($U71,'Radar 7779GHz'!A:A,1,FALSE),"-") -> #N/A | AZ71: =IF(AY71="x",VLOOKUP($U71,LiDAR!A:A,1,FALSE),"-") -> - | BF71: =IF(BE71="x",VLOOKUP($U71,DFC!A:A,1,FALSE),"-") -> - | BI71: =IF(BH71="x",VLOOKUP(U71,'DSF ADSP'!A:A,1,FALSE),"-") -> - | BL71: =IF(BK71="x",VLOOKUP($U71,'DSF LSMS'!$A:$A,1,FALSE),"-") -> -
B72: REG_153 | C72: 69 | D72: normal | E72: 10/10: Closed | H72: =VLOOKUP(U72,'CDV3 DTL'!E:G,2,FALSE) -> #N/A | P72: Taiwan | Q72: =HYPERLINK("https://drive.google.com/open?id=1H8Xthmv_TcskMLIo6n_HLn2uXca-hdA6","2018-01-10_Taiwan_Low-power Radio-frequency Devices Technical Regulations") -> 2018-01-10_Taiwan_Low-power Radio-frequency Devices Technical Regulations | S72: 66 | T72: Regulations | U72: 12147_2018-01-10_Taiwan_Low-power Radio-frequency Devices Technical Regulations | W72: =IF(VLOOKUP(U72,'CDV2 DTL'!P:P,1,FALSE)=U72,"OK","Missing") -> OK | X72: =IF(VLOOKUP(U72,'CDV3 DTL'!E:E,1,FALSE)=U72,"OK","Missing") -> #N/A | AE72: =IF(AD72="x",VLOOKUP($U72,DVS!A:A,1,FALSE),"-") -> - | AN72: =IF(AM72="x",VLOOKUP($U72,'Domain ControllerECU'!A:A,1,FALSE),"-") -> - | AQ72: =IF(AP72="x",VLOOKUP($U72,RLT!A:A,1,FALSE),"-") -> - | AT72: =IF(AS72="x",VLOOKUP($U72,ULSECU!A:A,1,FALSE),"-") -> - | AV72: x | AW72: =IF(AV72="x",VLOOKUP($U72,'Radar 7779GHz'!A:A,1,FALSE),"-") -> #N/A | AZ72: =IF(AY72="x",VLOOKUP($U72,LiDAR!A:A,1,FALSE),"-") -> - | BF72: =IF(BE72="x",VLOOKUP($U72,DFC!A:A,1,FALSE),"-") -> - | BI72: =IF(BH72="x",VLOOKUP(U72,'DSF ADSP'!A:A,1,FALSE),"-") -> - | BL72: =IF(BK72="x",VLOOKUP($U72,'DSF LSMS'!$A:$A,1,FALSE),"-") -> -
B73: REG_155 | C73: 70 | D73: normal | E73: Obsolete | H73: =VLOOKUP(U73,'CDV3 DTL'!E:G,2,FALSE) -> #N/A | P73: EU | Q73: =HYPERLINK("https://drive.google.com/open?id=1VAGxCDaniU_0JecQ6BhnPmNLSftxlyVM","EUNCAP_AEB Car2Car V2.0.1") -> EUNCAP_AEB Car2Car V2.0.1 | S73: 25 | T73: Standard | W73: =IF(VLOOKUP(U73,'CDV2 DTL'!P:P,1,FALSE)=U73,"OK","Missing") -> #N/A | X73: =IF(VLOOKUP(U73,'CDV3 DTL'!E:E,1,FALSE)=U73,"OK","Missing") -> #N/A | AE73: =IF(AD73="x",VLOOKUP($U73,DVS!A:A,1,FALSE),"-") -> - | AN73: =IF(AM73="x",VLOOKUP($U73,'Domain ControllerECU'!A:A,1,FALSE),"-") -> - | AQ73: =IF(AP73="x",VLOOKUP($U73,RLT!A:A,1,FALSE),"-") -> - | AT73: =IF(AS73="x",VLOOKUP($U73,ULSECU!A:A,1,FALSE),"-") -> - | AW73: =IF(AV73="x",VLOOKUP($U73,'Radar 7779GHz'!A:A,1,FALSE),"-") -> - | AZ73: =IF(AY73="x",VLOOKUP($U73,LiDAR!A:A,1,FALSE),"-") -> - | BF73: =IF(BE73="x",VLOOKUP($U73,DFC!A:A,1,FALSE),"-") -> - | BI73: =IF(BH73="x",VLOOKUP(U73,'DSF ADSP'!A:A,1,FALSE),"-") -> - | BL73: =IF(BK73="x",VLOOKUP($U73,'DSF LSMS'!$A:$A,1,FALSE),"-") -> -
B74: REG_156 | C74: 71 | D74: normal | E74: 10/10: Closed | H74: =VLOOKUP(U74,'CDV3 DTL'!E:G,2,FALSE) -> #N/A | P74: USA | Q74: =HYPERLINK("https://drive.google.com/open?id=1CAyaBOt29KQat-osgV1d8m1_bOXZ-hKd","CFR 47 Part95 Subpart M_76–81 GHz Band Radar Service") -> CFR 47 Part95 Subpart M_76–81 GHz Band Radar Service | S74: 2 | T74: Regulations | U74: 12150_CFR 47 Part95 Subpart M_76–81 GHz Band Radar Service | W74: OK | X74: =IF(VLOOKUP(U74,'CDV3 DTL'!E:E,1,FALSE)=U74,"OK","Missing") -> #N/A | AE74: =IF(AD74="x",VLOOKUP($U74,DVS!A:A,1,FALSE),"-") -> - | AN74: =IF(AM74="x",VLOOKUP($U74,'Domain ControllerECU'!A:A,1,FALSE),"-") -> - | AQ74: =IF(AP74="x",VLOOKUP($U74,RLT!A:A,1,FALSE),"-") -> - | AT74: =IF(AS74="x",VLOOKUP($U74,ULSECU!A:A,1,FALSE),"-") -> - | AV74: x | AW74: =IF(AV74="x",VLOOKUP($U74,'Radar 7779GHz'!A:A,1,FALSE),"-") -> #N/A | AZ74: =IF(AY74="x",VLOOKUP($U74,LiDAR!A:A,1,FALSE),"-") -> - | BF74: =IF(BE74="x",VLOOKUP($U74,DFC!A:A,1,FALSE),"-") -> - | BI74: =IF(BH74="x",VLOOKUP(U74,'DSF ADSP'!A:A,1,FALSE),"-") -> - | BL74: =IF(BK74="x",VLOOKUP($U74,'DSF LSMS'!$A:$A,1,FALSE),"-") -> -
B75: REG_157 | C75: 72 | D75: low | E75: 10/10: Closed | H75: =VLOOKUP(U75,'CDV3 DTL'!E:G,2,FALSE) -> #N/A | P75: China | Q75: =HYPERLINK("https://drive.google.com/open?id=1Q9WLbjY5RSIrzY_WeoDlCIFZ5FRHzkli","GB 21670-2008_Braking") -> GB 21670-2008_Braking | S75: 90 | T75: Regulations | U75: 12151_GB 21670-2008_Braking | W75: =IF(VLOOKUP(U75,'CDV2 DTL'!P:P,1,FALSE)=U75,"OK","Missing") -> OK | X75: =IF(VLOOKUP(U75,'CDV3 DTL'!E:E,1,FALSE)=U75,"OK","Missing") -> #N/A | AE75: =IF(AD75="x",VLOOKUP($U75,DVS!A:A,1,FALSE),"-") -> - | AN75: =IF(AM75="x",VLOOKUP($U75,'Domain ControllerECU'!A:A,1,FALSE),"-") -> - | AQ75: =IF(AP75="x",VLOOKUP($U75,RLT!A:A,1,FALSE),"-") -> - | AT75: =IF(AS75="x",VLOOKUP($U75,ULSECU!A:A,1,FALSE),"-") -> - | AW75: =IF(AV75="x",VLOOKUP($U75,'Radar 7779GHz'!A:A,1,FALSE),"-") -> - | AZ75: =IF(AY75="x",VLOOKUP($U75,LiDAR!A:A,1,FALSE),"-") -> - | BF75: =IF(BE75="x",VLOOKUP($U75,DFC!A:A,1,FALSE),"-") -> - | BI75: =IF(BH75="x",VLOOKUP(U75,'DSF ADSP'!A:A,1,FALSE),"-") -> - | BL75: =IF(BK75="x",VLOOKUP($U75,'DSF LSMS'!$A:$A,1,FALSE),"-") -> -
B76: REG_158 | C76: 73 | D76: normal | E76: 10/10: Closed | H76: =VLOOKUP(U76,'CDV3 DTL'!E:G,2,FALSE) -> #N/A | P76: USA | Q76: =HYPERLINK("https://drive.google.com/open?id=1x7a0nCalJFtuGgpqtNGaX-uQh15vxpM4","CFR 21 Section 1010 General") -> CFR 21 Section 1010 General | S76: 6 | T76: Regulations | U76: 12152_CFR 21 Section 1010 General | W76: =IF(VLOOKUP(U76,'CDV2 DTL'!P:P,1,FALSE)=U76,"OK","Missing") -> OK | X76: =IF(VLOOKUP(U76,'CDV3 DTL'!E:E,1,FALSE)=U76,"OK","Missing") -> #N/A | AE76: =IF(AD76="x",VLOOKUP($U76,DVS!A:A,1,FALSE),"-") -> - | AN76: =IF(AM76="x",VLOOKUP($U76,'Domain ControllerECU'!A:A,1,FALSE),"-") -> - | AQ76: =IF(AP76="x",VLOOKUP($U76,RLT!A:A,1,FALSE),"-") -> - | AT76: =IF(AS76="x",VLOOKUP($U76,ULSECU!A:A,1,FALSE),"-") -> - | AW76: =IF(AV76="x",VLOOKUP($U76,'Radar 7779GHz'!A:A,1,FALSE),"-") -> - | AY76: x | AZ76: =IF(AY76="x",VLOOKUP($U76,LiDAR!A:A,1,FALSE),"-") -> #N/A | BF76: =IF(BE76="x",VLOOKUP($U76,DFC!A:A,1,FALSE),"-") -> - | BI76: =IF(BH76="x",VLOOKUP(U76,'DSF ADSP'!A:A,1,FALSE),"-") -> - | BL76: =IF(BK76="x",VLOOKUP($U76,'DSF LSMS'!$A:$A,1,FALSE),"-") -> -
B77: REG_159 | C77: 74 | D77: low | E77: 10/10: Closed | H77: =VLOOKUP(U77,'CDV3 DTL'!E:G,2,FALSE) -> #N/A | P77: UN | Q77: =HYPERLINK("https://drive.google.com/open?id=1m4XY8cBp2pWNcmCD5_WS7RU4w34ef-d0","UN ECE R121r2 Am1_HMI") -> UN ECE R121r2 Am1_HMI | S77: 2 | T77: Regulations | U77: 12153_UN ECE R121r2 Am1_HMI | W77: =IF(VLOOKUP(U77,'CDV2 DTL'!P:P,1,FALSE)=U77,"OK","Missing") -> OK | X77: =IF(VLOOKUP(U77,'CDV3 DTL'!E:E,1,FALSE)=U77,"OK","Missing") -> #N/A | AE77: =IF(AD77="x",VLOOKUP($U77,DVS!A:A,1,FALSE),"-") -> - | AN77: =IF(AM77="x",VLOOKUP($U77,'Domain ControllerECU'!A:A,1,FALSE),"-") -> - | AQ77: =IF(AP77="x",VLOOKUP($U77,RLT!A:A,1,FALSE),"-") -> - | AT77: =IF(AS77="x",VLOOKUP($U77,ULSECU!A:A,1,FALSE),"-") -> - | AW77: =IF(AV77="x",VLOOKUP($U77,'Radar 7779GHz'!A:A,1,FALSE),"-") -> - | AZ77: =IF(AY77="x",VLOOKUP($U77,LiDAR!A:A,1,FALSE),"-") -> - | BF77: =IF(BE77="x",VLOOKUP($U77,DFC!A:A,1,FALSE),"-") -> - | BI77: =IF(BH77="x",VLOOKUP(U77,'DSF ADSP'!A:A,1,FALSE),"-") -> - | BL77: =IF(BK77="x",VLOOKUP($U77,'DSF LSMS'!$A:$A,1,FALSE),"-") -> -
B78: REG_160 | C78: 75 | D78: low | E78: Obsolete | H78: =VLOOKUP(U78,'CDV3 DTL'!E:G,2,FALSE) -> #N/A | J78: x | O78: N2-N3; M2-M3 | P78: UN | Q78: =HYPERLINK("https://drive.google.com/open?id=14DlF2P_CeERMuY6tddCY3NiWIwQHybPS","UN ECE R130 Am1_LDWS_Trucks") -> UN ECE R130 Am1_LDWS_Trucks | S78: 2 | T78: Regulations | U78: 12154_UN ECE R130 Am1_LDWS_Trucks | W78: =IF(VLOOKUP(U78,'CDV2 DTL'!P:P,1,FALSE)=U78,"OK","Missing") -> #N/A | X78: =IF(VLOOKUP(U78,'CDV3 DTL'!E:E,1,FALSE)=U78,"OK","Missing") -> #N/A | AE78: =IF(AD78="x",VLOOKUP($U78,DVS!A:A,1,FALSE),"-") -> - | AN78: =IF(AM78="x",VLOOKUP($U78,'Domain ControllerECU'!A:A,1,FALSE),"-") -> - | AQ78: =IF(AP78="x",VLOOKUP($U78,RLT!A:A,1,FALSE),"-") -> - | AT78: =IF(AS78="x",VLOOKUP($U78,ULSECU!A:A,1,FALSE),"-") -> - | AW78: =IF(AV78="x",VLOOKUP($U78,'Radar 7779GHz'!A:A,1,FALSE),"-") -> - | AZ78: =IF(AY78="x",VLOOKUP($U78,LiDAR!A:A,1,FALSE),"-") -> - | BF78: =IF(BE78="x",VLOOKUP($U78,DFC!A:A,1,FALSE),"-") -> - | BH78: x | BI78: =IF(BH78="x",VLOOKUP(U78,'DSF ADSP'!A:A,1,FALSE),"-") -> #N/A | BL78: =IF(BK78="x",VLOOKUP($U78,'DSF LSMS'!$A:$A,1,FALSE),"-") -> -
B79: REG_161 | C79: 76 | D79: low | E79: Obsolete | H79: =VLOOKUP(U79,'CDV3 DTL'!E:G,2,FALSE) -> #N/A | J79: x | M79: 2016 | O79: N2-N3; M2-M3 | P79: UN | Q79: =HYPERLINK("https://drive.google.com/open?id=11cq9uDPCMvp7wa1Hthw3NJ4R8kwiJzjy","UN ECE R 131 r1_Am1_AEBS_Trucks") -> UN ECE R 131 r1_Am1_AEBS_Trucks | S79: 2 | T79: Regulations | U79: 12155_UN ECE R131r1_Am1_AEBS_Trucks | W79: =IF(VLOOKUP(U79,'CDV2 DTL'!P:P,1,FALSE)=U79,"OK","Missing") -> #N/A | X79: =IF(VLOOKUP(U79,'CDV3 DTL'!E:E,1,FALSE)=U79,"OK","Missing") -> #N/A | AE79: =IF(AD79="x",VLOOKUP($U79,DVS!A:A,1,FALSE),"-") -> - | AN79: =IF(AM79="x",VLOOKUP($U79,'Domain ControllerECU'!A:A,1,FALSE),"-") -> - | AQ79: =IF(AP79="x",VLOOKUP($U79,RLT!A:A,1,FALSE),"-") -> - | AT79: =IF(AS79="x",VLOOKUP($U79,ULSECU!A:A,1,FALSE),"-") -> - | AV79: x | AW79: =IF(AV79="x",VLOOKUP($U79,'Radar 7779GHz'!A:A,1,FALSE),"-") -> #N/A | AZ79: =IF(AY79="x",VLOOKUP($U79,LiDAR!A:A,1,FALSE),"-") -> - | BE79: x | BF79: =IF(BE79="x",VLOOKUP($U79,DFC!A:A,1,FALSE),"-") -> #N/A | BI79: =IF(BH79="x",VLOOKUP(U79,'DSF ADSP'!A:A,1,FALSE),"-") -> - | BL79: =IF(BK79="x",VLOOKUP($U79,'DSF LSMS'!$A:$A,1,FALSE),"-") -> -
B80: REG_162 | C80: 77 | D80: low | E80: Obsolete | H80: =VLOOKUP(U80,'CDV3 DTL'!E:G,2,FALSE) -> #N/A | P80: EU | Q80: =HYPERLINK("https://drive.google.com/open?id=11erleIhncQyJaBQj0KX-RKl93nL-jBSA","Decision_2004/545/EC_79GHz range") -> Decision_2004/545/EC_79GHz range | S80: 2 | T80: Regulations | U80: (-) | W80: =IF(VLOOKUP(U80,'CDV2 DTL'!P:P,1,FALSE)=U80,"OK","Missing") -> #N/A | X80: =IF(VLOOKUP(U80,'CDV3 DTL'!E:E,1,FALSE)=U80,"OK","Missing") -> #N/A | AE80: =IF(AD80="x",VLOOKUP($U80,DVS!A:A,1,FALSE),"-") -> - | AN80: =IF(AM80="x",VLOOKUP($U80,'Domain ControllerECU'!A:A,1,FALSE),"-") -> - | AQ80: =IF(AP80="x",VLOOKUP($U80,RLT!A:A,1,FALSE),"-") -> - | AT80: =IF(AS80="x",VLOOKUP($U80,ULSECU!A:A,1,FALSE),"-") -> - | AV80: x | AW80: =IF(AV80="x",VLOOKUP($U80,'Radar 7779GHz'!A:A,1,FALSE),"-") -> #N/A | AZ80: =IF(AY80="x",VLOOKUP($U80,LiDAR!A:A,1,FALSE),"-") -> - | BF80: =IF(BE80="x",VLOOKUP($U80,DFC!A:A,1,FALSE),"-") -> - | BI80: =IF(BH80="x",VLOOKUP(U80,'DSF ADSP'!A:A,1,FALSE),"-") -> - | BL80: =IF(BK80="x",VLOOKUP($U80,'DSF LSMS'!$A:$A,1,FALSE),"-") -> -
B81: REG_163 | C81: 78 | D81: Low | E81: Obsolete | H81: =VLOOKUP(U81,'CDV3 DTL'!E:G,2,FALSE) -> #N/A | P81: USA | Q81: =HYPERLINK("https://drive.google.com/open?id=1srRO18LzjDr6JHCKg2HlNaZ3OJRmyLds","CFR 49 Part 581 Bumber Standard") -> CFR 49 Part 581 Bumber Standard | S81: 5 | T81: Regulations | U81: (-) | W81: =IF(VLOOKUP(U81,'CDV2 DTL'!P:P,1,FALSE)=U81,"OK","Missing") -> #N/A | X81: =IF(VLOOKUP(U81,'CDV3 DTL'!E:E,1,FALSE)=U81,"OK","Missing") -> #N/A | AE81: =IF(AD81="x",VLOOKUP($U81,DVS!A:A,1,FALSE),"-") -> - | AG81: x | AJ81: x | AN81: =IF(AM81="x",VLOOKUP($U81,'Domain ControllerECU'!A:A,1,FALSE),"-") -> - | AQ81: =IF(AP81="x",VLOOKUP($U81,RLT!A:A,1,FALSE),"-") -> - | AT81: =IF(AS81="x",VLOOKUP($U81,ULSECU!A:A,1,FALSE),"-") -> - | AW81: =IF(AV81="x",VLOOKUP($U81,'Radar 7779GHz'!A:A,1,FALSE),"-") -> - | AZ81: =IF(AY81="x",VLOOKUP($U81,LiDAR!A:A,1,FALSE),"-") -> - | BF81: =IF(BE81="x",VLOOKUP($U81,DFC!A:A,1,FALSE),"-") -> - | BI81: =IF(BH81="x",VLOOKUP(U81,'DSF ADSP'!A:A,1,FALSE),"-") -> - | BL81: =IF(BK81="x",VLOOKUP($U81,'DSF LSMS'!$A:$A,1,FALSE),"-") -> -
B82: REG_164 | C82: 79 | D82: low | E82: Obsolete | H82: =VLOOKUP(U82,'CDV3 DTL'!E:G,2,FALSE) -> #N/A | P82: EU | Q82: =HYPERLINK("https://drive.google.com/open?id=0B41cx_IVa9ynNFJ0WWJxcERrdFdOcjdXMUZGaGlCR2NNMDJB","2019-02_Version4.1.GUIDELINE EU APPROVAL OF AD VEHICLES") -> 2019-02_Version4.1.GUIDELINE EU APPROVAL OF AD VEHICLES | S82: 10 | T82: Regulations | W82: =IF(VLOOKUP(U82,'CDV2 DTL'!P:P,1,FALSE)=U82,"OK","Missing") -> #N/A | X82: =IF(VLOOKUP(U82,'CDV3 DTL'!E:E,1,FALSE)=U82,"OK","Missing") -> #N/A | AE82: =IF(AD82="x",VLOOKUP($U82,DVS!A:A,1,FALSE),"-") -> - | AN82: =IF(AM82="x",VLOOKUP($U82,'Domain ControllerECU'!A:A,1,FALSE),"-") -> - | AQ82: =IF(AP82="x",VLOOKUP($U82,RLT!A:A,1,FALSE),"-") -> - | AT82: =IF(AS82="x",VLOOKUP($U82,ULSECU!A:A,1,FALSE),"-") -> - | AW82: =IF(AV82="x",VLOOKUP($U82,'Radar 7779GHz'!A:A,1,FALSE),"-") -> - | AZ82: =IF(AY82="x",VLOOKUP($U82,LiDAR!A:A,1,FALSE),"-") -> - | BF82: =IF(BE82="x",VLOOKUP($U82,DFC!A:A,1,FALSE),"-") -> - | BH82: x | BI82: =IF(BH82="x",VLOOKUP(U82,'DSF ADSP'!A:A,1,FALSE),"-") -> #N/A | BL82: =IF(BK82="x",VLOOKUP($U82,'DSF LSMS'!$A:$A,1,FALSE),"-") -> -
B83: REG_165 | C83: 80 | D83: low | E83: 10/10: Closed | H83: =VLOOKUP(U83,'CDV3 DTL'!E:G,2,FALSE) -> #N/A | P83: EU | Q83: =HYPERLINK("https://drive.google.com/open?id=1Ij3OXRsCeFyRPADMHyIBhT2gcBg0JsbZ","2014/53/EU_RED") -> 2014/53/EU_RED | S83: 45 | T83: Regulations | U83: 1216_Directive 2014-53-EU | W83: =IF(VLOOKUP(U83,'CDV2 DTL'!P:P,1,FALSE)=U83,"OK","Missing") -> OK | X83: =IF(VLOOKUP(U83,'CDV3 DTL'!E:E,1,FALSE)=U83,"OK","Missing") -> #N/A | AE83: =IF(AD83="x",VLOOKUP($U83,DVS!A:A,1,FALSE),"-") -> - | AN83: =IF(AM83="x",VLOOKUP($U83,'Domain ControllerECU'!A:A,1,FALSE),"-") -> - | AQ83: =IF(AP83="x",VLOOKUP($U83,RLT!A:A,1,FALSE),"-") -> - | AT83: =IF(AS83="x",VLOOKUP($U83,ULSECU!A:A,1,FALSE),"-") -> - | AV83: x | AW83: =IF(AV83="x",VLOOKUP($U83,'Radar 7779GHz'!A:A,1,FALSE),"-") -> #N/A | AZ83: =IF(AY83="x",VLOOKUP($U83,LiDAR!A:A,1,FALSE),"-") -> - | BF83: =IF(BE83="x",VLOOKUP($U83,DFC!A:A,1,FALSE),"-") -> - | BI83: =IF(BH83="x",VLOOKUP(U83,'DSF ADSP'!A:A,1,FALSE),"-") -> - | BL83: =IF(BK83="x",VLOOKUP($U83,'DSF LSMS'!$A:$A,1,FALSE),"-") -> -
